Workbook

Sheet Summary
B2: CBG Sector Summary Dashboard
B5: 1. State-wise Distribution — CBG Plants, Demand & Biomass Surplus (Pie Charts)
B6: State | C6: CBG Plants (Nos.) | D6: Plant Capacity (TPD) | E6: Current CBG Demand (TPD) | F6: Net Biomass Surplus (KTPA)
B7: Uttar Pradesh | C7: =SUMIFS('All States'!$E$4:$E$627,'All States'!$C$4:$C$627,"UP") -> 231 | D7: =SUMIFS('All States'!$F$4:$F$627,'All States'!$C$4:$C$627,"UP") -> 1771.08 | E7: =SUMIFS('All States'!$U$4:$U$627,'All States'!$C$4:$C$627,"UP") -> 114.3785 | F7: =SUMIFS('All States'!$M$4:$M$627,'All States'!$C$4:$C$627,"UP") -> 23156.965
B8: Maharashtra | C8: =SUMIFS('All States'!$E$4:$E$627,'All States'!$C$4:$C$627,"MH") -> 136 | D8: =SUMIFS('All States'!$F$4:$F$627,'All States'!$C$4:$C$627,"MH") -> 33158.331 | E8: =SUMIFS('All States'!$U$4:$U$627,'All States'!$C$4:$C$627,"MH") -> 115.34128 | F8: =SUMIFS('All States'!$M$4:$M$627,'All States'!$C$4:$C$627,"MH") -> 3804.11
B9: Madhya Pradesh | C9: =SUMIFS('All States'!$E$4:$E$627,'All States'!$C$4:$C$627,"MP") -> 98 | D9: =SUMIFS('All States'!$F$4:$F$627,'All States'!$C$4:$C$627,"MP") -> 16771.93 | E9: =SUMIFS('All States'!$U$4:$U$627,'All States'!$C$4:$C$627,"MP") -> 35.876302 | F9: =SUMIFS('All States'!$M$4:$M$627,'All States'!$C$4:$C$627,"MP") -> 17652.81
B10: Gujarat | C10: =SUMIFS('All States'!$E$4:$E$627,'All States'!$C$4:$C$627,"GJ") -> 102 | D10: =SUMIFS('All States'!$F$4:$F$627,'All States'!$C$4:$C$627,"GJ") -> 627.69 | E10: =SUMIFS('All States'!$U$4:$U$627,'All States'!$C$4:$C$627,"GJ") -> 122.57734 | F10: =SUMIFS('All States'!$M$4:$M$627,'All States'!$C$4:$C$627,"GJ") -> 2130.035
B11: Punjab | C11: =SUMIFS('All States'!$E$4:$E$627,'All States'!$C$4:$C$627,"PB") -> 82 | D11: =SUMIFS('All States'!$F$4:$F$627,'All States'!$C$4:$C$627,"PB") -> 1718.259 | E11: =SUMIFS('All States'!$U$4:$U$627,'All States'!$C$4:$C$627,"PB") -> 24.95712 | F11: =SUMIFS('All States'!$M$4:$M$627,'All States'!$C$4:$C$627,"PB") -> 13795.865
B12: Haryana | C12: =SUMIFS('All States'!$E$4:$E$627,'All States'!$C$4:$C$627,"HR") -> 68 | D12: =SUMIFS('All States'!$F$4:$F$627,'All States'!$C$4:$C$627,"HR") -> 525.1 | E12: =SUMIFS('All States'!$U$4:$U$627,'All States'!$C$4:$C$627,"HR") -> 52.515072 | F12: =SUMIFS('All States'!$M$4:$M$627,'All States'!$C$4:$C$627,"HR") -> 6881.1375
B13: Andhra Pradesh | C13: =SUMIFS('All States'!$E$4:$E$627,'All States'!$C$4:$C$627,"AP") -> 61 | D13: =SUMIFS('All States'!$F$4:$F$627,'All States'!$C$4:$C$627,"AP") -> 704.25 | E13: =SUMIFS('All States'!$U$4:$U$627,'All States'!$C$4:$C$627,"AP") -> 20.611828 | F13: =SUMIFS('All States'!$M$4:$M$627,'All States'!$C$4:$C$627,"AP") -> 4371.98
B14: Tamil Nadu | C14: =SUMIFS('All States'!$E$4:$E$627,'All States'!$C$4:$C$627,"TN") -> 53 | D14: =SUMIFS('All States'!$F$4:$F$627,'All States'!$C$4:$C$627,"TN") -> 544.94 | E14: =SUMIFS('All States'!$U$4:$U$627,'All States'!$C$4:$C$627,"TN") -> 40.129321 | F14: =SUMIFS('All States'!$M$4:$M$627,'All States'!$C$4:$C$627,"TN") -> 3933.86
B15: Karnataka | C15: =SUMIFS('All States'!$E$4:$E$627,'All States'!$C$4:$C$627,"KA") -> 37 | D15: =SUMIFS('All States'!$F$4:$F$627,'All States'!$C$4:$C$627,"KA") -> 201.028 | E15: =SUMIFS('All States'!$U$4:$U$627,'All States'!$C$4:$C$627,"KA") -> 45.800448 | F15: =SUMIFS('All States'!$M$4:$M$627,'All States'!$C$4:$C$627,"KA") -> 4502.22
B16: Rajasthan | C16: =SUMIFS('All States'!$E$4:$E$627,'All States'!$C$4:$C$627,"RJ") -> 47 | D16: =SUMIFS('All States'!$F$4:$F$627,'All States'!$C$4:$C$627,"RJ") -> 373.988 | E16: =SUMIFS('All States'!$U$4:$U$627,'All States'!$C$4:$C$627,"RJ") -> 42.829092 | F16: =SUMIFS('All States'!$M$4:$M$627,'All States'!$C$4:$C$627,"RJ") -> 6423.355
B17: Telangana | C17: =SUMIFS('All States'!$E$4:$E$627,'All States'!$C$4:$C$627,"TE") -> 48 | D17: =SUMIFS('All States'!$F$4:$F$627,'All States'!$C$4:$C$627,"TE") -> 456.18 | E17: =SUMIFS('All States'!$U$4:$U$627,'All States'!$C$4:$C$627,"TE") -> 21.346079 | F17: =SUMIFS('All States'!$M$4:$M$627,'All States'!$C$4:$C$627,"TE") -> 8397.135
B18: Bihar | C18: =SUMIFS('All States'!$E$4:$E$627,'All States'!$C$4:$C$627,"BR") -> 35 | D18: =SUMIFS('All States'!$F$4:$F$627,'All States'!$C$4:$C$627,"BR") -> 529.6 | E18: =SUMIFS('All States'!$U$4:$U$627,'All States'!$C$4:$C$627,"BR") -> 21.285847 | F18: =SUMIFS('All States'!$M$4:$M$627,'All States'!$C$4:$C$627,"BR") -> 9592.41
B19: Odisha | C19: =SUMIFS('All States'!$E$4:$E$627,'All States'!$C$4:$C$627,"OD") -> 26 | D19: =SUMIFS('All States'!$F$4:$F$627,'All States'!$C$4:$C$627,"OD") -> 194.6 | E19: =SUMIFS('All States'!$U$4:$U$627,'All States'!$C$4:$C$627,"OD") -> 14.076062 | F19: =SUMIFS('All States'!$M$4:$M$627,'All States'!$C$4:$C$627,"OD") -> 4139.52
B20: Chhattisgarh | C20: =SUMIFS('All States'!$E$4:$E$627,'All States'!$C$4:$C$627,"CG") -> 27 | D20: =SUMIFS('All States'!$F$4:$F$627,'All States'!$C$4:$C$627,"CG") -> 162.7 | E20: =SUMIFS('All States'!$U$4:$U$627,'All States'!$C$4:$C$627,"CG") -> 2.8055752 | F20: =SUMIFS('All States'!$M$4:$M$627,'All States'!$C$4:$C$627,"CG") -> -69.35
B21: Uttarakhand | C21: =SUMIFS('All States'!$E$4:$E$627,'All States'!$C$4:$C$627,"UK") -> 15 | D21: =SUMIFS('All States'!$F$4:$F$627,'All States'!$C$4:$C$627,"UK") -> 2960.32 | E21: =SUMIFS('All States'!$U$4:$U$627,'All States'!$C$4:$C$627,"UK") -> 5.9043379 | F21: =SUMIFS('All States'!$M$4:$M$627,'All States'!$C$4:$C$627,"UK") -> 598.54
B22: West Bengal | C22: =SUMIFS('All States'!$E$4:$E$627,'All States'!$C$4:$C$627,"WB") -> 14 | D22: =SUMIFS('All States'!$F$4:$F$627,'All States'!$C$4:$C$627,"WB") -> 73.9 | E22: =SUMIFS('All States'!$U$4:$U$627,'All States'!$C$4:$C$627,"WB") -> 12.092529 | F22: =SUMIFS('All States'!$M$4:$M$627,'All States'!$C$4:$C$627,"WB") -> -36.5
B23: Jharkhand | C23: =SUMIFS('All States'!$E$4:$E$627,'All States'!$C$4:$C$627,"JH") -> 5 | D23: =SUMIFS('All States'!$F$4:$F$627,'All States'!$C$4:$C$627,"JH") -> 161 | E23: =SUMIFS('All States'!$U$4:$U$627,'All States'!$C$4:$C$627,"JH") -> 14.505604 | F23: =SUMIFS('All States'!$M$4:$M$627,'All States'!$C$4:$C$627,"JH") -> 1727.88
B24: Delhi | C24: =SUMIFS('All States'!$E$4:$E$627,'All States'!$C$4:$C$627,"DL") -> 8 | D24: =SUMIFS('All States'!$F$4:$F$627,'All States'!$C$4:$C$627,"DL") -> 50.3 | E24: =SUMIFS('All States'!$U$4:$U$627,'All States'!$C$4:$C$627,"DL") -> 54.279529 | F24: =SUMIFS('All States'!$M$4:$M$627,'All States'!$C$4:$C$627,"DL") -> 0
B25: Assam | C25: =SUMIFS('All States'!$E$4:$E$627,'All States'!$C$4:$C$627,"AS") -> 6 | D25: =SUMIFS('All States'!$F$4:$F$627,'All States'!$C$4:$C$627,"AS") -> 63.5 | E25: =SUMIFS('All States'!$U$4:$U$627,'All States'!$C$4:$C$627,"AS") -> 3.1972683 | F25: =SUMIFS('All States'!$M$4:$M$627,'All States'!$C$4:$C$627,"AS") -> 2312.685
B26: Kerala | C26: =SUMIFS('All States'!$E$4:$E$627,'All States'!$C$4:$C$627,"KL") -> 5 | D26: =SUMIFS('All States'!$F$4:$F$627,'All States'!$C$4:$C$627,"KL") -> 29.8 | E26: =SUMIFS('All States'!$U$4:$U$627,'All States'!$C$4:$C$627,"KL") -> 20.025327 | F26: =SUMIFS('All States'!$M$4:$M$627,'All States'!$C$4:$C$627,"KL") -> 216.72
B27: Chandigarh | C27: =SUMIFS('All States'!$E$4:$E$627,'All States'!$C$4:$C$627,"CH") -> 1 | D27: =SUMIFS('All States'!$F$4:$F$627,'All States'!$C$4:$C$627,"CH") -> 20 | E27: =SUMIFS('All States'!$U$4:$U$627,'All States'!$C$4:$C$627,"CH") -> 3.1210416 | F27: =SUMIFS('All States'!$M$4:$M$627,'All States'!$C$4:$C$627,"CH") -> 1.35
B28: Goa | C28: =SUMIFS('All States'!$E$4:$E$627,'All States'!$C$4:$C$627,"GA") -> 1 | D28: =SUMIFS('All States'!$F$4:$F$627,'All States'!$C$4:$C$627,"GA") -> 0.5 | E28: =SUMIFS('All States'!$U$4:$U$627,'All States'!$C$4:$C$627,"GA") -> 1.4078541 | F28: =SUMIFS('All States'!$M$4:$M$627,'All States'!$C$4:$C$627,"GA") -> 21.39
B29: Himachal Pradesh | C29: =SUMIFS('All States'!$E$4:$E$627,'All States'!$C$4:$C$627,"HP") -> 5 | D29: =SUMIFS('All States'!$F$4:$F$627,'All States'!$C$4:$C$627,"HP") -> 37.15 | E29: =SUMIFS('All States'!$U$4:$U$627,'All States'!$C$4:$C$627,"HP") -> 2.5497852 | F29: =SUMIFS('All States'!$M$4:$M$627,'All States'!$C$4:$C$627,"HP") -> 717.36
B30: Jammu & Kashmir | C30: =SUMIFS('All States'!$E$4:$E$627,'All States'!$C$4:$C$627,"JK") -> 1 | D30: =SUMIFS('All States'!$F$4:$F$627,'All States'!$C$4:$C$627,"JK") -> 1 | E30: =SUMIFS('All States'!$U$4:$U$627,'All States'!$C$4:$C$627,"JK") -> 0.375 | F30: =SUMIFS('All States'!$M$4:$M$627,'All States'!$C$4:$C$627,"JK") -> 843.645
B31: Source: All States sheet (624 district rows aggregated to 24 states), live SUMIFS. Demand = Current CBG Demand (TPD) at 3% penetration of district CNG offtake plus PNG household demand (Control!B4, B5, B8). Surplus = Total Net Surplus after feedstock used by existing plants (KTPA). Charts are placed to the right of this table.
B34: 2. Top 5 Entities
B35: (a) Top 5 Entities by Number of CBG Plants
B36: Rank | C36: Entity | D36: No. of CBG Plants
B37: 1 | C37: Reliance Industries Limited | D37: =COUNTIF('CBG Plants'!$K$2:$K$1216,$C37&"*") -> 50
B38: 2 | C38: Bio-WMS Private Limited | D38: =COUNTIF('CBG Plants'!$K$2:$K$1216,$C38&"*") -> 13
B39: 3 | C39: Mann Residency Pvt. Ltd. | D39: =COUNTIF('CBG Plants'!$K$2:$K$1216,$C39&"*") -> 13
B40: 4 | C40: EverEnviro Resource Management Private Limited | D40: =COUNTIF('CBG Plants'!$K$2:$K$1216,$C40&"*") -> 11
B41: 5 | C41: IOC GPS RENEWABLES PRIVATE LIMITED | D41: =COUNTIF('CBG Plants'!$K$2:$K$1216,$C41&"*") -> 10
B43: (b) Top 5 Entities by Total Plant Production Capacity (TPD)
B44: Rank | C44: Entity | D44: Total Capacity (TPD)
B45: 1 | C45: Reliance Industries Limited | D45: =SUMIF('CBG Plants'!$K$2:$K$1216,$C45&"*",'CBG Plants'!$AA$2:$AA$1216) -> 1056.2
B46: 2 | C46: ZENECO WASTECX PRIVATE LIMITED | D46: =SUMIF('CBG Plants'!$K$2:$K$1216,$C46&"*",'CBG Plants'!$AA$2:$AA$1216) -> 422
B47: 3 | C47: Municipal Corporation Amritsar | D47: =SUMIF('CBG Plants'!$K$2:$K$1216,$C47&"*",'CBG Plants'!$AA$2:$AA$1216) -> 294
B48: 4 | C48: Coimbatore City Municipal Corporation | D48: =SUMIF('CBG Plants'!$K$2:$K$1216,$C48&"*",'CBG Plants'!$AA$2:$AA$1216) -> 200
B49: 5 | C49: MC Ludhiana | D49: =SUMIF('CBG Plants'!$K$2:$K$1216,$C49&"*",'CBG Plants'!$AA$2:$AA$1216) -> 200
B55: 3. Top 10 Districts to Start a CBG Plant — Ranked by Assured Offtake + Biomass Availability + Gov. Support
B56: Rank | C56: District | D56: State | E56: Composite Score | F56: Current CBG Demand (TPD) | G56: Net Biomass Surplus (KTPA) | H56: Gov. Support | I56: Existing CBG Plants | L56: src row (helper)
B57: 1 | C57: Thane | D57: Maharashtra | E57: =0.4*(F57-MIN('All States'!$U$4:$U$627))/(MAX('All States'!$U$4:$U$627)-MIN('All States'!$U$4:$U$627))+0.35*(G57-MIN('All States'!$M$4:$M$627))/(MAX('All States'!$M$4:$M$627)-MIN('All States'!$M$4:$M$627))+0.25*(H57="High")+0.1*(LEFT(INDEX('All States'!$Z$4:$Z$627,$L57),11)="Operational") -> 0.86006205 | F57: =INDEX('All States'!$U$4:$U$627,$L57) -> 30.464987 | G57: =INDEX('All States'!$M$4:$M$627,$L57) -> 39.06 | H57: =INDEX('All States'!$AK$4:$AK$627,$L57) -> High | I57: =INDEX('All States'!$E$4:$E$627,$L57) -> 3 | L57: =SUMPRODUCT(('All States'!$C$4:$C$627=INDEX(Assumptions!$B$92:$B$115,MATCH($D57,Assumptions!$C$92:$C$115,0)))*('All States'!$D$4:$D$627=$C57)*ROW('All States'!$C$4:$C$627))-3 -> 198
B58: 2 | C58: Ahmedabad | D58: Gujarat | E58: =0.4*(F58-MIN('All States'!$U$4:$U$627))/(MAX('All States'!$U$4:$U$627)-MIN('All States'!$U$4:$U$627))+0.35*(G58-MIN('All States'!$M$4:$M$627))/(MAX('All States'!$M$4:$M$627)-MIN('All States'!$M$4:$M$627))+0.25*(H58="High")+0.1*(LEFT(INDEX('All States'!$Z$4:$Z$627,$L58),11)="Operational") -> 0.73518166 | F58: =INDEX('All States'!$U$4:$U$627,$L58) -> 16.844178 | G58: =INDEX('All States'!$M$4:$M$627,$L58) -> 261.17 | H58: =INDEX('All States'!$AK$4:$AK$627,$L58) -> High | I58: =INDEX('All States'!$E$4:$E$627,$L58) -> 4 | L58: =SUMPRODUCT(('All States'!$C$4:$C$627=INDEX(Assumptions!$B$92:$B$115,MATCH($D58,Assumptions!$C$92:$C$115,0)))*('All States'!$D$4:$D$627=$C58)*ROW('All States'!$C$4:$C$627))-3 -> 34
B59: 3 | C59: Nashik | D59: Maharashtra | E59: =0.4*(F59-MIN('All States'!$U$4:$U$627))/(MAX('All States'!$U$4:$U$627)-MIN('All States'!$U$4:$U$627))+0.35*(G59-MIN('All States'!$M$4:$M$627))/(MAX('All States'!$M$4:$M$627)-MIN('All States'!$M$4:$M$627))+0.25*(H59="High")+0.1*(LEFT(INDEX('All States'!$Z$4:$Z$627,$L59),11)="Operational") -> 0.70971076 | F59: =INDEX('All States'!$U$4:$U$627,$L59) -> 5.4730203 | G59: =INDEX('All States'!$M$4:$M$627,$L59) -> 770.895 | H59: =INDEX('All States'!$AK$4:$AK$627,$L59) -> High | I59: =INDEX('All States'!$E$4:$E$627,$L59) -> 6 | L59: =SUMPRODUCT(('All States'!$C$4:$C$627=INDEX(Assumptions!$B$92:$B$115,MATCH($D59,Assumptions!$C$92:$C$115,0)))*('All States'!$D$4:$D$627=$C59)*ROW('All States'!$C$4:$C$627))-3 -> 188
B60: 4 | C60: Pune | D60: Maharashtra | E60: =0.4*(F60-MIN('All States'!$U$4:$U$627))/(MAX('All States'!$U$4:$U$627)-MIN('All States'!$U$4:$U$627))+0.35*(G60-MIN('All States'!$M$4:$M$627))/(MAX('All States'!$M$4:$M$627)-MIN('All States'!$M$4:$M$627))+0.25*(H60="High")+0.1*(LEFT(INDEX('All States'!$Z$4:$Z$627,$L60),11)="Operational") -> 0.67763344 | F60: =INDEX('All States'!$U$4:$U$627,$L60) -> 24.953372 | G60: =INDEX('All States'!$M$4:$M$627,$L60) -> -413.99 | H60: =INDEX('All States'!$AK$4:$AK$627,$L60) -> High | I60: =INDEX('All States'!$E$4:$E$627,$L60) -> 23 | L60: =SUMPRODUCT(('All States'!$C$4:$C$627=INDEX(Assumptions!$B$92:$B$115,MATCH($D60,Assumptions!$C$92:$C$115,0)))*('All States'!$D$4:$D$627=$C60)*ROW('All States'!$C$4:$C$627))-3 -> 191
B61: 5 | C61: Sirsa | D61: Haryana | E61: =0.4*(F61-MIN('All States'!$U$4:$U$627))/(MAX('All States'!$U$4:$U$627)-MIN('All States'!$U$4:$U$627))+0.35*(G61-MIN('All States'!$M$4:$M$627))/(MAX('All States'!$M$4:$M$627)-MIN('All States'!$M$4:$M$627))+0.25*(H61="High")+0.1*(LEFT(INDEX('All States'!$Z$4:$Z$627,$L61),11)="Operational") -> 0.66727228 | F61: =INDEX('All States'!$U$4:$U$627,$L61) -> 1.2171453 | G61: =INDEX('All States'!$M$4:$M$627,$L61) -> 826.22 | H61: =INDEX('All States'!$AK$4:$AK$627,$L61) -> High | I61: =INDEX('All States'!$E$4:$E$627,$L61) -> 6 | L61: =SUMPRODUCT(('All States'!$C$4:$C$627=INDEX(Assumptions!$B$92:$B$115,MATCH($D61,Assumptions!$C$92:$C$115,0)))*('All States'!$D$4:$D$627=$C61)*ROW('All States'!$C$4:$C$627))-3 -> 285
B62: 6 | C62: Valsad | D62: Gujarat | E62: =0.4*(F62-MIN('All States'!$U$4:$U$627))/(MAX('All States'!$U$4:$U$627)-MIN('All States'!$U$4:$U$627))+0.35*(G62-MIN('All States'!$M$4:$M$627))/(MAX('All States'!$M$4:$M$627)-MIN('All States'!$M$4:$M$627))+0.25*(H62="High")+0.1*(LEFT(INDEX('All States'!$Z$4:$Z$627,$L62),11)="Operational") -> 0.66089061 | F62: =INDEX('All States'!$U$4:$U$627,$L62) -> 14.549574 | G62: =INDEX('All States'!$M$4:$M$627,$L62) -> 79.38 | H62: =INDEX('All States'!$AK$4:$AK$627,$L62) -> High | I62: =INDEX('All States'!$E$4:$E$627,$L62) -> 0 | L62: =SUMPRODUCT(('All States'!$C$4:$C$627=INDEX(Assumptions!$B$92:$B$115,MATCH($D62,Assumptions!$C$92:$C$115,0)))*('All States'!$D$4:$D$627=$C62)*ROW('All States'!$C$4:$C$627))-3 -> 66
B63: 7 | C63: Rajkot | D63: Gujarat | E63: =0.4*(F63-MIN('All States'!$U$4:$U$627))/(MAX('All States'!$U$4:$U$627)-MIN('All States'!$U$4:$U$627))+0.35*(G63-MIN('All States'!$M$4:$M$627))/(MAX('All States'!$M$4:$M$627)-MIN('All States'!$M$4:$M$627))+0.25*(H63="High")+0.1*(LEFT(INDEX('All States'!$Z$4:$Z$627,$L63),11)="Operational") -> 0.64511993 | F63: =INDEX('All States'!$U$4:$U$627,$L63) -> 11.528341 | G63: =INDEX('All States'!$M$4:$M$627,$L63) -> 177.75 | H63: =INDEX('All States'!$AK$4:$AK$627,$L63) -> High | I63: =INDEX('All States'!$E$4:$E$627,$L63) -> 2 | L63: =SUMPRODUCT(('All States'!$C$4:$C$627=INDEX(Assumptions!$B$92:$B$115,MATCH($D63,Assumptions!$C$92:$C$115,0)))*('All States'!$D$4:$D$627=$C63)*ROW('All States'!$C$4:$C$627))-3 -> 60
B64: 8 | C64: Jind | D64: Haryana | E64: =0.4*(F64-MIN('All States'!$U$4:$U$627))/(MAX('All States'!$U$4:$U$627)-MIN('All States'!$U$4:$U$627))+0.35*(G64-MIN('All States'!$M$4:$M$627))/(MAX('All States'!$M$4:$M$627)-MIN('All States'!$M$4:$M$627))+0.25*(H64="High")+0.1*(LEFT(INDEX('All States'!$Z$4:$Z$627,$L64),11)="Operational") -> 0.64363928 | F64: =INDEX('All States'!$U$4:$U$627,$L64) -> 2.0258775 | G64: =INDEX('All States'!$M$4:$M$627,$L64) -> 685.23 | H64: =INDEX('All States'!$AK$4:$AK$627,$L64) -> High | I64: =INDEX('All States'!$E$4:$E$627,$L64) -> 9 | L64: =SUMPRODUCT(('All States'!$C$4:$C$627=INDEX(Assumptions!$B$92:$B$115,MATCH($D64,Assumptions!$C$92:$C$115,0)))*('All States'!$D$4:$D$627=$C64)*ROW('All States'!$C$4:$C$627))-3 -> 274
B65: 9 | C65: Hardoi | D65: Uttar Pradesh | E65: =0.4*(F65-MIN('All States'!$U$4:$U$627))/(MAX('All States'!$U$4:$U$627)-MIN('All States'!$U$4:$U$627))+0.35*(G65-MIN('All States'!$M$4:$M$627))/(MAX('All States'!$M$4:$M$627)-MIN('All States'!$M$4:$M$627))+0.25*(H65="High")+0.1*(LEFT(INDEX('All States'!$Z$4:$Z$627,$L65),11)="Operational") -> 0.63337461 | F65: =INDEX('All States'!$U$4:$U$627,$L65) -> 1.6397723 | G65: =INDEX('All States'!$M$4:$M$627,$L65) -> 663.845 | H65: =INDEX('All States'!$AK$4:$AK$627,$L65) -> High | I65: =INDEX('All States'!$E$4:$E$627,$L65) -> 2 | L65: =SUMPRODUCT(('All States'!$C$4:$C$627=INDEX(Assumptions!$B$92:$B$115,MATCH($D65,Assumptions!$C$92:$C$115,0)))*('All States'!$D$4:$D$627=$C65)*ROW('All States'!$C$4:$C$627))-3 -> 128
B66: 10 | C66: Shahjahanpur | D66: Uttar Pradesh | E66: =0.4*(F66-MIN('All States'!$U$4:$U$627))/(MAX('All States'!$U$4:$U$627)-MIN('All States'!$U$4:$U$627))+0.35*(G66-MIN('All States'!$M$4:$M$627))/(MAX('All States'!$M$4:$M$627)-MIN('All States'!$M$4:$M$627))+0.25*(H66="High")+0.1*(LEFT(INDEX('All States'!$Z$4:$Z$627,$L66),11)="Operational") -> 0.63291081 | F66: =INDEX('All States'!$U$4:$U$627,$L66) -> 1.8294396 | G66: =INDEX('All States'!$M$4:$M$627,$L66) -> 651.685 | H66: =INDEX('All States'!$AK$4:$AK$627,$L66) -> High | I66: =INDEX('All States'!$E$4:$E$627,$L66) -> 2 | L66: =SUMPRODUCT(('All States'!$C$4:$C$627=INDEX(Assumptions!$B$92:$B$115,MATCH($D66,Assumptions!$C$92:$C$115,0)))*('All States'!$D$4:$D$627=$C66)*ROW('All States'!$C$4:$C$627))-3 -> 159
B68: Methodology: Composite Score = 0.40 x Offtake (Current CBG Demand TPD, min-max normalised across all 624 districts) + 0.35 x Biomass (Net Surplus KTPA, min-max normalised) + 0.25 x Gov. Support flag (High=1, Low=0) + 0.10 bonus if the district sits on an Operational (vs. Partially Commissioned / Under Construction) common-carrier gas pipeline. Score and all metric columns are live formulas against the All States sheet; column L holds the helper row index. Rank order is fixed at the time of this update - re-sort if the underlying data or the Control assumptions change. "Assured offtake" is proxied by existing CGD/CNG+PNG demand in the district since the source data has no direct offtake-contract field - treat as a screening shortlist, not a substitute for site-level due diligence.
B71: 4. Top 10 Geographical Areas (GAs) to Start a CBG Plant — Same Ranking Basis
B72: Rank | C72: Geographical Area (GA) | D72: State | E72: GAID | F72: Authorised CGD Entity | G72: Composite Score | H72: Current CBG Demand (TPD) | I72: Net Biomass Surplus (KTPA) | J72: Gov. Support | L72: src row (helper)
B73: 1 | C73: Lakhimpur Kheri, Sitapur, Bahraich, Shrawasti, Balrampur, Siddharth Nagar & Maharajganj districts | D73: Uttar Pradesh | E73: 11A.01 | F73: Bharat Petroleum Corporation Limited | G73: =0.4*(H73-MIN(GAs!$X$4:$X$320))/(MAX(GAs!$X$4:$X$320)-MIN(GAs!$X$4:$X$320))+0.35*(I73-MIN(GAs!$P$4:$P$320))/(MAX(GAs!$P$4:$P$320)-MIN(GAs!$P$4:$P$320))+0.25*(J73="High")+0.1*(LEFT(INDEX(GAs!$AC$4:$AC$320,$L73),11)="Operational") -> 0.79175268 | H73: =INDEX(GAs!$X$4:$X$320,$L73) -> 12.450731 | I73: =INDEX(GAs!$P$4:$P$320,$L73) -> 3352.44 | J73: =INDEX(GAs!$AO$4:$AO$320,$L73) -> High | L73: =MATCH($E73,GAs!$D$4:$D$320,0) -> 275
B74: 2 | C74: Valsad (EAAA), Dhule & Nashik Districts | D74: Maharashtra & Gujarat | E74: 9.39 | F74: Maharashtra Natural Gas Limited | G74: =0.4*(H74-MIN(GAs!$X$4:$X$320))/(MAX(GAs!$X$4:$X$320)-MIN(GAs!$X$4:$X$320))+0.35*(I74-MIN(GAs!$P$4:$P$320))/(MAX(GAs!$P$4:$P$320)-MIN(GAs!$P$4:$P$320))+0.25*(J74="High")+0.1*(LEFT(INDEX(GAs!$AC$4:$AC$320,$L74),11)="Operational") -> 0.66511745 | H74: =INDEX(GAs!$X$4:$X$320,$L74) -> 25.495615 | I74: =INDEX(GAs!$P$4:$P$320,$L74) -> 955.2 | J74: =INDEX(GAs!$AO$4:$AO$320,$L74) -> High | L74: =MATCH($E74,GAs!$D$4:$D$320,0) -> 304
B75: 3 | C75: Palghar District & Thane Rural | D75: Maharashtra | E75: 4.03 | F75: Gujarat Gas Limited | G75: =0.4*(H75-MIN(GAs!$X$4:$X$320))/(MAX(GAs!$X$4:$X$320)-MIN(GAs!$X$4:$X$320))+0.35*(I75-MIN(GAs!$P$4:$P$320))/(MAX(GAs!$P$4:$P$320)-MIN(GAs!$P$4:$P$320))+0.25*(J75="High")+0.1*(LEFT(INDEX(GAs!$AC$4:$AC$320,$L75),11)="Operational") -> 0.63700898 | H75: =INDEX(GAs!$X$4:$X$320,$L75) -> 32.206371 | I75: =INDEX(GAs!$P$4:$P$320,$L75) -> 120.54 | J75: =INDEX(GAs!$AO$4:$AO$320,$L75) -> High | L75: =MATCH($E75,GAs!$D$4:$D$320,0) -> 245
B76: 4 | C76: Sirsa, Fatehabad and Mansa (Punjab) Districts | D76: Haryana and Punjab | E76: 10.12 | F76: Gujarat Gas Limited | G76: =0.4*(H76-MIN(GAs!$X$4:$X$320))/(MAX(GAs!$X$4:$X$320)-MIN(GAs!$X$4:$X$320))+0.35*(I76-MIN(GAs!$P$4:$P$320))/(MAX(GAs!$P$4:$P$320)-MIN(GAs!$P$4:$P$320))+0.25*(J76="High")+0.1*(LEFT(INDEX(GAs!$AC$4:$AC$320,$L76),11)="Operational") -> 0.62586034 | H76: =INDEX(GAs!$X$4:$X$320,$L76) -> 4.7935712 | I76: =INDEX(GAs!$P$4:$P$320,$L76) -> 2174.465 | J76: =INDEX(GAs!$AO$4:$AO$320,$L76) -> High | L76: =MATCH($E76,GAs!$D$4:$D$320,0) -> 270
B77: 5 | C77: Thane urban and adjoining Municipalities | D77: Maharashtra | E77: 99.07 | F77: Mahanagar Gas Limited | G77: =0.4*(H77-MIN(GAs!$X$4:$X$320))/(MAX(GAs!$X$4:$X$320)-MIN(GAs!$X$4:$X$320))+0.35*(I77-MIN(GAs!$P$4:$P$320))/(MAX(GAs!$P$4:$P$320)-MIN(GAs!$P$4:$P$320))+0.25*(J77="High")+0.1*(LEFT(INDEX(GAs!$AC$4:$AC$320,$L77),11)="Operational") -> 0.61660464 | H77: =INDEX(GAs!$X$4:$X$320,$L77) -> 30.464987 | I77: =INDEX(GAs!$P$4:$P$320,$L77) -> 39.06 | J77: =INDEX(GAs!$AO$4:$AO$320,$L77) -> High | L77: =MATCH($E77,GAs!$D$4:$D$320,0) -> 237
B78: 6 | C78: Pune City including Pimpri - Chinchwad & adjoining contiguous areas Hinjewadi, Chakan, Talegaon | D78: Maharashtra | E78: 99.05 | F78: Maharashtra Natural Gas Limited | G78: =0.4*(H78-MIN(GAs!$X$4:$X$320))/(MAX(GAs!$X$4:$X$320)-MIN(GAs!$X$4:$X$320))+0.35*(I78-MIN(GAs!$P$4:$P$320))/(MAX(GAs!$P$4:$P$320)-MIN(GAs!$P$4:$P$320))+0.25*(J78="High")+0.1*(LEFT(INDEX(GAs!$AC$4:$AC$320,$L78),11)="Operational") -> 0.59324451 | H78: =INDEX(GAs!$X$4:$X$320,$L78) -> 24.953372 | I78: =INDEX(GAs!$P$4:$P$320,$L78) -> 224.76 | J78: =INDEX(GAs!$AO$4:$AO$320,$L78) -> High | L78: =MATCH($E78,GAs!$D$4:$D$320,0) -> 302
B79: 7 | C79: Bareilly (EAAA) District, Pilibhit and Rampur Districts | D79: Uttar Pradesh | E79: 10.37 | F79: Hindustan Petroleum Corporation Limited | G79: =0.4*(H79-MIN(GAs!$X$4:$X$320))/(MAX(GAs!$X$4:$X$320)-MIN(GAs!$X$4:$X$320))+0.35*(I79-MIN(GAs!$P$4:$P$320))/(MAX(GAs!$P$4:$P$320)-MIN(GAs!$P$4:$P$320))+0.25*(J79="High")+0.1*(LEFT(INDEX(GAs!$AC$4:$AC$320,$L79),11)="Operational") -> 0.56717299 | H79: =INDEX(GAs!$X$4:$X$320,$L79) -> 9.0922735 | I79: =INDEX(GAs!$P$4:$P$320,$L79) -> 1202.02 | J79: =INDEX(GAs!$AO$4:$AO$320,$L79) -> High | L79: =MATCH($E79,GAs!$D$4:$D$320,0) -> 286
B80: 8 | C80: Farrukhabad, Etah and Hardoi Districts | D80: Uttar Pradesh | E80: 10.39 | F80: Hindustan Petroleum Corporation Limited | G80: =0.4*(H80-MIN(GAs!$X$4:$X$320))/(MAX(GAs!$X$4:$X$320)-MIN(GAs!$X$4:$X$320))+0.35*(I80-MIN(GAs!$P$4:$P$320))/(MAX(GAs!$P$4:$P$320)-MIN(GAs!$P$4:$P$320))+0.25*(J80="High")+0.1*(LEFT(INDEX(GAs!$AC$4:$AC$320,$L80),11)="Operational") -> 0.5510777 | H80: =INDEX(GAs!$X$4:$X$320,$L80) -> 4.9193167 | I80: =INDEX(GAs!$P$4:$P$320,$L80) -> 1359.74 | J80: =INDEX(GAs!$AO$4:$AO$320,$L80) -> High | L80: =MATCH($E80,GAs!$D$4:$D$320,0) -> 123
B81: 9 | C81: Jhansi (EAAA) District, Bhind, Jalaun, Lalitpur and Datia Districts | D81: Madhya Pradesh and Uttar Pradesh | E81: 10.31 | F81: Adani Total Gas Limited | G81: =0.4*(H81-MIN(GAs!$X$4:$X$320))/(MAX(GAs!$X$4:$X$320)-MIN(GAs!$X$4:$X$320))+0.35*(I81-MIN(GAs!$P$4:$P$320))/(MAX(GAs!$P$4:$P$320)-MIN(GAs!$P$4:$P$320))+0.25*(J81="High")+0.1*(LEFT(INDEX(GAs!$AC$4:$AC$320,$L81),11)="Operational") -> 0.54588863 | H81: =INDEX(GAs!$X$4:$X$320,$L81) -> 3.3022035 | I81: =INDEX(GAs!$P$4:$P$320,$L81) -> 1432.14 | J81: =INDEX(GAs!$AO$4:$AO$320,$L81) -> High | L81: =MATCH($E81,GAs!$D$4:$D$320,0) -> 209
B82: 10 | C82: Ahmednagar & Aurangabad Districts | D82: Maharashtra | E82: 9.38 | F82: Bharat Petroleum Corporation Limited | G82: =0.4*(H82-MIN(GAs!$X$4:$X$320))/(MAX(GAs!$X$4:$X$320)-MIN(GAs!$X$4:$X$320))+0.35*(I82-MIN(GAs!$P$4:$P$320))/(MAX(GAs!$P$4:$P$320)-MIN(GAs!$P$4:$P$320))+0.25*(J82="High")+0.1*(LEFT(INDEX(GAs!$AC$4:$AC$320,$L82),11)="Operational") -> 0.54512785 | H82: =INDEX(GAs!$X$4:$X$320,$L82) -> 11.258632 | I82: =INDEX(GAs!$P$4:$P$320,$L82) -> 792.99 | J82: =INDEX(GAs!$AO$4:$AO$320,$L82) -> High | L82: =MATCH($E82,GAs!$D$4:$D$320,0) -> 278
B84: Source: GAs sheet (309 authorised City Gas Distribution geographical areas), live INDEX/MATCH on GAID. Same weighted-score methodology as Section 3, applied at GA level and normalised across the 309 GAs (a GA can span multiple districts, so results differ from the district ranking). GAID is the PNGRB geographical-area identifier; column L holds the helper row index.

Sheet Control
B3: Parameters | C3: UoM | H3: Napier Grass | I3: Maize Stover | J3: Paddy Straw | K3: Cane Trash | L3: Press Mud | M3: OF MSW | N3: Thick Slop | O3: Soya Trash
B4: Net CBG Demand | C4: TPD | D4: 3 | G4: Yeild | H4: 0.04089164 | I4: 0.10008581 | J4: 0.12470724 | K4: 0.1063785 | L4: 0.040390117 | M4: 0.038243549 | N4: 0.039213706 | O4: 0.10743667
B5: Net Biomass Surplus | C5: KTPA | D5: 50 | G5: Moisture | H5: 0.75 | I5: 0.15 | J5: 0.2 | K5: 0.12 | L5: 0.7 | M5: 0.75 | N5: 0.8 | O5: 0.2
B6: Straws (PS, CT, MS) | C6: % | E6: =SUM(J7,K7,I7) -> 0 | G6: ODM | H6: 0.25 | I6: 0.85 | J6: 0.8 | K6: 0.88 | L6: 0.3 | M6: 0.25 | N6: 0.2 | O6: 0.8
B7: Industrials (PM, OFMSW, TS) | C7: % | E7: =SUM(L7,M7,N7) -> 0 | G7: RM Blend
B8: Energy Crops | C8: % | E8: =SUM(H7) -> 0
B9: Net Est Demand 5Y | D9: 10
B10: Nearest Pipeline | C10: km | D10: 3000
B11: Distance from large city | C11: km | D11: 0

Sheet Top District
B2: Sr. | C2: State | D2: District | E2: Net CBG Demand (TPD) | F2: Raw Material (KTPA) | G2: Nearest Pipeline (km) | H2: Distance from Large city | I2: Est Net CBG Demand - 5Y
B3: 1 | C3: {=_xlfn._xlws.FILTER('All States (2)'!C4:C1000,('All States (2)'!AE4:AE1000="Y")*('All States (2)'!AF4:AF1000="Y")*('All States (2)'!AG4:AG1000="Y"),"No matching data")} -> GJ | D3: {=_xlfn._xlws.FILTER('All States (2)'!D4:D1000,('All States (2)'!AE4:AE1000="Y")*('All States (2)'!AF4:AF1000="Y")*('All States (2)'!AG4:AG1000="Y"),"No matching data")} -> Gandhinagar | E3: {=_xlfn._xlws.FILTER('All States (2)'!R4:R1000,('All States (2)'!AE4:AE1000="Y")*('All States (2)'!AF4:AF1000="Y")*('All States (2)'!AG4:AG1000="Y"),"No matching data")} -> 3.8257156 | F3: {=_xlfn._xlws.FILTER('All States (2)'!M4:M1000,('All States (2)'!AE4:AE1000="Y")*('All States (2)'!AF4:AF1000="Y")*('All States (2)'!AG4:AG1000="Y"),"No matching data")} -> 51.81 | G3: {=_xlfn._xlws.FILTER('All States (2)'!AB4:AB1000,('All States (2)'!AE4:AE1000="Y")*('All States (2)'!AF4:AF1000="Y")*('All States (2)'!AG4:AG1000="Y"),"No matching data")} -> 9.8 | I3: {=_xlfn._xlws.FILTER('All States (2)'!X4:X1000,('All States (2)'!AE4:AE1000="Y")*('All States (2)'!AF4:AF1000="Y")*('All States (2)'!AG4:AG1000="Y"),"No matching data")} -> 31.7774
B4: 2 | C4: GJ | D4: Mahesana | E4: 6.8257156 | F4: 96.255 | G4: 9.8 | I4: 34.7774
B5: 3 | C5: GJ | D5: Rajkot | E5: 4.4283409 | F5: 177.75 | G5: 189.3 | I5: 51.5336
B6: 4 | C6: GJ | D6: Valsad | E6: 14.549574 | F6: 79.38 | G6: 134.2 | I6: 73.9657
B7: 5 | C7: MH | D7: Ahilyanagar | E7: 5.6293159 | F7: 358.665 | G7: 84.4 | I7: 28.5931
B8: 6 | C8: MH | D8: Chhatrapati Sambhajinagar | E8: 5.6293159 | F8: 434.325 | G8: 189.2 | I8: 28.5931
B9: 7 | C9: HR | D9: Faridabad | E9: 4.4662171 | F9: 59.295 | G9: 48.3 | I9: 22.7334
B10: 8 | C10: HR | D10: Gurugram | E10: 4.8764329 | F10: 63.1925 | G10: 13.5 | I10: 37.9087
B11: 9 | C11: HR | D11: Rewari | E11: 3.6887038 | F11: 68.16 | G11: 28.2 | I11: 18.7271
B12: 10 | C12: TN | D12: Thiruvallur | E12: 3.3277882 | F12: 109.34 | G12: 40.4 | I12: 16.8913
B13: 11
B14: 12
B15: 13
B16: 14
B17: 15
B18: 16
B19: 17
B20: 18
B21: 19
B22: 20
B23: 21
B24: 22
... B59: 57

Sheet Top GAs
B2: GA ID | C2: State | D2: Districts | E2: Current Net CBG Demand in GA (TPD) | F2: Raw Material (KTPA) | G2: Pipeline Availability (km) | H2: Distance from Large city | I2: Est Net CBG Demand - 5Y
B3: {=_xlfn._xlws.FILTER( GAs!D4:D1000, (GAs!AH4:AH1000="Y")* (GAs!AI4:AI1000="Y")* (GAs!AJ4:AJ1000="Y"), "No matching data" )} -> 98.10 | C3: {=_xlfn._xlws.FILTER( GAs!C4:C1000, (GAs!AH4:AH1000="Y")* (GAs!AI4:AI1000="Y")* (GAs!AJ4:AJ1000="Y"), "No matching data" )} -> Gujarat | D3: {=_xlfn._xlws.FILTER( GAs!E4:E1000, (GAs!AH4:AH1000="Y")* (GAs!AI4:AI1000="Y")* (GAs!AJ4:AJ1000="Y"), "No matching data" )} -> Valsad | E3: {=_xlfn._xlws.FILTER( GAs!U4:U1000, (GAs!AH4:AH1000="Y")* (GAs!AI4:AI1000="Y")* (GAs!AJ4:AJ1000="Y"), "No matching data" )} -> 14.549574 | F3: {=_xlfn._xlws.FILTER( GAs!P4:P1000, (GAs!AH4:AH1000="Y")* (GAs!AI4:AI1000="Y")* (GAs!AJ4:AJ1000="Y"), "No matching data" )} -> 79.38 | G3: {=_xlfn._xlws.FILTER( GAs!AJ4:AJ1000, (GAs!AH4:AH1000="Y")* (GAs!AI4:AI1000="Y")* (GAs!AJ4:AJ1000="Y"), "No matching data" )} -> Y | I3: {=_xlfn._xlws.FILTER( GAs!AA4:AA1000, (GAs!AH4:AH1000="Y")* (GAs!AI4:AI1000="Y")* (GAs!AJ4:AJ1000="Y"), "No matching data" )} -> 71.388755
B4: 95.03 | C4: Haryana | D4: Gurugram-1 | E4: 4.8764329 | F4: 63.1925 | G4: Y | I4: 39.525597
B5: 98.13 | C5: Haryana | D5: Gurugram-2 | E5: 4.8764329 | F5: 63.1925 | G5: Y | I5: 39.525597
B6: 95.01 | C6: Haryana | D6: Faridabad-2 | E6: 4.4662171 | F6: 59.295 | G6: Y | I6: 21.350597
B7: 95.02 | C7: Haryana | D7: Faridabad-1 | E7: 4.4662171 | F7: 59.295 | G7: Y | I7: 21.350597
B8: 98.06 | C8: Gujarat | D8: Rajkot | E8: 4.4283409 | F8: 177.75 | G8: Y | I8: 51.533613
B9: 6.15 | C9: Haryana | D9: Rewari District | E9: 3.6887038 | F9: 68.16 | G9: Y | I9: 16.899109
B10: 9.26 | C10: Karnataka | D10: Ballari & Gadag Districts | E10: 3.6433884 | F10: 485.85 | G10: Y | I10: 17.651988
B11: 99.05 | C11: Maharashtra | D11: Pune City including Pimpri - Chinchwad & adjoining contiguous areas Hinjewadi, Chakan, Talegaon | E11: 19.753372 | F11: 224.76 | G11: Y | I11: 77.765568
B12: 9.39 | C12: Maharashtra & Gujarat | D12: Valsad (EAAA), Dhule & Nashik Districts | E12: 13.495615 | F12: 955.2 | G12: Y | I12: 118.59969

Sheet All States (2)
E2: Competition | M2: Crop Surplus | R2: CGD Demand | Z2: Pipeline
B3: Sr | C3: State | D3: District | E3: CBG Plant Nos. | F3: Total CBG Plant Capacity (TPD) | G3: Functional & Completed (Nos) | H3: Under Construction (Nos.) | I3: Yet to Start (Nos.) | J3: P1 | K3: P2 | L3: P3 | M3: Total Net Surplus (KTPA) | N3: Total Gross Surplus (KTPA) | O3: Whaet Surplus | P3: Rice Surplus | Q3: Maize Surplus | R3: Net TPD CBG | S3: Gross TPD CNG | T3: Current CNG Stations | U3: Current CBG Demand @ 3% (TPD) | V3: Current PNG HH | W3: Est. 5Y CNG Stations | X3: Future Net CBG Demand @ 5% (TPD) | Y3: Est. 5Y PNG HH | Z3: Type | AA3: Name of Pipeline | AB3: Distance to Pipeline Route (Km, approx.) | AC3: MMSCMD Capacity | AD3: Feedstock Used by Existing Plants (TPD) | AE3: Demand | AF3: Raw Material | AG3: Nearest Pipeline | AH3: Distance from Large city | AI3: Est Net CBG Demand - 5Y | AK3: Gov Support
B4: 4 | C4: TE | D4: Hyderabad | E4: =SUM(G4:I4) -> 2 | F4: =SUMIFS('CBG Plants'!N:N,'CBG Plants'!F:F,D4,'CBG Plants'!L:L,"Completed") +SUMIFS('CBG Plants'!N:N,'CBG Plants'!F:F,D4,'CBG Plants'!L:L,"Functional")+SUMIFS('CBG Plants'!N:N,'CBG Plants'!F:F,D4,'CBG Plants'!L:L,"Under Construction")+SUMIFS('CBG Plants'!N:N,'CBG Plants'!F:F,D4,'CBG Plants'!L:L,"Yet to start construction") -> 5 | G4: =COUNTIFS('CBG Plants'!F:F,D4,'CBG Plants'!L:L,"Completed") +COUNTIFS('CBG Plants'!F:F,D4,'CBG Plants'!L:L,"Functional") -> 2 | H4: =COUNTIFS('CBG Plants'!F:F,D4,'CBG Plants'!L:L,"Under Construction") -> 0 | I4: =COUNTIFS('CBG Plants'!F:F,D4,'CBG Plants'!L:L,"Yet to start construction") -> 0 | J4: AMBERPET -HYDERABAD | K4: NAGOLE -HYDERDABAD | M4: =IFERROR(N4-(AD4*365/1000),"") -> 0 | N4: =SUM(O4:Q4) -> 0 | R4: =IFERROR(U4-F4,"") -> 4.7826125 | S4: =IFERROR(T4*Assumptions!$C$4,"") -> 245 | T4: 98 | U4: =IFERROR(S4*Assumptions!$C$5,"")+IFERROR(V4*Assumptions!$C$8*Assumptions!$C$5,"") -> 9.7826125 | V4: 242051 | W4: =IFERROR(ROUND(T4*(1+Assumptions!$C$7)^5,0),"") -> 299 | X4: =IFERROR(ROUND(W4*Assumptions!$C$4*Assumptions!$C$6,4),"")+IFERROR(ROUND(Y4*Assumptions!$C$8*Assumptions!$C$6,4),"") - F4 -> 44.7479 | Y4: =IFERROR(ROUND(V4*(1+Assumptions!$C$7)^5,0),"") -> 738681 | Z4: Operational Common Carrier | AA4: Kakinada-Hyderabad-Uran-Ahmedabad (East West Pipeline) | AB4: 0.6 | AC4: 85 | AD4: 0 | AE4: =IF(R4="","",IF(R4>=Control!$D$4,"Y","N")) -> Y | AF4: =IF(S4="","",IF(M4>=Control!$D$5,"Y","N")) -> N | AG4: =IF(T4="","",IF(AB4<=Control!$D$10,"Y","N")) -> Y | AI4: =IF(X4="","",IF(X4>=Control!$D$9,"Y","N")) -> Y | AK4: =IFERROR(INDEX(Assumptions!$D$92:$D$115,MATCH(C4,Assumptions!$B$92:$B$115,0)),"Low") -> Low
B5: 29 | C5: TE | D5: Suryapet | E5: =SUM(G5:I5) -> 1 | F5: =SUMIFS('CBG Plants'!N:N,'CBG Plants'!F:F,D5,'CBG Plants'!L:L,"Completed") +SUMIFS('CBG Plants'!N:N,'CBG Plants'!F:F,D5,'CBG Plants'!L:L,"Functional")+SUMIFS('CBG Plants'!N:N,'CBG Plants'!F:F,D5,'CBG Plants'!L:L,"Under Construction")+SUMIFS('CBG Plants'!N:N,'CBG Plants'!F:F,D5,'CBG Plants'!L:L,"Yet to start construction") -> 0 | G5: =COUNTIFS('CBG Plants'!F:F,D5,'CBG Plants'!L:L,"Completed") +COUNTIFS('CBG Plants'!F:F,D5,'CBG Plants'!L:L,"Functional") -> 0 | H5: =COUNTIFS('CBG Plants'!F:F,D5,'CBG Plants'!L:L,"Under Construction") -> 0 | I5: =COUNTIFS('CBG Plants'!F:F,D5,'CBG Plants'!L:L,"Yet to start construction") -> 1 | J5: SAMYUKTHA POWER PRIVATE LIMITED | M5: =IFERROR(N5-(AD5*365/1000),"") -> 557.34 | N5: =SUM(O5:Q5) -> 557.34 | O5: 0 | P5: 555.24 | Q5: 2.1 | R5: =IFERROR(U5-F5,"") -> 0.54627585 | S5: =IFERROR(T5*Assumptions!$C$4,"") -> 17.5 | T5: 7 | U5: =IFERROR(S5*Assumptions!$C$5,"")+IFERROR(V5*Assumptions!$C$8*Assumptions!$C$5,"") -> 0.54627585 | V5: 2117 | W5: =IFERROR(ROUND(T5*(1+Assumptions!$C$7)^5,0),"") -> 21 | X5: =IFERROR(ROUND(W5*Assumptions!$C$4*Assumptions!$C$6,4),"")+IFERROR(ROUND(Y5*Assumptions!$C$8*Assumptions!$C$6,4),"") - F5 -> 2.7332 | Y5: =IFERROR(ROUND(V5*(1+Assumptions!$C$7)^5,0),"") -> 6461 | Z5: Operational Common Carrier | AA5: Kakinada-Hyderabad-Uran-Ahmedabad (East West Pipeline) | AB5: 18.8 | AC5: 85 | AD5: 0 | AE5: =IF(R5="","",IF(R5>=Control!$D$4,"Y","N")) -> N | AF5: =IF(S5="","",IF(M5>=Control!$D$5,"Y","N")) -> Y | AG5: =IF(T5="","",IF(AB5<=Control!$D$10,"Y","N")) -> Y | AI5: =IF(X5="","",IF(X5>=Control!$D$9,"Y","N")) -> N | AK5: =IFERROR(INDEX(Assumptions!$D$92:$D$115,MATCH(C5,Assumptions!$B$92:$B$115,0)),"Low") -> Low
B6: 2 | C6: TE | D6: Bhadradri Kothagudem | E6: =SUM(G6:I6) -> 0 | F6: =SUMIFS('CBG Plants'!N:N,'CBG Plants'!F:F,D6,'CBG Plants'!L:L,"Completed") +SUMIFS('CBG Plants'!N:N,'CBG Plants'!F:F,D6,'CBG Plants'!L:L,"Functional")+SUMIFS('CBG Plants'!N:N,'CBG Plants'!F:F,D6,'CBG Plants'!L:L,"Under Construction")+SUMIFS('CBG Plants'!N:N,'CBG Plants'!F:F,D6,'CBG Plants'!L:L,"Yet to start construction") -> 0 | G6: =COUNTIFS('CBG Plants'!F:F,D6,'CBG Plants'!L:L,"Completed") +COUNTIFS('CBG Plants'!F:F,D6,'CBG Plants'!L:L,"Functional") -> 0 | H6: =COUNTIFS('CBG Plants'!F:F,D6,'CBG Plants'!L:L,"Under Construction") -> 0 | I6: =COUNTIFS('CBG Plants'!F:F,D6,'CBG Plants'!L:L,"Yet to start construction") -> 0 | M6: =IFERROR(N6-(AD6*365/1000),"") -> 228.06 | N6: =SUM(O6:Q6) -> 228.06 | O6: 0 | P6: 131.46 | Q6: 96.6 | R6: =IFERROR(U6-F6,"") -> 0.5361354 | S6: =IFERROR(T6*Assumptions!$C$4,"") -> 17.5 | T6: 7 | U6: =IFERROR(S6*Assumptions!$C$5,"")+IFERROR(V6*Assumptions!$C$8*Assumptions!$C$5,"") -> 0.5361354 | V6: 1108 | W6: =IFERROR(ROUND(T6*(1+Assumptions!$C$7)^5,0),"") -> 21 | X6: =IFERROR(ROUND(W6*Assumptions!$C$4*Assumptions!$C$6,4),"")+IFERROR(ROUND(Y6*Assumptions!$C$8*Assumptions!$C$6,4),"") - F6 -> 2.6816 | Y6: =IFERROR(ROUND(V6*(1+Assumptions!$C$7)^5,0),"") -> 3381 | Z6: Operational Common Carrier | AA6: Kakinada-Hyderabad-Uran-Ahmedabad (East West Pipeline) | AB6: 57.6 | AC6: 85 | AD6: 0 | AE6: =IF(R6="","",IF(R6>=Control!$D$4,"Y","N")) -> N | AF6: =IF(S6="","",IF(M6>=Control!$D$5,"Y","N")) -> Y | AG6: =IF(T6="","",IF(AB6<=Control!$D$10,"Y","N")) -> Y | AI6: =IF(X6="","",IF(X6>=Control!$D$9,"Y","N")) -> N | AK6: =IFERROR(INDEX(Assumptions!$D$92:$D$115,MATCH(C6,Assumptions!$B$92:$B$115,0)),"Low") -> Low
B7: 9 | C7: TE | D7: Kamareddy | E7: =SUM(G7:I7) -> 0 | F7: =SUMIFS('CBG Plants'!N:N,'CBG Plants'!F:F,D7,'CBG Plants'!L:L,"Completed") +SUMIFS('CBG Plants'!N:N,'CBG Plants'!F:F,D7,'CBG Plants'!L:L,"Functional")+SUMIFS('CBG Plants'!N:N,'CBG Plants'!F:F,D7,'CBG Plants'!L:L,"Under Construction")+SUMIFS('CBG Plants'!N:N,'CBG Plants'!F:F,D7,'CBG Plants'!L:L,"Yet to start construction") -> 0 | G7: =COUNTIFS('CBG Plants'!F:F,D7,'CBG Plants'!L:L,"Completed") +COUNTIFS('CBG Plants'!F:F,D7,'CBG Plants'!L:L,"Functional") -> 0 | H7: =COUNTIFS('CBG Plants'!F:F,D7,'CBG Plants'!L:L,"Under Construction") -> 0 | I7: =COUNTIFS('CBG Plants'!F:F,D7,'CBG Plants'!L:L,"Yet to start construction") -> 0 | J7: BLUELEO-01 | K7: Blue leo by bia green pvt ltd | M7: =IFERROR(N7-(AD7*365/1000),"") -> 507.6 | N7: =SUM(O7:Q7) -> 507.6 | O7: 0.45 | P7: 388.5 | Q7: 118.65 | R7: =IFERROR(U7-F7,"") -> 0.375 | S7: =IFERROR(T7*Assumptions!$C$4,"") -> 12.5 | T7: 5 | U7: =IFERROR(S7*Assumptions!$C$5,"")+IFERROR(V7*Assumptions!$C$8*Assumptions!$C$5,"") -> 0.375 | V7: 0 | W7: =IFERROR(ROUND(T7*(1+Assumptions!$C$7)^5,0),"") -> 15 | X7: =IFERROR(ROUND(W7*Assumptions!$C$4*Assumptions!$C$6,4),"")+IFERROR(ROUND(Y7*Assumptions!$C$8*Assumptions!$C$6,4),"") - F7 -> 1.875 | Y7: =IFERROR(ROUND(V7*(1+Assumptions!$C$7)^5,0),"") -> 0 | Z7: Operational Common Carrier | AA7: Kakinada-Hyderabad-Uran-Ahmedabad (East West Pipeline) | AB7: 87.9 | AC7: 85 | AD7: 0 | AE7: =IF(R7="","",IF(R7>=Control!$D$4,"Y","N")) -> N | AF7: =IF(S7="","",IF(M7>=Control!$D$5,"Y","N")) -> Y | AG7: =IF(T7="","",IF(AB7<=Control!$D$10,"Y","N")) -> Y | AI7: =IF(X7="","",IF(X7>=Control!$D$9,"Y","N")) -> N | AK7: =IFERROR(INDEX(Assumptions!$D$92:$D$115,MATCH(C7,Assumptions!$B$92:$B$115,0)),"Low") -> Low
B8: 12 | C8: TE | D8: Kumuram Bheem Asifabad | E8: =SUM(G8:I8) -> 0 | F8: =SUMIFS('CBG Plants'!N:N,'CBG Plants'!F:F,D8,'CBG Plants'!L:L,"Completed") +SUMIFS('CBG Plants'!N:N,'CBG Plants'!F:F,D8,'CBG Plants'!L:L,"Functional")+SUMIFS('CBG Plants'!N:N,'CBG Plants'!F:F,D8,'CBG Plants'!L:L,"Under Construction")+SUMIFS('CBG Plants'!N:N,'CBG Plants'!F:F,D8,'CBG Plants'!L:L,"Yet to start construction") -> 0 | G8: =COUNTIFS('CBG Plants'!F:F,D8,'CBG Plants'!L:L,"Completed") +COUNTIFS('CBG Plants'!F:F,D8,'CBG Plants'!L:L,"Functional") -> 0 | H8: =COUNTIFS('CBG Plants'!F:F,D8,'CBG Plants'!L:L,"Under Construction") -> 0 | I8: =COUNTIFS('CBG Plants'!F:F,D8,'CBG Plants'!L:L,"Yet to start construction") -> 0 | M8: =IFERROR(N8-(AD8*365/1000),"") -> 43.92 | N8: =SUM(O8:Q8) -> 43.92 | O8: 0.45 | P8: 38.22 | Q8: 5.25 | R8: =IFERROR(U8-F8,"") -> 0.375 | S8: =IFERROR(T8*Assumptions!$C$4,"") -> 12.5 | T8: 5 | U8: =IFERROR(S8*Assumptions!$C$5,"")+IFERROR(V8*Assumptions!$C$8*Assumptions!$C$5,"") -> 0.375 | V8: 0 | W8: =IFERROR(ROUND(T8*(1+Assumptions!$C$7)^5,0),"") -> 15 | X8: =IFERROR(ROUND(W8*Assumptions!$C$4*Assumptions!$C$6,4),"")+IFERROR(ROUND(Y8*Assumptions!$C$8*Assumptions!$C$6,4),"") - F8 -> 1.875 | Y8: =IFERROR(ROUND(V8*(1+Assumptions!$C$7)^5,0),"") -> 0 | Z8: Operational Common Carrier | AA8: Kakinada-Hyderabad-Uran-Ahmedabad (East West Pipeline) | AB8: 228 | AC8: 85 | AD8: 0 | AE8: =IF(R8="","",IF(R8>=Control!$D$4,"Y","N")) -> N | AF8: =IF(S8="","",IF(M8>=Control!$D$5,"Y","N")) -> N | AG8: =IF(T8="","",IF(AB8<=Control!$D$10,"Y","N")) -> Y | AI8: =IF(X8="","",IF(X8>=Control!$D$9,"Y","N")) -> N | AK8: =IFERROR(INDEX(Assumptions!$D$92:$D$115,MATCH(C8,Assumptions!$B$92:$B$115,0)),"Low") -> Low
B9: 22 | C9: TE | D9: Nirmal | E9: =SUM(G9:I9) -> 0 | F9: =SUMIFS('CBG Plants'!N:N,'CBG Plants'!F:F,D9,'CBG Plants'!L:L,"Completed") +SUMIFS('CBG Plants'!N:N,'CBG Plants'!F:F,D9,'CBG Plants'!L:L,"Functional")+SUMIFS('CBG Plants'!N:N,'CBG Plants'!F:F,D9,'CBG Plants'!L:L,"Under Construction")+SUMIFS('CBG Plants'!N:N,'CBG Plants'!F:F,D9,'CBG Plants'!L:L,"Yet to start construction") -> 0 | G9: =COUNTIFS('CBG Plants'!F:F,D9,'CBG Plants'!L:L,"Completed") +COUNTIFS('CBG Plants'!F:F,D9,'CBG Plants'!L:L,"Functional") -> 0 | H9: =COUNTIFS('CBG Plants'!F:F,D9,'CBG Plants'!L:L,"Under Construction") -> 0 | I9: =COUNTIFS('CBG Plants'!F:F,D9,'CBG Plants'!L:L,"Yet to start construction") -> 0 | M9: =IFERROR(N9-(AD9*365/1000),"") -> 336.315 | N9: =SUM(O9:Q9) -> 336.315 | O9: 0 | P9: 147.84 | Q9: 188.475 | R9: =IFERROR(U9-F9,"") -> 0.375 | S9: =IFERROR(T9*Assumptions!$C$4,"") -> 12.5 | T9: 5 | U9: =IFERROR(S9*Assumptions!$C$5,"")+IFERROR(V9*Assumptions!$C$8*Assumptions!$C$5,"") -> 0.375 | V9: 0 | W9: =IFERROR(ROUND(T9*(1+Assumptions!$C$7)^5,0),"") -> 15 | X9: =IFERROR(ROUND(W9*Assumptions!$C$4*Assumptions!$C$6,4),"")+IFERROR(ROUND(Y9*Assumptions!$C$8*Assumptions!$C$6,4),"") - F9 -> 1.875 | Y9: =IFERROR(ROUND(V9*(1+Assumptions!$C$7)^5,0),"") -> 0 | Z9: Operational Common Carrier | AA9: Kakinada-Hyderabad-Uran-Ahmedabad (East West Pipeline) | AB9: 179.2 | AC9: 85 | AD9: 0 | AE9: =IF(R9="","",IF(R9>=Control!$D$4,"Y","N")) -> N | AF9: =IF(S9="","",IF(M9>=Control!$D$5,"Y","N")) -> Y | AG9: =IF(T9="","",IF(AB9<=Control!$D$10,"Y","N")) -> Y | AI9: =IF(X9="","",IF(X9>=Control!$D$9,"Y","N")) -> N | AK9: =IFERROR(INDEX(Assumptions!$D$92:$D$115,MATCH(C9,Assumptions!$B$92:$B$115,0)),"Low") -> Low
B10: 13 | C10: TE | D10: Mahabubabad | E10: =SUM(G10:I10) -> 0 | F10: =SUMIFS('CBG Plants'!N:N,'CBG Plants'!F:F,D10,'CBG Plants'!L:L,"Completed") +SUMIFS('CBG Plants'!N:N,'CBG Plants'!F:F,D10,'CBG Plants'!L:L,"Functional")+SUMIFS('CBG Plants'!N:N,'CBG Plants'!F:F,D10,'CBG Plants'!L:L,"Under Construction")+SUMIFS('CBG Plants'!N:N,'CBG Plants'!F:F,D10,'CBG Plants'!L:L,"Yet to start construction") -> 0 | G10: =COUNTIFS('CBG Plants'!F:F,D10,'CBG Plants'!L:L,"Completed") +COUNTIFS('CBG Plants'!F:F,D10,'CBG Plants'!L:L,"Functional") -> 0 | H10: =COUNTIFS('CBG Plants'!F:F,D10,'CBG Plants'!L:L,"Under Construction") -> 0 | I10: =COUNTIFS('CBG Plants'!F:F,D10,'CBG Plants'!L:L,"Yet to start construction") -> 0 | J10: USHODAYAM BIOENERGY PRIVATE LIMITED | K10: Solika Energy - Udithyal | M10: =IFERROR(N10-(AD10*365/1000),"") -> 281.235 | N10: =SUM(O10:Q10) -> 303.135 | O10: 0 | P10: 188.16 | Q10: 114.975 | R10: =IFERROR(U10-F10,"") -> 0.31546695 | S10: =IFERROR(T10*Assumptions!$C$4,"") -> 10 | T10: 4 | U10: =IFERROR(S10*Assumptions!$C$5,"")+IFERROR(V10*Assumptions!$C$8*Assumptions!$C$5,"") -> 0.31546695 | V10: 1539 | W10: =IFERROR(ROUND(T10*(1+Assumptions!$C$7)^5,0),"") -> 12 | X10: =IFERROR(ROUND(W10*Assumptions!$C$4*Assumptions!$C$6,4),"")+IFERROR(ROUND(Y10*Assumptions!$C$8*Assumptions!$C$6,4),"") - F10 -> 1.5787 | Y10: =IFERROR(ROUND(V10*(1+Assumptions!$C$7)^5,0),"") -> 4697 | Z10: Operational Common Carrier | AA10: Kakinada-Hyderabad-Uran-Ahmedabad (East West Pipeline) | AB10: 49.1 | AC10: 85 | AD10: 60 | AE10: =IF(R10="","",IF(R10>=Control!$D$4,"Y","N")) -> N | AF10: =IF(S10="","",IF(M10>=Control!$D$5,"Y","N")) -> Y | AG10: =IF(T10="","",IF(AB10<=Control!$D$10,"Y","N")) -> Y | AI10: =IF(X10="","",IF(X10>=Control!$D$9,"Y","N")) -> N | AK10: =IFERROR(INDEX(Assumptions!$D$92:$D$115,MATCH(C10,Assumptions!$B$92:$B$115,0)),"Low") -> Low
B11: 19 | C11: TE | D11: Nagarkurnool | E11: =SUM(G11:I11) -> 0 | F11: =SUMIFS('CBG Plants'!N:N,'CBG Plants'!F:F,D11,'CBG Plants'!L:L,"Completed") +SUMIFS('CBG Plants'!N:N,'CBG Plants'!F:F,D11,'CBG Plants'!L:L,"Functional")+SUMIFS('CBG Plants'!N:N,'CBG Plants'!F:F,D11,'CBG Plants'!L:L,"Under Construction")+SUMIFS('CBG Plants'!N:N,'CBG Plants'!F:F,D11,'CBG Plants'!L:L,"Yet to start construction") -> 0 | G11: =COUNTIFS('CBG Plants'!F:F,D11,'CBG Plants'!L:L,"Completed") +COUNTIFS('CBG Plants'!F:F,D11,'CBG Plants'!L:L,"Functional") -> 0 | H11: =COUNTIFS('CBG Plants'!F:F,D11,'CBG Plants'!L:L,"Under Construction") -> 0 | I11: =COUNTIFS('CBG Plants'!F:F,D11,'CBG Plants'!L:L,"Yet to start construction") -> 0 | M11: =IFERROR(N11-(AD11*365/1000),"") -> 339.255 | N11: =SUM(O11:Q11) -> 339.255 | O11: 0 | P11: 190.68 | Q11: 148.575 | R11: =IFERROR(U11-F11,"") -> 0.22529145 | S11: =IFERROR(T11*Assumptions!$C$4,"") -> 7.5 | T11: 3 | U11: =IFERROR(S11*Assumptions!$C$5,"")+IFERROR(V11*Assumptions!$C$8*Assumptions!$C$5,"") -> 0.22529145 | V11: 29 | W11: =IFERROR(ROUND(T11*(1+Assumptions!$C$7)^5,0),"") -> 9 | X11: =IFERROR(ROUND(W11*Assumptions!$C$4*Assumptions!$C$6,4),"")+IFERROR(ROUND(Y11*Assumptions!$C$8*Assumptions!$C$6,4),"") - F11 -> 1.1265 | Y11: =IFERROR(ROUND(V11*(1+Assumptions!$C$7)^5,0),"") -> 89 | Z11: Operational Common Carrier | AA11: Kakinada-Hyderabad-Uran-Ahmedabad (East West Pipeline) | AB11: 108.4 | AC11: 85 | AD11: 0 | AE11: =IF(R11="","",IF(R11>=Control!$D$4,"Y","N")) -> N | AF11: =IF(S11="","",IF(M11>=Control!$D$5,"Y","N")) -> Y | AG11: =IF(T11="","",IF(AB11<=Control!$D$10,"Y","N")) -> Y | AI11: =IF(X11="","",IF(X11>=Control!$D$9,"Y","N")) -> N | AK11: =IFERROR(INDEX(Assumptions!$D$92:$D$115,MATCH(C11,Assumptions!$B$92:$B$115,0)),"Low") -> Low
B12: 10 | C12: TE | D12: Karimnagar | E12: =SUM(G12:I12) -> 0 | F12: =SUMIFS('CBG Plants'!N:N,'CBG Plants'!F:F,D12,'CBG Plants'!L:L,"Completed") +SUMIFS('CBG Plants'!N:N,'CBG Plants'!F:F,D12,'CBG Plants'!L:L,"Functional")+SUMIFS('CBG Plants'!N:N,'CBG Plants'!F:F,D12,'CBG Plants'!L:L,"Under Construction")+SUMIFS('CBG Plants'!N:N,'CBG Plants'!F:F,D12,'CBG Plants'!L:L,"Yet to start construction") -> 0 | G12: =COUNTIFS('CBG Plants'!F:F,D12,'CBG Plants'!L:L,"Completed") +COUNTIFS('CBG Plants'!F:F,D12,'CBG Plants'!L:L,"Functional") -> 0 | H12: =COUNTIFS('CBG Plants'!F:F,D12,'CBG Plants'!L:L,"Under Construction") -> 0 | I12: =COUNTIFS('CBG Plants'!F:F,D12,'CBG Plants'!L:L,"Yet to start construction") -> 0 | M12: =IFERROR(N12-(AD12*365/1000),"") -> 381.885 | N12: =SUM(O12:Q12) -> 381.885 | O12: 0 | P12: 326.76 | Q12: 55.125 | R12: =IFERROR(U12-F12,"") -> 0.15206025 | S12: =IFERROR(T12*Assumptions!$C$4,"") -> 5 | T12: 2 | U12: =IFERROR(S12*Assumptions!$C$5,"")+IFERROR(V12*Assumptions!$C$8*Assumptions!$C$5,"") -> 0.15206025 | V12: 205 | W12: =IFERROR(ROUND(T12*(1+Assumptions!$C$7)^5,0),"") -> 6 | X12: =IFERROR(ROUND(W12*Assumptions!$C$4*Assumptions!$C$6,4),"")+IFERROR(ROUND(Y12*Assumptions!$C$8*Assumptions!$C$6,4),"") - F12 -> 0.7605 | Y12: =IFERROR(ROUND(V12*(1+Assumptions!$C$7)^5,0),"") -> 626 | Z12: Operational Common Carrier | AA12: Kakinada-Hyderabad-Uran-Ahmedabad (East West Pipeline) | AB12: 118.1 | AC12: 85 | AD12: 0 | AE12: =IF(R12="","",IF(R12>=Control!$D$4,"Y","N")) -> N | AF12: =IF(S12="","",IF(M12>=Control!$D$5,"Y","N")) -> Y | AG12: =IF(T12="","",IF(AB12<=Control!$D$10,"Y","N")) -> Y | AI12: =IF(X12="","",IF(X12>=Control!$D$9,"Y","N")) -> N | AK12: =IFERROR(INDEX(Assumptions!$D$92:$D$115,MATCH(C12,Assumptions!$B$92:$B$115,0)),"Low") -> Low
B13: 24 | C13: TE | D13: Peddapalli | E13: =SUM(G13:I13) -> 0 | F13: =SUMIFS('CBG Plants'!N:N,'CBG Plants'!F:F,D13,'CBG Plants'!L:L,"Completed") +SUMIFS('CBG Plants'!N:N,'CBG Plants'!F:F,D13,'CBG Plants'!L:L,"Functional")+SUMIFS('CBG Plants'!N:N,'CBG Plants'!F:F,D13,'CBG Plants'!L:L,"Under Construction")+SUMIFS('CBG Plants'!N:N,'CBG Plants'!F:F,D13,'CBG Plants'!L:L,"Yet to start construction") -> 0 | G13: =COUNTIFS('CBG Plants'!F:F,D13,'CBG Plants'!L:L,"Completed") +COUNTIFS('CBG Plants'!F:F,D13,'CBG Plants'!L:L,"Functional") -> 0 | H13: =COUNTIFS('CBG Plants'!F:F,D13,'CBG Plants'!L:L,"Under Construction") -> 0 | I13: =COUNTIFS('CBG Plants'!F:F,D13,'CBG Plants'!L:L,"Yet to start construction") -> 0 | M13: =IFERROR(N13-(AD13*365/1000),"") -> 285.705 | N13: =SUM(O13:Q13) -> 285.705 | O13: 0 | P13: 251.58 | Q13: 34.125 | R13: =IFERROR(U13-F13,"") -> 0.15206025 | S13: =IFERROR(T13*Assumptions!$C$4,"") -> 5 | T13: 2 | U13: =IFERROR(S13*Assumptions!$C$5,"")+IFERROR(V13*Assumptions!$C$8*Assumptions!$C$5,"") -> 0.15206025 | V13: 205 | W13: =IFERROR(ROUND(T13*(1+Assumptions!$C$7)^5,0),"") -> 6 | X13: =IFERROR(ROUND(W13*Assumptions!$C$4*Assumptions!$C$6,4),"")+IFERROR(ROUND(Y13*Assumptions!$C$8*Assumptions!$C$6,4),"") - F13 -> 0.7605 | Y13: =IFERROR(ROUND(V13*(1+Assumptions!$C$7)^5,0),"") -> 626 | Z13: Operational Common Carrier | AA13: Kakinada-Hyderabad-Uran-Ahmedabad (East West Pipeline) | AB13: 147.1 | AC13: 85 | AD13: 0 | AE13: =IF(R13="","",IF(R13>=Control!$D$4,"Y","N")) -> N | AF13: =IF(S13="","",IF(M13>=Control!$D$5,"Y","N")) -> Y | AG13: =IF(T13="","",IF(AB13<=Control!$D$10,"Y","N")) -> Y | AI13: =IF(X13="","",IF(X13>=Control!$D$9,"Y","N")) -> N | AK13: =IFERROR(INDEX(Assumptions!$D$92:$D$115,MATCH(C13,Assumptions!$B$92:$B$115,0)),"Low") -> Low
B14: 25 | C14: TE | D14: Rajanna Sircilla | E14: =SUM(G14:I14) -> 0 | F14: =SUMIFS('CBG Plants'!N:N,'CBG Plants'!F:F,D14,'CBG Plants'!L:L,"Completed") +SUMIFS('CBG Plants'!N:N,'CBG Plants'!F:F,D14,'CBG Plants'!L:L,"Functional")+SUMIFS('CBG Plants'!N:N,'CBG Plants'!F:F,D14,'CBG Plants'!L:L,"Under Construction")+SUMIFS('CBG Plants'!N:N,'CBG Plants'!F:F,D14,'CBG Plants'!L:L,"Yet to start construction") -> 0 | G14: =COUNTIFS('CBG Plants'!F:F,D14,'CBG Plants'!L:L,"Completed") +COUNTIFS('CBG Plants'!F:F,D14,'CBG Plants'!L:L,"Functional") -> 0 | H14: =COUNTIFS('CBG Plants'!F:F,D14,'CBG Plants'!L:L,"Under Construction") -> 0 | I14: =COUNTIFS('CBG Plants'!F:F,D14,'CBG Plants'!L:L,"Yet to start construction") -> 0 | M14: =IFERROR(N14-(AD14*365/1000),"") -> 232.89 | N14: =SUM(O14:Q14) -> 232.89 | O14: 0 | P14: 227.64 | Q14: 5.25 | R14: =IFERROR(U14-F14,"") -> 0.15206025 | S14: =IFERROR(T14*Assumptions!$C$4,"") -> 5 | T14: 2 | U14: =IFERROR(S14*Assumptions!$C$5,"")+IFERROR(V14*Assumptions!$C$8*Assumptions!$C$5,"") -> 0.15206025 | V14: 205 | W14: =IFERROR(ROUND(T14*(1+Assumptions!$C$7)^5,0),"") -> 6 | X14: =IFERROR(ROUND(W14*Assumptions!$C$4*Assumptions!$C$6,4),"")+IFERROR(ROUND(Y14*Assumptions!$C$8*Assumptions!$C$6,4),"") - F14 -> 0.7605 | Y14: =IFERROR(ROUND(V14*(1+Assumptions!$C$7)^5,0),"") -> 626 | Z14: Operational Common Carrier | AA14: Kakinada-Hyderabad-Uran-Ahmedabad (East West Pipeline) | AB14: 117.5 | AC14: 85 | AD14: 0 | AE14: =IF(R14="","",IF(R14>=Control!$D$4,"Y","N")) -> N | AF14: =IF(S14="","",IF(M14>=Control!$D$5,"Y","N")) -> Y | AG14: =IF(T14="","",IF(AB14<=Control!$D$10,"Y","N")) -> Y | AI14: =IF(X14="","",IF(X14>=Control!$D$9,"Y","N")) -> N | AK14: =IFERROR(INDEX(Assumptions!$D$92:$D$115,MATCH(C14,Assumptions!$B$92:$B$115,0)),"Low") -> Low
B15: 7 | C15: TE | D15: Jayashankar Bhupalapally | E15: =SUM(G15:I15) -> 0 | F15: =SUMIFS('CBG Plants'!N:N,'CBG Plants'!F:F,D15,'CBG Plants'!L:L,"Completed") +SUMIFS('CBG Plants'!N:N,'CBG Plants'!F:F,D15,'CBG Plants'!L:L,"Functional")+SUMIFS('CBG Plants'!N:N,'CBG Plants'!F:F,D15,'CBG Plants'!L:L,"Under Construction")+SUMIFS('CBG Plants'!N:N,'CBG Plants'!F:F,D15,'CBG Plants'!L:L,"Yet to start construction") -> 0 | G15: =COUNTIFS('CBG Plants'!F:F,D15,'CBG Plants'!L:L,"Completed") +COUNTIFS('CBG Plants'!F:F,D15,'CBG Plants'!L:L,"Functional") -> 0 | H15: =COUNTIFS('CBG Plants'!F:F,D15,'CBG Plants'!L:L,"Under Construction") -> 0 | I15: =COUNTIFS('CBG Plants'!F:F,D15,'CBG Plants'!L:L,"Yet to start construction") -> 0 | M15: =IFERROR(N15-(AD15*365/1000),"") -> 138.81 | N15: =SUM(O15:Q15) -> 138.81 | O15: 0 | P15: 104.16 | Q15: 34.65 | R15: =IFERROR(U15-F15,"") -> 0 | S15: =IFERROR(T15*Assumptions!$C$4,"") -> 0 | T15: 0 | U15: =IFERROR(S15*Assumptions!$C$5,"")+IFERROR(V15*Assumptions!$C$8*Assumptions!$C$5,"") -> 0 | V15: 0 | W15: =IFERROR(ROUND(T15*(1+Assumptions!$C$7)^5,0),"") -> 0 | X15: =IFERROR(ROUND(W15*Assumptions!$C$4*Assumptions!$C$6,4),"")+IFERROR(ROUND(Y15*Assumptions!$C$8*Assumptions!$C$6,4),"") - F15 -> 0 | Y15: =IFERROR(ROUND(V15*(1+Assumptions!$C$7)^5,0),"") -> 0 | Z15: Operational Common Carrier | AA15: Kakinada-Hyderabad-Uran-Ahmedabad (East West Pipeline) | AB15: 139.7 | AC15: 85 | AD15: 0 | AE15: =IF(R15="","",IF(R15>=Control!$D$4,"Y","N")) -> N | AF15: =IF(S15="","",IF(M15>=Control!$D$5,"Y","N")) -> Y | AG15: =IF(T15="","",IF(AB15<=Control!$D$10,"Y","N")) -> Y | AI15: =IF(X15="","",IF(X15>=Control!$D$9,"Y","N")) -> N | AK15: =IFERROR(INDEX(Assumptions!$D$92:$D$115,MATCH(C15,Assumptions!$B$92:$B$115,0)),"Low") -> Low
B16: 27 | C16: TE | D16: Sangareddy | E16: =SUM(G16:I16) -> 2 | F16: =SUMIFS('CBG Plants'!N:N,'CBG Plants'!F:F,D16,'CBG Plants'!L:L,"Completed") +SUMIFS('CBG Plants'!N:N,'CBG Plants'!F:F,D16,'CBG Plants'!L:L,"Functional")+SUMIFS('CBG Plants'!N:N,'CBG Plants'!F:F,D16,'CBG Plants'!L:L,"Under Construction")+SUMIFS('CBG Plants'!N:N,'CBG Plants'!F:F,D16,'CBG Plants'!L:L,"Yet to start construction") -> 2.58 | G16: =COUNTIFS('CBG Plants'!F:F,D16,'CBG Plants'!L:L,"Completed") +COUNTIFS('CBG Plants'!F:F,D16,'CBG Plants'!L:L,"Functional") -> 0 | H16: =COUNTIFS('CBG Plants'!F:F,D16,'CBG Plants'!L:L,"Under Construction") -> 1 | I16: =COUNTIFS('CBG Plants'!F:F,D16,'CBG Plants'!L:L,"Yet to start construction") -> 1 | J16: BLUELEO-01 | K16: Blue leo by bia green pvt ltd | M16: =IFERROR(N16-(AD16*365/1000),"") -> 173.46 | N16: =SUM(O16:Q16) -> 173.46 | O16: 0 | P16: 162.96 | Q16: 10.5 | R16: =IFERROR(U16-F16,"") -> -2.0450706 | S16: =IFERROR(T16*Assumptions!$C$4,"") -> 17.5 | T16: 7 | U16: =IFERROR(S16*Assumptions!$C$5,"")+IFERROR(V16*Assumptions!$C$8*Assumptions!$C$5,"") -> 0.5349294 | V16: 988 | W16: =IFERROR(ROUND(T16*(1+Assumptions!$C$7)^5,0),"") -> 21 | X16: =IFERROR(ROUND(W16*Assumptions!$C$4*Assumptions!$C$6,4),"")+IFERROR(ROUND(Y16*Assumptions!$C$8*Assumptions!$C$6,4),"") - F16 -> 0.0955 | Y16: =IFERROR(ROUND(V16*(1+Assumptions!$C$7)^5,0),"") -> 3015 | Z16: Operational Common Carrier | AA16: Kakinada-Hyderabad-Uran-Ahmedabad (East West Pipeline) | AB16: 25 | AC16: 85 | AD16: 0 | AE16: =IF(R16="","",IF(R16>=Control!$D$4,"Y","N")) -> N | AF16: =IF(S16="","",IF(M16>=Control!$D$5,"Y","N")) -> Y | AG16: =IF(T16="","",IF(AB16<=Control!$D$10,"Y","N")) -> Y | AI16: =IF(X16="","",IF(X16>=Control!$D$9,"Y","N")) -> N | AK16: =IFERROR(INDEX(Assumptions!$D$92:$D$115,MATCH(C16,Assumptions!$B$92:$B$115,0)),"Low") -> Low
B17: 31 | C17: TE | D17: Wanaparthy | E17: =SUM(G17:I17) -> 1 | F17: =SUMIFS('CBG Plants'!N:N,'CBG Plants'!F:F,D17,'CBG Plants'!L:L,"Completed") +SUMIFS('CBG Plants'!N:N,'CBG Plants'!F:F,D17,'CBG Plants'!L:L,"Functional")+SUMIFS('CBG Plants'!N:N,'CBG Plants'!F:F,D17,'CBG Plants'!L:L,"Under Construction")+SUMIFS('CBG Plants'!N:N,'CBG Plants'!F:F,D17,'CBG Plants'!L:L,"Yet to start construction") -> 3.8 | G17: =COUNTIFS('CBG Plants'!F:F,D17,'CBG Plants'!L:L,"Completed") +COUNTIFS('CBG Plants'!F:F,D17,'CBG Plants'!L:L,"Functional") -> 0 | H17: =COUNTIFS('CBG Plants'!F:F,D17,'CBG Plants'!L:L,"Under Construction") -> 1 | I17: =COUNTIFS('CBG Plants'!F:F,D17,'CBG Plants'!L:L,"Yet to start construction") -> 0 | J17: Bio CNG | M17: =IFERROR(N17-(AD17*365/1000),"") -> 218.4 | N17: =SUM(O17:Q17) -> 218.4 | O17: 0 | P17: 205.8 | Q17: 12.6 | R17: =IFERROR(U17-F17,"") -> -3.5747085 | S17: =IFERROR(T17*Assumptions!$C$4,"") -> 7.5 | T17: 3 | U17: =IFERROR(S17*Assumptions!$C$5,"")+IFERROR(V17*Assumptions!$C$8*Assumptions!$C$5,"") -> 0.22529145 | V17: 29 | W17: =IFERROR(ROUND(T17*(1+Assumptions!$C$7)^5,0),"") -> 9 | X17: =IFERROR(ROUND(W17*Assumptions!$C$4*Assumptions!$C$6,4),"")+IFERROR(ROUND(Y17*Assumptions!$C$8*Assumptions!$C$6,4),"") - F17 -> -2.6735 | Y17: =IFERROR(ROUND(V17*(1+Assumptions!$C$7)^5,0),"") -> 89 | Z17: Operational Common Carrier | AA17: Kakinada-Hyderabad-Uran-Ahmedabad (East West Pipeline) | AB17: 129.2 | AC17: 85 | AD17: 0 | AE17: =IF(R17="","",IF(R17>=Control!$D$4,"Y","N")) -> N | AF17: =IF(S17="","",IF(M17>=Control!$D$5,"Y","N")) -> Y | AG17: =IF(T17="","",IF(AB17<=Control!$D$10,"Y","N")) -> Y | AI17: =IF(X17="","",IF(X17>=Control!$D$9,"Y","N")) -> N | AK17: =IFERROR(INDEX(Assumptions!$D$92:$D$115,MATCH(C17,Assumptions!$B$92:$B$115,0)),"Low") -> Low
B18: 30 | C18: TE | D18: Vikarabad | E18: =SUM(G18:I18) -> 2 | F18: =SUMIFS('CBG Plants'!N:N,'CBG Plants'!F:F,D18,'CBG Plants'!L:L,"Completed") +SUMIFS('CBG Plants'!N:N,'CBG Plants'!F:F,D18,'CBG Plants'!L:L,"Functional")+SUMIFS('CBG Plants'!N:N,'CBG Plants'!F:F,D18,'CBG Plants'!L:L,"Under Construction")+SUMIFS('CBG Plants'!N:N,'CBG Plants'!F:F,D18,'CBG Plants'!L:L,"Yet to start construction") -> 5.5 | G18: =COUNTIFS('CBG Plants'!F:F,D18,'CBG Plants'!L:L,"Completed") +COUNTIFS('CBG Plants'!F:F,D18,'CBG Plants'!L:L,"Functional") -> 0 | H18: =COUNTIFS('CBG Plants'!F:F,D18,'CBG Plants'!L:L,"Under Construction") -> 0 | I18: =COUNTIFS('CBG Plants'!F:F,D18,'CBG Plants'!L:L,"Yet to start construction") -> 2 | J18: CBG plant | K18: GODESI AGRO RENEWABLE ENERGY | M18: =IFERROR(N18-(AD18*365/1000),"") -> 150.78 | N18: =SUM(O18:Q18) -> 150.78 | O18: 0 | P18: 117.18 | Q18: 33.6 | R18: =IFERROR(U18-F18,"") -> -4.7278398 | S18: =IFERROR(T18*Assumptions!$C$4,"") -> 25 | T18: 10 | U18: =IFERROR(S18*Assumptions!$C$5,"")+IFERROR(V18*Assumptions!$C$8*Assumptions!$C$5,"") -> 0.77216025 | V18: 2205 | W18: =IFERROR(ROUND(T18*(1+Assumptions!$C$7)^5,0),"") -> 31 | X18: =IFERROR(ROUND(W18*Assumptions!$C$4*Assumptions!$C$6,4),"")+IFERROR(ROUND(Y18*Assumptions!$C$8*Assumptions!$C$6,4),"") - F18 -> -1.5123 | Y18: =IFERROR(ROUND(V18*(1+Assumptions!$C$7)^5,0),"") -> 6729 | Z18: Operational Common Carrier | AA18: Kakinada-Hyderabad-Uran-Ahmedabad (East West Pipeline) | AB18: 35.9 | AC18: 85 | AD18: 0 | AE18: =IF(R18="","",IF(R18>=Control!$D$4,"Y","N")) -> N | AF18: =IF(S18="","",IF(M18>=Control!$D$5,"Y","N")) -> Y | AG18: =IF(T18="","",IF(AB18<=Control!$D$10,"Y","N")) -> Y | AI18: =IF(X18="","",IF(X18>=Control!$D$9,"Y","N")) -> N | AK18: =IFERROR(INDEX(Assumptions!$D$92:$D$115,MATCH(C18,Assumptions!$B$92:$B$115,0)),"Low") -> Low
B19: 14 | C19: TE | D19: Mahbubnagar | E19: =SUM(G19:I19) -> 2 | F19: =SUMIFS('CBG Plants'!N:N,'CBG Plants'!F:F,D19,'CBG Plants'!L:L,"Completed") +SUMIFS('CBG Plants'!N:N,'CBG Plants'!F:F,D19,'CBG Plants'!L:L,"Functional")+SUMIFS('CBG Plants'!N:N,'CBG Plants'!F:F,D19,'CBG Plants'!L:L,"Under Construction")+SUMIFS('CBG Plants'!N:N,'CBG Plants'!F:F,D19,'CBG Plants'!L:L,"Yet to start construction") -> 7 | G19: =COUNTIFS('CBG Plants'!F:F,D19,'CBG Plants'!L:L,"Completed") +COUNTIFS('CBG Plants'!F:F,D19,'CBG Plants'!L:L,"Functional") -> 1 | H19: =COUNTIFS('CBG Plants'!F:F,D19,'CBG Plants'!L:L,"Under Construction") -> 0 | I19: =COUNTIFS('CBG Plants'!F:F,D19,'CBG Plants'!L:L,"Yet to start construction") -> 1 | J19: USHODAYAM BIOENERGY PRIVATE LIMITED | K19: Solika Energy - Udithyal | M19: =IFERROR(N19-(AD19*365/1000),"") -> 214.77 | N19: =SUM(O19:Q19) -> 236.67 | O19: 0 | P19: 208.32 | Q19: 28.35 | R19: =IFERROR(U19-F19,"") -> -6.7747085 | S19: =IFERROR(T19*Assumptions!$C$4,"") -> 7.5 | T19: 3 | U19: =IFERROR(S19*Assumptions!$C$5,"")+IFERROR(V19*Assumptions!$C$8*Assumptions!$C$5,"") -> 0.22529145 | V19: 29 | W19: =IFERROR(ROUND(T19*(1+Assumptions!$C$7)^5,0),"") -> 9 | X19: =IFERROR(ROUND(W19*Assumptions!$C$4*Assumptions!$C$6,4),"")+IFERROR(ROUND(Y19*Assumptions!$C$8*Assumptions!$C$6,4),"") - F19 -> -5.8735 | Y19: =IFERROR(ROUND(V19*(1+Assumptions!$C$7)^5,0),"") -> 89 | Z19: Operational Common Carrier | AA19: Kakinada-Hyderabad-Uran-Ahmedabad (East West Pipeline) | AB19: 81.7 | AC19: 85 | AD19: 60 | AE19: =IF(R19="","",IF(R19>=Control!$D$4,"Y","N")) -> N | AF19: =IF(S19="","",IF(M19>=Control!$D$5,"Y","N")) -> Y | AG19: =IF(T19="","",IF(AB19<=Control!$D$10,"Y","N")) -> Y | AI19: =IF(X19="","",IF(X19>=Control!$D$9,"Y","N")) -> N | AK19: =IFERROR(INDEX(Assumptions!$D$92:$D$115,MATCH(C19,Assumptions!$B$92:$B$115,0)),"Low") -> Low
B20: 5 | C20: TE | D20: Jagtial | E20: =SUM(G20:I20) -> 2 | F20: =SUMIFS('CBG Plants'!N:N,'CBG Plants'!F:F,D20,'CBG Plants'!L:L,"Completed") +SUMIFS('CBG Plants'!N:N,'CBG Plants'!F:F,D20,'CBG Plants'!L:L,"Functional")+SUMIFS('CBG Plants'!N:N,'CBG Plants'!F:F,D20,'CBG Plants'!L:L,"Under Construction")+SUMIFS('CBG Plants'!N:N,'CBG Plants'!F:F,D20,'CBG Plants'!L:L,"Yet to start construction") -> 7 | G20: =COUNTIFS('CBG Plants'!F:F,D20,'CBG Plants'!L:L,"Completed") +COUNTIFS('CBG Plants'!F:F,D20,'CBG Plants'!L:L,"Functional") -> 0 | H20: =COUNTIFS('CBG Plants'!F:F,D20,'CBG Plants'!L:L,"Under Construction") -> 0 | I20: =COUNTIFS('CBG Plants'!F:F,D20,'CBG Plants'!L:L,"Yet to start construction") -> 2 | J20: EcoMax Energy Karimnagar | K20: Alyra Bio fuels and Fertilizers | M20: =IFERROR(N20-(AD20*365/1000),"") -> 0 | N20: =SUM(O20:Q20) -> 0 | R20: =IFERROR(U20-F20,"") -> -6.8479398 | S20: =IFERROR(T20*Assumptions!$C$4,"") -> 5 | T20: 2 | U20: =IFERROR(S20*Assumptions!$C$5,"")+IFERROR(V20*Assumptions!$C$8*Assumptions!$C$5,"") -> 0.15206025 | V20: 205 | W20: =IFERROR(ROUND(T20*(1+Assumptions!$C$7)^5,0),"") -> 6 | X20: =IFERROR(ROUND(W20*Assumptions!$C$4*Assumptions!$C$6,4),"")+IFERROR(ROUND(Y20*Assumptions!$C$8*Assumptions!$C$6,4),"") - F20 -> -6.2395 | Y20: =IFERROR(ROUND(V20*(1+Assumptions!$C$7)^5,0),"") -> 626 | Z20: Operational Common Carrier | AA20: Kakinada-Hyderabad-Uran-Ahmedabad (East West Pipeline) | AB20: 163.8 | AC20: 85 | AD20: 0 | AE20: =IF(R20="","",IF(R20>=Control!$D$4,"Y","N")) -> N | AF20: =IF(S20="","",IF(M20>=Control!$D$5,"Y","N")) -> N | AG20: =IF(T20="","",IF(AB20<=Control!$D$10,"Y","N")) -> Y | AI20: =IF(X20="","",IF(X20>=Control!$D$9,"Y","N")) -> N | AK20: =IFERROR(INDEX(Assumptions!$D$92:$D$115,MATCH(C20,Assumptions!$B$92:$B$115,0)),"Low") -> Low
B21: 11 | C21: TE | D21: Khammam | E21: =SUM(G21:I21) -> 2 | F21: =SUMIFS('CBG Plants'!N:N,'CBG Plants'!F:F,D21,'CBG Plants'!L:L,"Completed") +SUMIFS('CBG Plants'!N:N,'CBG Plants'!F:F,D21,'CBG Plants'!L:L,"Functional")+SUMIFS('CBG Plants'!N:N,'CBG Plants'!F:F,D21,'CBG Plants'!L:L,"Under Construction")+SUMIFS('CBG Plants'!N:N,'CBG Plants'!F:F,D21,'CBG Plants'!L:L,"Yet to start construction") -> 7.5 | G21: =COUNTIFS('CBG Plants'!F:F,D21,'CBG Plants'!L:L,"Completed") +COUNTIFS('CBG Plants'!F:F,D21,'CBG Plants'!L:L,"Functional") -> 0 | H21: =COUNTIFS('CBG Plants'!F:F,D21,'CBG Plants'!L:L,"Under Construction") -> 1 | I21: =COUNTIFS('CBG Plants'!F:F,D21,'CBG Plants'!L:L,"Yet to start construction") -> 1 | J21: AGRIVERT BIOFUELS PRIVATE LIMITED | K21: VAYU SHAKTHI | M21: =IFERROR(N21-(AD21*365/1000),"") -> 482.16 | N21: =SUM(O21:Q21) -> 482.16 | O21: 0 | P21: 295.26 | Q21: 186.9 | R21: =IFERROR(U21-F21,"") -> -6.9638646 | S21: =IFERROR(T21*Assumptions!$C$4,"") -> 17.5 | T21: 7 | U21: =IFERROR(S21*Assumptions!$C$5,"")+IFERROR(V21*Assumptions!$C$8*Assumptions!$C$5,"") -> 0.5361354 | V21: 1108 | W21: =IFERROR(ROUND(T21*(1+Assumptions!$C$7)^5,0),"") -> 21 | X21: =IFERROR(ROUND(W21*Assumptions!$C$4*Assumptions!$C$6,4),"")+IFERROR(ROUND(Y21*Assumptions!$C$8*Assumptions!$C$6,4),"") - F21 -> -4.8184 | Y21: =IFERROR(ROUND(V21*(1+Assumptions!$C$7)^5,0),"") -> 3381 | Z21: Operational Common Carrier | AA21: Kakinada-Hyderabad-Uran-Ahmedabad (East West Pipeline) | AB21: 0.6 | AC21: 85 | AD21: 0 | AE21: =IF(R21="","",IF(R21>=Control!$D$4,"Y","N")) -> N | AF21: =IF(S21="","",IF(M21>=Control!$D$5,"Y","N")) -> Y | AG21: =IF(T21="","",IF(AB21<=Control!$D$10,"Y","N")) -> Y | AI21: =IF(X21="","",IF(X21>=Control!$D$9,"Y","N")) -> N | AK21: =IFERROR(INDEX(Assumptions!$D$92:$D$115,MATCH(C21,Assumptions!$B$92:$B$115,0)),"Low") -> Low
B22: 18 | C22: TE | D22: Mulugu | E22: =SUM(G22:I22) -> 2 | F22: =SUMIFS('CBG Plants'!N:N,'CBG Plants'!F:F,D22,'CBG Plants'!L:L,"Completed") +SUMIFS('CBG Plants'!N:N,'CBG Plants'!F:F,D22,'CBG Plants'!L:L,"Functional")+SUMIFS('CBG Plants'!N:N,'CBG Plants'!F:F,D22,'CBG Plants'!L:L,"Under Construction")+SUMIFS('CBG Plants'!N:N,'CBG Plants'!F:F,D22,'CBG Plants'!L:L,"Yet to start construction") -> 9 | G22: =COUNTIFS('CBG Plants'!F:F,D22,'CBG Plants'!L:L,"Completed") +COUNTIFS('CBG Plants'!F:F,D22,'CBG Plants'!L:L,"Functional") -> 0 | H22: =COUNTIFS('CBG Plants'!F:F,D22,'CBG Plants'!L:L,"Under Construction") -> 0 | I22: =COUNTIFS('CBG Plants'!F:F,D22,'CBG Plants'!L:L,"Yet to start construction") -> 2 | J22: Mulugu Bio Energy | K22: KASHYAPA ECOFUELS | M22: =IFERROR(N22-(AD22*365/1000),"") -> 93.03 | N22: =SUM(O22:Q22) -> 93.03 | O22: 0 | P22: 73.08 | Q22: 19.95 | R22: =IFERROR(U22-F22,"") -> -9 | S22: =IFERROR(T22*Assumptions!$C$4,"") -> 0 | T22: 0 | U22: =IFERROR(S22*Assumptions!$C$5,"")+IFERROR(V22*Assumptions!$C$8*Assumptions!$C$5,"") -> 0 | V22: 0 | W22: =IFERROR(ROUND(T22*(1+Assumptions!$C$7)^5,0),"") -> 0 | X22: =IFERROR(ROUND(W22*Assumptions!$C$4*Assumptions!$C$6,4),"")+IFERROR(ROUND(Y22*Assumptions!$C$8*Assumptions!$C$6,4),"") - F22 -> -9 | Y22: =IFERROR(ROUND(V22*(1+Assumptions!$C$7)^5,0),"") -> 0 | Z22: Operational Common Carrier | AA22: Kakinada-Hyderabad-Uran-Ahmedabad (East West Pipeline) | AB22: 121.1 | AC22: 85 | AD22: 0 | AE22: =IF(R22="","",IF(R22>=Control!$D$4,"Y","N")) -> N | AF22: =IF(S22="","",IF(M22>=Control!$D$5,"Y","N")) -> Y | AG22: =IF(T22="","",IF(AB22<=Control!$D$10,"Y","N")) -> Y | AI22: =IF(X22="","",IF(X22>=Control!$D$9,"Y","N")) -> N | AK22: =IFERROR(INDEX(Assumptions!$D$92:$D$115,MATCH(C22,Assumptions!$B$92:$B$115,0)),"Low") -> Low
B23: 28 | C23: TE | D23: Siddipet | E23: =SUM(G23:I23) -> 2 | F23: =SUMIFS('CBG Plants'!N:N,'CBG Plants'!F:F,D23,'CBG Plants'!L:L,"Completed") +SUMIFS('CBG Plants'!N:N,'CBG Plants'!F:F,D23,'CBG Plants'!L:L,"Functional")+SUMIFS('CBG Plants'!N:N,'CBG Plants'!F:F,D23,'CBG Plants'!L:L,"Under Construction")+SUMIFS('CBG Plants'!N:N,'CBG Plants'!F:F,D23,'CBG Plants'!L:L,"Yet to start construction") -> 11 | G23: =COUNTIFS('CBG Plants'!F:F,D23,'CBG Plants'!L:L,"Completed") +COUNTIFS('CBG Plants'!F:F,D23,'CBG Plants'!L:L,"Functional") -> 1 | H23: =COUNTIFS('CBG Plants'!F:F,D23,'CBG Plants'!L:L,"Under Construction") -> 0 | I23: =COUNTIFS('CBG Plants'!F:F,D23,'CBG Plants'!L:L,"Yet to start construction") -> 1 | J23: Juno Joule Bio Fuels Telangana 10 TPD Plant | K23: Carbon Masters Biogas Plant | M23: =IFERROR(N23-(AD23*365/1000),"") -> 509.43 | N23: =SUM(O23:Q23) -> 520.38 | O23: 0 | P23: 453.18 | Q23: 67.2 | R23: =IFERROR(U23-F23,"") -> -10.465071 | S23: =IFERROR(T23*Assumptions!$C$4,"") -> 17.5 | T23: 7 | U23: =IFERROR(S23*Assumptions!$C$5,"")+IFERROR(V23*Assumptions!$C$8*Assumptions!$C$5,"") -> 0.5349294 | V23: 988 | W23: =IFERROR(ROUND(T23*(1+Assumptions!$C$7)^5,0),"") -> 21 | X23: =IFERROR(ROUND(W23*Assumptions!$C$4*Assumptions!$C$6,4),"")+IFERROR(ROUND(Y23*Assumptions!$C$8*Assumptions!$C$6,4),"") - F23 -> -8.3245 | Y23: =IFERROR(ROUND(V23*(1+Assumptions!$C$7)^5,0),"") -> 3015 | Z23: Operational Common Carrier | AA23: Kakinada-Hyderabad-Uran-Ahmedabad (East West Pipeline) | AB23: 73.1 | AC23: 85 | AD23: 30 | AE23: =IF(R23="","",IF(R23>=Control!$D$4,"Y","N")) -> N | AF23: =IF(S23="","",IF(M23>=Control!$D$5,"Y","N")) -> Y | AG23: =IF(T23="","",IF(AB23<=Control!$D$10,"Y","N")) -> Y | AI23: =IF(X23="","",IF(X23>=Control!$D$9,"Y","N")) -> N | AK23: =IFERROR(INDEX(Assumptions!$D$92:$D$115,MATCH(C23,Assumptions!$B$92:$B$115,0)),"Low") -> Low
B24: 15 | C24: TE | D24: Mancherial | E24: =SUM(G24:I24) -> 1 | F24: =SUMIFS('CBG Plants'!N:N,'CBG Plants'!F:F,D24,'CBG Plants'!L:L,"Completed") +SUMIFS('CBG Plants'!N:N,'CBG Plants'!F:F,D24,'CBG Plants'!L:L,"Functional")+SUMIFS('CBG Plants'!N:N,'CBG Plants'!F:F,D24,'CBG Plants'!L:L,"Under Construction")+SUMIFS('CBG Plants'!N:N,'CBG Plants'!F:F,D24,'CBG Plants'!L:L,"Yet to start construction") -> 12 | G24: =COUNTIFS('CBG Plants'!F:F,D24,'CBG Plants'!L:L,"Completed") +COUNTIFS('CBG Plants'!F:F,D24,'CBG Plants'!L:L,"Functional") -> 0 | H24: =COUNTIFS('CBG Plants'!F:F,D24,'CBG Plants'!L:L,"Under Construction") -> 0 | I24: =COUNTIFS('CBG Plants'!F:F,D24,'CBG Plants'!L:L,"Yet to start construction") -> 1 | J24: Prathmay Projects Pvt Ltd Compressed bio gas | M24: =IFERROR(N24-(AD24*365/1000),"") -> 146.475 | N24: =SUM(O24:Q24) -> 146.475 | O24: 0 | P24: 142.8 | Q24: 3.675 | R24: =IFERROR(U24-F24,"") -> -11.625 | S24: =IFERROR(T24*Assumptions!$C$4,"") -> 12.5 | T24: 5 | U24: =IFERROR(S24*Assumptions!$C$5,"")+IFERROR(V24*Assumptions!$C$8*Assumptions!$C$5,"") -> 0.375 | V24: 0 | W24: =IFERROR(ROUND(T24*(1+Assumptions!$C$7)^5,0),"") -> 15 | X24: =IFERROR(ROUND(W24*Assumptions!$C$4*Assumptions!$C$6,4),"")+IFERROR(ROUND(Y24*Assumptions!$C$8*Assumptions!$C$6,4),"") - F24 -> -10.125 | Y24: =IFERROR(ROUND(V24*(1+Assumptions!$C$7)^5,0),"") -> 0 | Z24: Operational Common Carrier | AA24: Kakinada-Hyderabad-Uran-Ahmedabad (East West Pipeline) | AB24: 189 | AC24: 85 | AD24: 0 | AE24: =IF(R24="","",IF(R24>=Control!$D$4,"Y","N")) -> N | AF24: =IF(S24="","",IF(M24>=Control!$D$5,"Y","N")) -> Y | AG24: =IF(T24="","",IF(AB24<=Control!$D$10,"Y","N")) -> Y | AI24: =IF(X24="","",IF(X24>=Control!$D$9,"Y","N")) -> N | AK24: =IFERROR(INDEX(Assumptions!$D$92:$D$115,MATCH(C24,Assumptions!$B$92:$B$115,0)),"Low") -> Low
B25: 8 | C25: TE | D25: Jogulamba Gadwal | E25: =SUM(G25:I25) -> 1 | F25: =SUMIFS('CBG Plants'!N:N,'CBG Plants'!F:F,D25,'CBG Plants'!L:L,"Completed") +SUMIFS('CBG Plants'!N:N,'CBG Plants'!F:F,D25,'CBG Plants'!L:L,"Functional")+SUMIFS('CBG Plants'!N:N,'CBG Plants'!F:F,D25,'CBG Plants'!L:L,"Under Construction")+SUMIFS('CBG Plants'!N:N,'CBG Plants'!F:F,D25,'CBG Plants'!L:L,"Yet to start construction") -> 12 | G25: =COUNTIFS('CBG Plants'!F:F,D25,'CBG Plants'!L:L,"Completed") +COUNTIFS('CBG Plants'!F:F,D25,'CBG Plants'!L:L,"Functional") -> 0 | H25: =COUNTIFS('CBG Plants'!F:F,D25,'CBG Plants'!L:L,"Under Construction") -> 0 | I25: =COUNTIFS('CBG Plants'!F:F,D25,'CBG Plants'!L:L,"Yet to start construction") -> 1 | J25: Sri Hanuman Green Energies Unit-1 | M25: =IFERROR(N25-(AD25*365/1000),"") -> 141.96 | N25: =SUM(O25:Q25) -> 141.96 | O25: 0 | P25: 87.36 | Q25: 54.6 | R25: =IFERROR(U25-F25,"") -> -11.774709 | S25: =IFERROR(T25*Assumptions!$C$4,"") -> 7.5 | T25: 3 | U25: =IFERROR(S25*Assumptions!$C$5,"")+IFERROR(V25*Assumptions!$C$8*Assumptions!$C$5,"") -> 0.22529145 | V25: 29 | W25: =IFERROR(ROUND(T25*(1+Assumptions!$C$7)^5,0),"") -> 9 | X25: =IFERROR(ROUND(W25*Assumptions!$C$4*Assumptions!$C$6,4),"")+IFERROR(ROUND(Y25*Assumptions!$C$8*Assumptions!$C$6,4),"") - F25 -> -10.8735 | Y25: =IFERROR(ROUND(V25*(1+Assumptions!$C$7)^5,0),"") -> 89 | Z25: Operational Common Carrier | AA25: Kakinada-Hyderabad-Uran-Ahmedabad (East West Pipeline) | AB25: 160.2 | AC25: 85 | AD25: 0 | AE25: =IF(R25="","",IF(R25>=Control!$D$4,"Y","N")) -> N | AF25: =IF(S25="","",IF(M25>=Control!$D$5,"Y","N")) -> Y | AG25: =IF(T25="","",IF(AB25<=Control!$D$10,"Y","N")) -> Y | AI25: =IF(X25="","",IF(X25>=Control!$D$9,"Y","N")) -> N | AK25: =IFERROR(INDEX(Assumptions!$D$92:$D$115,MATCH(C25,Assumptions!$B$92:$B$115,0)),"Low") -> Low
B26: 23 | C26: TE | D26: Nizamabad | E26: =SUM(G26:I26) -> 1 | F26: =SUMIFS('CBG Plants'!N:N,'CBG Plants'!F:F,D26,'CBG Plants'!L:L,"Completed") +SUMIFS('CBG Plants'!N:N,'CBG Plants'!F:F,D26,'CBG Plants'!L:L,"Functional")+SUMIFS('CBG Plants'!N:N,'CBG Plants'!F:F,D26,'CBG Plants'!L:L,"Under Construction")+SUMIFS('CBG Plants'!N:N,'CBG Plants'!F:F,D26,'CBG Plants'!L:L,"Yet to start construction") -> 20 | G26: =COUNTIFS('CBG Plants'!F:F,D26,'CBG Plants'!L:L,"Completed") +COUNTIFS('CBG Plants'!F:F,D26,'CBG Plants'!L:L,"Functional") -> 0 | H26: =COUNTIFS('CBG Plants'!F:F,D26,'CBG Plants'!L:L,"Under Construction") -> 0 | I26: =COUNTIFS('CBG Plants'!F:F,D26,'CBG Plants'!L:L,"Yet to start construction") -> 1 | J26: Compressed bio gas plant | M26: =IFERROR(N26-(AD26*365/1000),"") -> 697.095 | N26: =SUM(O26:Q26) -> 697.095 | O26: 0 | P26: 592.62 | Q26: 104.475 | R26: =IFERROR(U26-F26,"") -> -19.625 | S26: =IFERROR(T26*Assumptions!$C$4,"") -> 12.5 | T26: 5 | U26: =IFERROR(S26*Assumptions!$C$5,"")+IFERROR(V26*Assumptions!$C$8*Assumptions!$C$5,"") -> 0.375 | V26: 0 | W26: =IFERROR(ROUND(T26*(1+Assumptions!$C$7)^5,0),"") -> 15 | X26: =IFERROR(ROUND(W26*Assumptions!$C$4*Assumptions!$C$6,4),"")+IFERROR(ROUND(Y26*Assumptions!$C$8*Assumptions!$C$6,4),"") - F26 -> -18.125 | Y26: =IFERROR(ROUND(V26*(1+Assumptions!$C$7)^5,0),"") -> 0 | Z26: Operational Common Carrier | AA26: Kakinada-Hyderabad-Uran-Ahmedabad (East West Pipeline) | AB26: 132.3 | AC26: 85 | AD26: 0 | AE26: =IF(R26="","",IF(R26>=Control!$D$4,"Y","N")) -> N | AF26: =IF(S26="","",IF(M26>=Control!$D$5,"Y","N")) -> Y | AG26: =IF(T26="","",IF(AB26<=Control!$D$10,"Y","N")) -> Y | AI26: =IF(X26="","",IF(X26>=Control!$D$9,"Y","N")) -> N | AK26: =IFERROR(INDEX(Assumptions!$D$92:$D$115,MATCH(C26,Assumptions!$B$92:$B$115,0)),"Low") -> Low
B27: 21 | C27: TE | D27: Narayanpet | E27: =SUM(G27:I27) -> 1 | F27: =SUMIFS('CBG Plants'!N:N,'CBG Plants'!F:F,D27,'CBG Plants'!L:L,"Completed") +SUMIFS('CBG Plants'!N:N,'CBG Plants'!F:F,D27,'CBG Plants'!L:L,"Functional")+SUMIFS('CBG Plants'!N:N,'CBG Plants'!F:F,D27,'CBG Plants'!L:L,"Under Construction")+SUMIFS('CBG Plants'!N:N,'CBG Plants'!F:F,D27,'CBG Plants'!L:L,"Yet to start construction") -> 20 | G27: =COUNTIFS('CBG Plants'!F:F,D27,'CBG Plants'!L:L,"Completed") +COUNTIFS('CBG Plants'!F:F,D27,'CBG Plants'!L:L,"Functional") -> 0 | H27: =COUNTIFS('CBG Plants'!F:F,D27,'CBG Plants'!L:L,"Under Construction") -> 0 | I27: =COUNTIFS('CBG Plants'!F:F,D27,'CBG Plants'!L:L,"Yet to start construction") -> 1 | J27: Devsristi Energy Private Limited | M27: =IFERROR(N27-(AD27*365/1000),"") -> 189.945 | N27: =SUM(O27:Q27) -> 189.945 | O27: 0 | P27: 189.42 | Q27: 0.525 | R27: =IFERROR(U27-F27,"") -> -19.774709 | S27: =IFERROR(T27*Assumptions!$C$4,"") -> 7.5 | T27: 3 | U27: =IFERROR(S27*Assumptions!$C$5,"")+IFERROR(V27*Assumptions!$C$8*Assumptions!$C$5,"") -> 0.22529145 | V27: 29 | W27: =IFERROR(ROUND(T27*(1+Assumptions!$C$7)^5,0),"") -> 9 | X27: =IFERROR(ROUND(W27*Assumptions!$C$4*Assumptions!$C$6,4),"")+IFERROR(ROUND(Y27*Assumptions!$C$8*Assumptions!$C$6,4),"") - F27 -> -18.8735 | Y27: =IFERROR(ROUND(V27*(1+Assumptions!$C$7)^5,0),"") -> 89 | Z27: Operational Common Carrier | AA27: Kakinada-Hyderabad-Uran-Ahmedabad (East West Pipeline) | AB27: 105 | AC27: 85 | AD27: 0 | AE27: =IF(R27="","",IF(R27>=Control!$D$4,"Y","N")) -> N | AF27: =IF(S27="","",IF(M27>=Control!$D$5,"Y","N")) -> Y | AG27: =IF(T27="","",IF(AB27<=Control!$D$10,"Y","N")) -> Y | AI27: =IF(X27="","",IF(X27>=Control!$D$9,"Y","N")) -> N | AK27: =IFERROR(INDEX(Assumptions!$D$92:$D$115,MATCH(C27,Assumptions!$B$92:$B$115,0)),"Low") -> Low
B28: 1 | C28: TE | D28: Adilabad | E28: =SUM(G28:I28) -> 2 | F28: =SUMIFS('CBG Plants'!N:N,'CBG Plants'!F:F,D28,'CBG Plants'!L:L,"Completed") +SUMIFS('CBG Plants'!N:N,'CBG Plants'!F:F,D28,'CBG Plants'!L:L,"Functional")+SUMIFS('CBG Plants'!N:N,'CBG Plants'!F:F,D28,'CBG Plants'!L:L,"Under Construction")+SUMIFS('CBG Plants'!N:N,'CBG Plants'!F:F,D28,'CBG Plants'!L:L,"Yet to start construction") -> 23 | G28: =COUNTIFS('CBG Plants'!F:F,D28,'CBG Plants'!L:L,"Completed") +COUNTIFS('CBG Plants'!F:F,D28,'CBG Plants'!L:L,"Functional") -> 0 | H28: =COUNTIFS('CBG Plants'!F:F,D28,'CBG Plants'!L:L,"Under Construction") -> 0 | I28: =COUNTIFS('CBG Plants'!F:F,D28,'CBG Plants'!L:L,"Yet to start construction") -> 2 | J28: GADIGUDAAGROBIOGASFARMER PRODUCER COMPANY LIMITED | K28: MANUKA GREEN ENERGY PVT LTD - CBG PLANT | M28: =IFERROR(N28-(AD28*365/1000),"") -> 28.935 | N28: =SUM(O28:Q28) -> 28.935 | O28: 0.9 | P28: 1.26 | Q28: 26.775 | R28: =IFERROR(U28-F28,"") -> -22.625 | S28: =IFERROR(T28*Assumptions!$C$4,"") -> 12.5 | T28: 5 | U28: =IFERROR(S28*Assumptions!$C$5,"")+IFERROR(V28*Assumptions!$C$8*Assumptions!$C$5,"") -> 0.375 | V28: 0 | W28: =IFERROR(ROUND(T28*(1+Assumptions!$C$7)^5,0),"") -> 15 | X28: =IFERROR(ROUND(W28*Assumptions!$C$4*Assumptions!$C$6,4),"")+IFERROR(ROUND(Y28*Assumptions!$C$8*Assumptions!$C$6,4),"") - F28 -> -21.125 | Y28: =IFERROR(ROUND(V28*(1+Assumptions!$C$7)^5,0),"") -> 0 | Z28: Operational Common Carrier | AA28: Kakinada-Hyderabad-Uran-Ahmedabad (East West Pipeline) | AB28: 229.6 | AC28: 85 | AD28: 0 | AE28: =IF(R28="","",IF(R28>=Control!$D$4,"Y","N")) -> N | AF28: =IF(S28="","",IF(M28>=Control!$D$5,"Y","N")) -> N | AG28: =IF(T28="","",IF(AB28<=Control!$D$10,"Y","N")) -> Y | AI28: =IF(X28="","",IF(X28>=Control!$D$9,"Y","N")) -> N | AK28: =IFERROR(INDEX(Assumptions!$D$92:$D$115,MATCH(C28,Assumptions!$B$92:$B$115,0)),"Low") -> Low
B29: 16 | C29: TE | D29: Medak | E29: =SUM(G29:I29) -> 1 | F29: =SUMIFS('CBG Plants'!N:N,'CBG Plants'!F:F,D29,'CBG Plants'!L:L,"Completed") +SUMIFS('CBG Plants'!N:N,'CBG Plants'!F:F,D29,'CBG Plants'!L:L,"Functional")+SUMIFS('CBG Plants'!N:N,'CBG Plants'!F:F,D29,'CBG Plants'!L:L,"Under Construction")+SUMIFS('CBG Plants'!N:N,'CBG Plants'!F:F,D29,'CBG Plants'!L:L,"Yet to start construction") -> 24 | G29: =COUNTIFS('CBG Plants'!F:F,D29,'CBG Plants'!L:L,"Completed") +COUNTIFS('CBG Plants'!F:F,D29,'CBG Plants'!L:L,"Functional") -> 0 | H29: =COUNTIFS('CBG Plants'!F:F,D29,'CBG Plants'!L:L,"Under Construction") -> 0 | I29: =COUNTIFS('CBG Plants'!F:F,D29,'CBG Plants'!L:L,"Yet to start construction") -> 1 | J29: RAINBOW FOOD PRODUCTS PRIVATE LIMITED | M29: =IFERROR(N29-(AD29*365/1000),"") -> 328.23 | N29: =SUM(O29:Q29) -> 328.23 | O29: 0 | P29: 322.98 | Q29: 5.25 | R29: =IFERROR(U29-F29,"") -> -23.465071 | S29: =IFERROR(T29*Assumptions!$C$4,"") -> 17.5 | T29: 7 | U29: =IFERROR(S29*Assumptions!$C$5,"")+IFERROR(V29*Assumptions!$C$8*Assumptions!$C$5,"") -> 0.5349294 | V29: 988 | W29: =IFERROR(ROUND(T29*(1+Assumptions!$C$7)^5,0),"") -> 21 | X29: =IFERROR(ROUND(W29*Assumptions!$C$4*Assumptions!$C$6,4),"")+IFERROR(ROUND(Y29*Assumptions!$C$8*Assumptions!$C$6,4),"") - F29 -> -21.3245 | Y29: =IFERROR(ROUND(V29*(1+Assumptions!$C$7)^5,0),"") -> 3015 | Z29: Operational Common Carrier | AA29: Kakinada-Hyderabad-Uran-Ahmedabad (East West Pipeline) | AB29: 54.2 | AC29: 85 | AD29: 0 | AE29: =IF(R29="","",IF(R29>=Control!$D$4,"Y","N")) -> N | AF29: =IF(S29="","",IF(M29>=Control!$D$5,"Y","N")) -> Y | AG29: =IF(T29="","",IF(AB29<=Control!$D$10,"Y","N")) -> Y | AI29: =IF(X29="","",IF(X29>=Control!$D$9,"Y","N")) -> N | AK29: =IFERROR(INDEX(Assumptions!$D$92:$D$115,MATCH(C29,Assumptions!$B$92:$B$115,0)),"Low") -> Low
B30: 6 | C30: TE | D30: Jangaon | E30: =SUM(G30:I30) -> 2 | F30: =SUMIFS('CBG Plants'!N:N,'CBG Plants'!F:F,D30,'CBG Plants'!L:L,"Completed") +SUMIFS('CBG Plants'!N:N,'CBG Plants'!F:F,D30,'CBG Plants'!L:L,"Functional")+SUMIFS('CBG Plants'!N:N,'CBG Plants'!F:F,D30,'CBG Plants'!L:L,"Under Construction")+SUMIFS('CBG Plants'!N:N,'CBG Plants'!F:F,D30,'CBG Plants'!L:L,"Yet to start construction") -> 24 | G30: =COUNTIFS('CBG Plants'!F:F,D30,'CBG Plants'!L:L,"Completed") +COUNTIFS('CBG Plants'!F:F,D30,'CBG Plants'!L:L,"Functional") -> 0 | H30: =COUNTIFS('CBG Plants'!F:F,D30,'CBG Plants'!L:L,"Under Construction") -> 0 | I30: =COUNTIFS('CBG Plants'!F:F,D30,'CBG Plants'!L:L,"Yet to start construction") -> 2 | J30: DVNS Stores Private Limited | K30: Krish and krish enterprises private limited | M30: =IFERROR(N30-(AD30*365/1000),"") -> 0 | N30: =SUM(O30:Q30) -> 0 | R30: =IFERROR(U30-F30,"") -> -23.684533 | S30: =IFERROR(T30*Assumptions!$C$4,"") -> 10 | T30: 4 | U30: =IFERROR(S30*Assumptions!$C$5,"")+IFERROR(V30*Assumptions!$C$8*Assumptions!$C$5,"") -> 0.31546695 | V30: 1539 | W30: =IFERROR(ROUND(T30*(1+Assumptions!$C$7)^5,0),"") -> 12 | X30: =IFERROR(ROUND(W30*Assumptions!$C$4*Assumptions!$C$6,4),"")+IFERROR(ROUND(Y30*Assumptions!$C$8*Assumptions!$C$6,4),"") - F30 -> -22.4213 | Y30: =IFERROR(ROUND(V30*(1+Assumptions!$C$7)^5,0),"") -> 4697 | Z30: Operational Common Carrier | AA30: Kakinada-Hyderabad-Uran-Ahmedabad (East West Pipeline) | AB30: 49.4 | AC30: 85 | AD30: 0 | AE30: =IF(R30="","",IF(R30>=Control!$D$4,"Y","N")) -> N | AF30: =IF(S30="","",IF(M30>=Control!$D$5,"Y","N")) -> N | AG30: =IF(T30="","",IF(AB30<=Control!$D$10,"Y","N")) -> Y | AI30: =IF(X30="","",IF(X30>=Control!$D$9,"Y","N")) -> N | AK30: =IFERROR(INDEX(Assumptions!$D$92:$D$115,MATCH(C30,Assumptions!$B$92:$B$115,0)),"Low") -> Low
B31: 26 | C31: TE | D31: Ranga Reddy | E31: =SUM(G31:I31) -> 5 | F31: =SUMIFS('CBG Plants'!N:N,'CBG Plants'!F:F,D31,'CBG Plants'!L:L,"Completed") +SUMIFS('CBG Plants'!N:N,'CBG Plants'!F:F,D31,'CBG Plants'!L:L,"Functional")+SUMIFS('CBG Plants'!N:N,'CBG Plants'!F:F,D31,'CBG Plants'!L:L,"Under Construction")+SUMIFS('CBG Plants'!N:N,'CBG Plants'!F:F,D31,'CBG Plants'!L:L,"Yet to start construction") -> 32.4 | G31: =COUNTIFS('CBG Plants'!F:F,D31,'CBG Plants'!L:L,"Completed") +COUNTIFS('CBG Plants'!F:F,D31,'CBG Plants'!L:L,"Functional") -> 1 | H31: =COUNTIFS('CBG Plants'!F:F,D31,'CBG Plants'!L:L,"Under Construction") -> 1 | I31: =COUNTIFS('CBG Plants'!F:F,D31,'CBG Plants'!L:L,"Yet to start construction") -> 3 | J31: BLUELEO-01 | K31: Blue leo by bia green pvt ltd | M31: =IFERROR(N31-(AD31*365/1000),"") -> 194.355 | N31: =SUM(O31:Q31) -> 194.355 | O31: 0 | P31: 133.98 | Q31: 60.375 | R31: =IFERROR(U31-F31,"") -> -31.62784 | S31: =IFERROR(T31*Assumptions!$C$4,"") -> 25 | T31: 10 | U31: =IFERROR(S31*Assumptions!$C$5,"")+IFERROR(V31*Assumptions!$C$8*Assumptions!$C$5,"") -> 0.77216025 | V31: 2205 | W31: =IFERROR(ROUND(T31*(1+Assumptions!$C$7)^5,0),"") -> 31 | X31: =IFERROR(ROUND(W31*Assumptions!$C$4*Assumptions!$C$6,4),"")+IFERROR(ROUND(Y31*Assumptions!$C$8*Assumptions!$C$6,4),"") - F31 -> -28.4123 | Y31: =IFERROR(ROUND(V31*(1+Assumptions!$C$7)^5,0),"") -> 6729 | Z31: Operational Common Carrier | AA31: Kakinada-Hyderabad-Uran-Ahmedabad (East West Pipeline) | AB31: 29.1 | AC31: 85 | AD31: 0 | AE31: =IF(R31="","",IF(R31>=Control!$D$4,"Y","N")) -> N | AF31: =IF(S31="","",IF(M31>=Control!$D$5,"Y","N")) -> Y | AG31: =IF(T31="","",IF(AB31<=Control!$D$10,"Y","N")) -> Y | AI31: =IF(X31="","",IF(X31>=Control!$D$9,"Y","N")) -> N | AK31: =IFERROR(INDEX(Assumptions!$D$92:$D$115,MATCH(C31,Assumptions!$B$92:$B$115,0)),"Low") -> Low
B32: 32 | C32: TE | D32: Warangal | E32: =SUM(G32:I32) -> 2 | F32: =SUMIFS('CBG Plants'!N:N,'CBG Plants'!F:F,D32,'CBG Plants'!L:L,"Completed") +SUMIFS('CBG Plants'!N:N,'CBG Plants'!F:F,D32,'CBG Plants'!L:L,"Functional")+SUMIFS('CBG Plants'!N:N,'CBG Plants'!F:F,D32,'CBG Plants'!L:L,"Under Construction")+SUMIFS('CBG Plants'!N:N,'CBG Plants'!F:F,D32,'CBG Plants'!L:L,"Yet to start construction") -> 32 | G32: =COUNTIFS('CBG Plants'!F:F,D32,'CBG Plants'!L:L,"Completed") +COUNTIFS('CBG Plants'!F:F,D32,'CBG Plants'!L:L,"Functional") -> 0 | H32: =COUNTIFS('CBG Plants'!F:F,D32,'CBG Plants'!L:L,"Under Construction") -> 0 | I32: =COUNTIFS('CBG Plants'!F:F,D32,'CBG Plants'!L:L,"Yet to start construction") -> 2 | J32: Compressed Bio Gas plant | K32: Raja Rajeshwara Impx Private Limited | M32: =IFERROR(N32-(AD32*365/1000),"") -> 290.535 | N32: =SUM(O32:Q32) -> 290.535 | O32: 0 | P32: 133.56 | Q32: 156.975 | R32: =IFERROR(U32-F32,"") -> -31.684533 | S32: =IFERROR(T32*Assumptions!$C$4,"") -> 10 | T32: 4 | U32: =IFERROR(S32*Assumptions!$C$5,"")+IFERROR(V32*Assumptions!$C$8*Assumptions!$C$5,"") -> 0.31546695 | V32: 1539 | W32: =IFERROR(ROUND(T32*(1+Assumptions!$C$7)^5,0),"") -> 12 | X32: =IFERROR(ROUND(W32*Assumptions!$C$4*Assumptions!$C$6,4),"")+IFERROR(ROUND(Y32*Assumptions!$C$8*Assumptions!$C$6,4),"") - F32 -> -30.4213 | Y32: =IFERROR(ROUND(V32*(1+Assumptions!$C$7)^5,0),"") -> 4697 | Z32: Operational Common Carrier | AA32: Kakinada-Hyderabad-Uran-Ahmedabad (East West Pipeline) | AB32: 67.6 | AC32: 85 | AD32: 0 | AE32: =IF(R32="","",IF(R32>=Control!$D$4,"Y","N")) -> N | AF32: =IF(S32="","",IF(M32>=Control!$D$5,"Y","N")) -> Y | AG32: =IF(T32="","",IF(AB32<=Control!$D$10,"Y","N")) -> Y | AI32: =IF(X32="","",IF(X32>=Control!$D$9,"Y","N")) -> N | AK32: =IFERROR(INDEX(Assumptions!$D$92:$D$115,MATCH(C32,Assumptions!$B$92:$B$115,0)),"Low") -> Low
B33: 3 | C33: TE | D33: Hanumakonda | E33: =SUM(G33:I33) -> 2 | F33: =SUMIFS('CBG Plants'!N:N,'CBG Plants'!F:F,D33,'CBG Plants'!L:L,"Completed") +SUMIFS('CBG Plants'!N:N,'CBG Plants'!F:F,D33,'CBG Plants'!L:L,"Functional")+SUMIFS('CBG Plants'!N:N,'CBG Plants'!F:F,D33,'CBG Plants'!L:L,"Under Construction")+SUMIFS('CBG Plants'!N:N,'CBG Plants'!F:F,D33,'CBG Plants'!L:L,"Yet to start construction") -> 33 | G33: =COUNTIFS('CBG Plants'!F:F,D33,'CBG Plants'!L:L,"Completed") +COUNTIFS('CBG Plants'!F:F,D33,'CBG Plants'!L:L,"Functional") -> 0 | H33: =COUNTIFS('CBG Plants'!F:F,D33,'CBG Plants'!L:L,"Under Construction") -> 1 | I33: =COUNTIFS('CBG Plants'!F:F,D33,'CBG Plants'!L:L,"Yet to start construction") -> 1 | J33: Warangal CBG Plant | K33: Leafera Energy | M33: =IFERROR(N33-(AD33*365/1000),"") -> 242.76 | N33: =SUM(O33:Q33) -> 242.76 | O33: 0 | P33: 148.26 | Q33: 94.5 | R33: =IFERROR(U33-F33,"") -> -33 | S33: =IFERROR(T33*Assumptions!$C$4,"") -> 0 | T33: 0 | U33: =IFERROR(S33*Assumptions!$C$5,"")+IFERROR(V33*Assumptions!$C$8*Assumptions!$C$5,"") -> 0 | V33: 0 | W33: =IFERROR(ROUND(T33*(1+Assumptions!$C$7)^5,0),"") -> 0 | X33: =IFERROR(ROUND(W33*Assumptions!$C$4*Assumptions!$C$6,4),"")+IFERROR(ROUND(Y33*Assumptions!$C$8*Assumptions!$C$6,4),"") - F33 -> -33 | Y33: =IFERROR(ROUND(V33*(1+Assumptions!$C$7)^5,0),"") -> 0 | Z33: Operational Common Carrier | AA33: Kakinada-Hyderabad-Uran-Ahmedabad (East West Pipeline) | AB33: 86.6 | AC33: 85 | AD33: 0 | AE33: =IF(R33="","",IF(R33>=Control!$D$4,"Y","N")) -> N | AF33: =IF(S33="","",IF(M33>=Control!$D$5,"Y","N")) -> Y | AG33: =IF(T33="","",IF(AB33<=Control!$D$10,"Y","N")) -> Y | AI33: =IF(X33="","",IF(X33>=Control!$D$9,"Y","N")) -> N | AK33: =IFERROR(INDEX(Assumptions!$D$92:$D$115,MATCH(C33,Assumptions!$B$92:$B$115,0)),"Low") -> Low
B34: 33 | C34: TE | D34: Yadadri Bhuvanagiri | E34: =SUM(G34:I34) -> 4 | F34: =SUMIFS('CBG Plants'!N:N,'CBG Plants'!F:F,D34,'CBG Plants'!L:L,"Completed") +SUMIFS('CBG Plants'!N:N,'CBG Plants'!F:F,D34,'CBG Plants'!L:L,"Functional")+SUMIFS('CBG Plants'!N:N,'CBG Plants'!F:F,D34,'CBG Plants'!L:L,"Under Construction")+SUMIFS('CBG Plants'!N:N,'CBG Plants'!F:F,D34,'CBG Plants'!L:L,"Yet to start construction") -> 39 | G34: =COUNTIFS('CBG Plants'!F:F,D34,'CBG Plants'!L:L,"Completed") +COUNTIFS('CBG Plants'!F:F,D34,'CBG Plants'!L:L,"Functional") -> 0 | H34: =COUNTIFS('CBG Plants'!F:F,D34,'CBG Plants'!L:L,"Under Construction") -> 1 | I34: =COUNTIFS('CBG Plants'!F:F,D34,'CBG Plants'!L:L,"Yet to start construction") -> 3 | J34: ARK BIO ENERGY PRIVATE LIMITED | K34: Shree Kala Meenakshi Agro Pvt Ltd | L34: Agriwaste Based CBG plant | M34: =IFERROR(N34-(AD34*365/1000),"") -> 338.205 | N34: =SUM(O34:Q34) -> 338.205 | O34: 0 | P34: 337.68 | Q34: 0.525 | R34: =IFERROR(U34-F34,"") -> -38.453724 | S34: =IFERROR(T34*Assumptions!$C$4,"") -> 17.5 | T34: 7 | U34: =IFERROR(S34*Assumptions!$C$5,"")+IFERROR(V34*Assumptions!$C$8*Assumptions!$C$5,"") -> 0.54627585 | V34: 2117 | W34: =IFERROR(ROUND(T34*(1+Assumptions!$C$7)^5,0),"") -> 21 | X34: =IFERROR(ROUND(W34*Assumptions!$C$4*Assumptions!$C$6,4),"")+IFERROR(ROUND(Y34*Assumptions!$C$8*Assumptions!$C$6,4),"") - F34 -> -36.2668 | Y34: =IFERROR(ROUND(V34*(1+Assumptions!$C$7)^5,0),"") -> 6461 | Z34: Operational Common Carrier | AA34: Kakinada-Hyderabad-Uran-Ahmedabad (East West Pipeline) | AB34: 13.7 | AC34: 85 | AD34: 0 | AE34: =IF(R34="","",IF(R34>=Control!$D$4,"Y","N")) -> N | AF34: =IF(S34="","",IF(M34>=Control!$D$5,"Y","N")) -> Y | AG34: =IF(T34="","",IF(AB34<=Control!$D$10,"Y","N")) -> Y | AI34: =IF(X34="","",IF(X34>=Control!$D$9,"Y","N")) -> N | AK34: =IFERROR(INDEX(Assumptions!$D$92:$D$115,MATCH(C34,Assumptions!$B$92:$B$115,0)),"Low") -> Low
B35: 20 | C35: TE | D35: Nalgonda | E35: =SUM(G35:I35) -> 5 | F35: =SUMIFS('CBG Plants'!N:N,'CBG Plants'!F:F,D35,'CBG Plants'!L:L,"Completed") +SUMIFS('CBG Plants'!N:N,'CBG Plants'!F:F,D35,'CBG Plants'!L:L,"Functional")+SUMIFS('CBG Plants'!N:N,'CBG Plants'!F:F,D35,'CBG Plants'!L:L,"Under Construction")+SUMIFS('CBG Plants'!N:N,'CBG Plants'!F:F,D35,'CBG Plants'!L:L,"Yet to start construction") -> 50 | G35: =COUNTIFS('CBG Plants'!F:F,D35,'CBG Plants'!L:L,"Completed") +COUNTIFS('CBG Plants'!F:F,D35,'CBG Plants'!L:L,"Functional") -> 0 | H35: =COUNTIFS('CBG Plants'!F:F,D35,'CBG Plants'!L:L,"Under Construction") -> 0 | I35: =COUNTIFS('CBG Plants'!F:F,D35,'CBG Plants'!L:L,"Yet to start construction") -> 5 | J35: GOO GreeneX | K35: GREEN COSMIC BIO FUELS PRIVATE LIMITED | L35: GSR BIO ENERGY PRIVATE LIMITED | M35: =IFERROR(N35-(AD35*365/1000),"") -> 603.75 | N35: =SUM(O35:Q35) -> 603.75 | O35: 0 | P35: 602.7 | Q35: 1.05 | R35: =IFERROR(U35-F35,"") -> -49.453724 | S35: =IFERROR(T35*Assumptions!$C$4,"") -> 17.5 | T35: 7 | U35: =IFERROR(S35*Assumptions!$C$5,"")+IFERROR(V35*Assumptions!$C$8*Assumptions!$C$5,"") -> 0.54627585 | V35: 2117 | W35: =IFERROR(ROUND(T35*(1+Assumptions!$C$7)^5,0),"") -> 21 | X35: =IFERROR(ROUND(W35*Assumptions!$C$4*Assumptions!$C$6,4),"")+IFERROR(ROUND(Y35*Assumptions!$C$8*Assumptions!$C$6,4),"") - F35 -> -47.2668 | Y35: =IFERROR(ROUND(V35*(1+Assumptions!$C$7)^5,0),"") -> 6461 | Z35: Operational Common Carrier | AA35: Kakinada-Hyderabad-Uran-Ahmedabad (East West Pipeline) | AB35: 47.7 | AC35: 85 | AD35: 0 | AE35: =IF(R35="","",IF(R35>=Control!$D$4,"Y","N")) -> N | AF35: =IF(S35="","",IF(M35>=Control!$D$5,"Y","N")) -> Y | AG35: =IF(T35="","",IF(AB35<=Control!$D$10,"Y","N")) -> Y | AI35: =IF(X35="","",IF(X35>=Control!$D$9,"Y","N")) -> N | AK35: =IFERROR(INDEX(Assumptions!$D$92:$D$115,MATCH(C35,Assumptions!$B$92:$B$115,0)),"Low") -> Low
B36: 17 | C36: TE | D36: Medchal Malkajgiri | E36: =SUM(G36:I36) -> 3 | F36: =SUMIFS('CBG Plants'!N:N,'CBG Plants'!F:F,D36,'CBG Plants'!L:L,"Completed") +SUMIFS('CBG Plants'!N:N,'CBG Plants'!F:F,D36,'CBG Plants'!L:L,"Functional")+SUMIFS('CBG Plants'!N:N,'CBG Plants'!F:F,D36,'CBG Plants'!L:L,"Under Construction")+SUMIFS('CBG Plants'!N:N,'CBG Plants'!F:F,D36,'CBG Plants'!L:L,"Yet to start construction") -> 76.4 | G36: =COUNTIFS('CBG Plants'!F:F,D36,'CBG Plants'!L:L,"Completed") +COUNTIFS('CBG Plants'!F:F,D36,'CBG Plants'!L:L,"Functional") -> 1 | H36: =COUNTIFS('CBG Plants'!F:F,D36,'CBG Plants'!L:L,"Under Construction") -> 0 | I36: =COUNTIFS('CBG Plants'!F:F,D36,'CBG Plants'!L:L,"Yet to start construction") -> 2 | J36: RED Hyderabad CBG Project | K36: EcoGas Renewables | L36: 5.4 TPD OF CAPACITY COMPRESSED BIOGAS GENERATION FROM 750 M3 PER DAY LANDFILL GAS (BIOGAS) COLLECTIO | M36: =IFERROR(N36-(AD36*365/1000),"") -> 19.845 | N36: =SUM(O36:Q36) -> 19.845 | O36: 0 | P36: 19.32 | Q36: 0.525 | R36: =IFERROR(U36-F36,"") -> -75.62784 | S36: =IFERROR(T36*Assumptions!$C$4,"") -> 25 | T36: 10 | U36: =IFERROR(S36*Assumptions!$C$5,"")+IFERROR(V36*Assumptions!$C$8*Assumptions!$C$5,"") -> 0.77216025 | V36: 2205 | W36: =IFERROR(ROUND(T36*(1+Assumptions!$C$7)^5,0),"") -> 31 | X36: =IFERROR(ROUND(W36*Assumptions!$C$4*Assumptions!$C$6,4),"")+IFERROR(ROUND(Y36*Assumptions!$C$8*Assumptions!$C$6,4),"") - F36 -> -72.4123 | Y36: =IFERROR(ROUND(V36*(1+Assumptions!$C$7)^5,0),"") -> 6729 | Z36: Operational Common Carrier | AA36: Kakinada-Hyderabad-Uran-Ahmedabad (East West Pipeline) | AB36: 18.4 | AC36: 85 | AD36: 0 | AE36: =IF(R36="","",IF(R36>=Control!$D$4,"Y","N")) -> N | AF36: =IF(S36="","",IF(M36>=Control!$D$5,"Y","N")) -> N | AG36: =IF(T36="","",IF(AB36<=Control!$D$10,"Y","N")) -> Y | AI36: =IF(X36="","",IF(X36>=Control!$D$9,"Y","N")) -> N | AK36: =IFERROR(INDEX(Assumptions!$D$92:$D$115,MATCH(C36,Assumptions!$B$92:$B$115,0)),"Low") -> Low
B37: 34 | C37: GJ | D37: Ahmedabad | E37: =SUM(G37:I37) -> 4 | F37: =SUMIFS('CBG Plants'!N:N,'CBG Plants'!F:F,D37,'CBG Plants'!L:L,"Completed") +SUMIFS('CBG Plants'!N:N,'CBG Plants'!F:F,D37,'CBG Plants'!L:L,"Functional")+SUMIFS('CBG Plants'!N:N,'CBG Plants'!F:F,D37,'CBG Plants'!L:L,"Under Construction")+SUMIFS('CBG Plants'!N:N,'CBG Plants'!F:F,D37,'CBG Plants'!L:L,"Yet to start construction") -> 20.8 | G37: =COUNTIFS('CBG Plants'!F:F,D37,'CBG Plants'!L:L,"Completed") +COUNTIFS('CBG Plants'!F:F,D37,'CBG Plants'!L:L,"Functional") -> 2 | H37: =COUNTIFS('CBG Plants'!F:F,D37,'CBG Plants'!L:L,"Under Construction") -> 1 | I37: =COUNTIFS('CBG Plants'!F:F,D37,'CBG Plants'!L:L,"Yet to start construction") -> 1 | J37: CEF Ahmedabad Cleaneffentech Private Limited | K37: Miracles Agrigreen Solutions Pvt. Ltd. | L37: AGRICULTURE PRODUCE MARKET COMMITTEE | M37: =IFERROR(N37-(AD37*365/1000),"") -> 261.17 | N37: =SUM(O37:Q37) -> 345.12 | O37: 143.1 | P37: 202.02 | Q37: 0 | R37: =IFERROR(U37-F37,"") -> -3.9558217 | S37: =IFERROR(T37*Assumptions!$C$4,"") -> 290 | T37: 116 | U37: =IFERROR(S37*Assumptions!$C$5,"")+IFERROR(V37*Assumptions!$C$8*Assumptions!$C$5,"") -> 16.844178 | V37: 810366 | W37: =IFERROR(ROUND(T37*(1+Assumptions!$C$7)^5,0),"") -> 354 | X37: =IFERROR(ROUND(W37*Assumptions!$C$4*Assumptions!$C$6,4),"")+IFERROR(ROUND(Y37*Assumptions!$C$8*Assumptions!$C$6,4),"") - F37 -> 64.8734 | Y37: =IFERROR(ROUND(V37*(1+Assumptions!$C$7)^5,0),"") -> 2473041 | Z37: Operational Common Carrier | AA37: High Pressure Gujarat Gas Grid | AB37: 45.1 | AC37: 44.8 | AD37: 230 | AE37: =IF(R37="","",IF(R37>=Control!$D$4,"Y","N")) -> N | AF37: =IF(S37="","",IF(M37>=Control!$D$5,"Y","N")) -> Y | AG37: =IF(T37="","",IF(AB37<=Control!$D$10,"Y","N")) -> Y | AI37: =IF(X37="","",IF(X37>=Control!$D$9,"Y","N")) -> Y | AK37: =IFERROR(INDEX(Assumptions!$D$92:$D$115,MATCH(C37,Assumptions!$B$92:$B$115,0)),"Low") -> High
B38: 35 | C38: GJ | D38: Amreli | E38: =SUM(G38:I38) -> 1 | F38: =SUMIFS('CBG Plants'!N:N,'CBG Plants'!F:F,D38,'CBG Plants'!L:L,"Completed") +SUMIFS('CBG Plants'!N:N,'CBG Plants'!F:F,D38,'CBG Plants'!L:L,"Functional")+SUMIFS('CBG Plants'!N:N,'CBG Plants'!F:F,D38,'CBG Plants'!L:L,"Under Construction")+SUMIFS('CBG Plants'!N:N,'CBG Plants'!F:F,D38,'CBG Plants'!L:L,"Yet to start construction") -> 3 | G38: =COUNTIFS('CBG Plants'!F:F,D38,'CBG Plants'!L:L,"Completed") +COUNTIFS('CBG Plants'!F:F,D38,'CBG Plants'!L:L,"Functional") -> 0 | H38: =COUNTIFS('CBG Plants'!F:F,D38,'CBG Plants'!L:L,"Under Construction") -> 0 | I38: =COUNTIFS('CBG Plants'!F:F,D38,'CBG Plants'!L:L,"Yet to start construction") -> 1 | J38: ADISHYAM BIOTECH PRIVATE LIMITED | M38: =IFERROR(N38-(AD38*365/1000),"") -> 67.5 | N38: =SUM(O38:Q38) -> 67.5 | O38: 67.5 | P38: 0 | Q38: 0 | R38: =IFERROR(U38-F38,"") -> -1.6756683 | S38: =IFERROR(T38*Assumptions!$C$4,"") -> 37.5 | T38: 15 | U38: =IFERROR(S38*Assumptions!$C$5,"")+IFERROR(V38*Assumptions!$C$8*Assumptions!$C$5,"") -> 1.3243317 | V38: 19834 | W38: =IFERROR(ROUND(T38*(1+Assumptions!$C$7)^5,0),"") -> 46 | X38: =IFERROR(ROUND(W38*Assumptions!$C$4*Assumptions!$C$6,4),"")+IFERROR(ROUND(Y38*Assumptions!$C$8*Assumptions!$C$6,4),"") - F38 -> 3.7639 | Y38: =IFERROR(ROUND(V38*(1+Assumptions!$C$7)^5,0),"") -> 60529 | Z38: Operational Common Carrier | AA38: High Pressure Gujarat Gas Grid | AB38: 138.1 | AC38: 44.8 | AD38: 0 | AE38: =IF(R38="","",IF(R38>=Control!$D$4,"Y","N")) -> N | AF38: =IF(S38="","",IF(M38>=Control!$D$5,"Y","N")) -> Y | AG38: =IF(T38="","",IF(AB38<=Control!$D$10,"Y","N")) -> Y | AI38: =IF(X38="","",IF(X38>=Control!$D$9,"Y","N")) -> N | AK38: =IFERROR(INDEX(Assumptions!$D$92:$D$115,MATCH(C38,Assumptions!$B$92:$B$115,0)),"Low") -> High
B39: 36 | C39: GJ | D39: Anand | E39: =SUM(G39:I39) -> 3 | F39: =SUMIFS('CBG Plants'!N:N,'CBG Plants'!F:F,D39,'CBG Plants'!L:L,"Completed") +SUMIFS('CBG Plants'!N:N,'CBG Plants'!F:F,D39,'CBG Plants'!L:L,"Functional")+SUMIFS('CBG Plants'!N:N,'CBG Plants'!F:F,D39,'CBG Plants'!L:L,"Under Construction")+SUMIFS('CBG Plants'!N:N,'CBG Plants'!F:F,D39,'CBG Plants'!L:L,"Yet to start construction") -> 22 | G39: =COUNTIFS('CBG Plants'!F:F,D39,'CBG Plants'!L:L,"Completed") +COUNTIFS('CBG Plants'!F:F,D39,'CBG Plants'!L:L,"Functional") -> 1 | H39: =COUNTIFS('CBG Plants'!F:F,D39,'CBG Plants'!L:L,"Under Construction") -> 1 | I39: =COUNTIFS('CBG Plants'!F:F,D39,'CBG Plants'!L:L,"Yet to start construction") -> 1 | J39: Bharat Biogas Energy Limited | K39: SARDAR SENDRIYA FERTILIZER | L39: SHREE HARI CBG PRIVATE LIMITED | M39: =IFERROR(N39-(AD39*365/1000),"") -> 160.17 | N39: =SUM(O39:Q39) -> 203.97 | O39: 41.85 | P39: 162.12 | Q39: 0 | R39: =IFERROR(U39-F39,"") -> -18.46315 | S39: =IFERROR(T39*Assumptions!$C$4,"") -> 92.5 | T39: 37 | U39: =IFERROR(S39*Assumptions!$C$5,"")+IFERROR(V39*Assumptions!$C$8*Assumptions!$C$5,"") -> 3.5368503 | V39: 75806 | W39: =IFERROR(ROUND(T39*(1+Assumptions!$C$7)^5,0),"") -> 113 | X39: =IFERROR(ROUND(W39*Assumptions!$C$4*Assumptions!$C$6,4),"")+IFERROR(ROUND(Y39*Assumptions!$C$8*Assumptions!$C$6,4),"") - F39 -> -4 | Y39: =IFERROR(ROUND(V39*(1+Assumptions!$C$7)^5,0),"") -> 231342 | Z39: Operational Common Carrier | AA39: High Pressure Gujarat Gas Grid | AB39: 31.4 | AC39: 44.8 | AD39: 120 | AE39: =IF(R39="","",IF(R39>=Control!$D$4,"Y","N")) -> N | AF39: =IF(S39="","",IF(M39>=Control!$D$5,"Y","N")) -> Y | AG39: =IF(T39="","",IF(AB39<=Control!$D$10,"Y","N")) -> Y | AI39: =IF(X39="","",IF(X39>=Control!$D$9,"Y","N")) -> N | AK39: =IFERROR(INDEX(Assumptions!$D$92:$D$115,MATCH(C39,Assumptions!$B$92:$B$115,0)),"Low") -> High
B40: 37 | C40: GJ | D40: Arvalli | E40: =SUM(G40:I40) -> 0 | F40: =SUMIFS('CBG Plants'!N:N,'CBG Plants'!F:F,D40,'CBG Plants'!L:L,"Completed") +SUMIFS('CBG Plants'!N:N,'CBG Plants'!F:F,D40,'CBG Plants'!L:L,"Functional")+SUMIFS('CBG Plants'!N:N,'CBG Plants'!F:F,D40,'CBG Plants'!L:L,"Under Construction")+SUMIFS('CBG Plants'!N:N,'CBG Plants'!F:F,D40,'CBG Plants'!L:L,"Yet to start construction") -> 0 | G40: =COUNTIFS('CBG Plants'!F:F,D40,'CBG Plants'!L:L,"Completed") +COUNTIFS('CBG Plants'!F:F,D40,'CBG Plants'!L:L,"Functional") -> 0 | H40: =COUNTIFS('CBG Plants'!F:F,D40,'CBG Plants'!L:L,"Under Construction") -> 0 | I40: =COUNTIFS('CBG Plants'!F:F,D40,'CBG Plants'!L:L,"Yet to start construction") -> 0 | J40: Milestone CBG Plant | K40: SHIV BIO GAS PRIVATE LIMITED | M40: =IFERROR(N40-(AD40*365/1000),"") -> 155.19 | N40: =SUM(O40:Q40) -> 155.19 | O40: 94.5 | P40: 0.84 | Q40: 59.85 | R40: =IFERROR(U40-F40,"") -> 0 | S40: =IFERROR(T40*Assumptions!$C$4,"") -> 0 | T40: 0 | U40: =IFERROR(S40*Assumptions!$C$5,"")+IFERROR(V40*Assumptions!$C$8*Assumptions!$C$5,"") -> 0 | V40: 0 | W40: =IFERROR(ROUND(T40*(1+Assumptions!$C$7)^5,0),"") -> 0 | X40: =IFERROR(ROUND(W40*Assumptions!$C$4*Assumptions!$C$6,4),"")+IFERROR(ROUND(Y40*Assumptions!$C$8*Assumptions!$C$6,4),"") - F40 -> 0 | Y40: =IFERROR(ROUND(V40*(1+Assumptions!$C$7)^5,0),"") -> 0 | Z40: Operational Common Carrier | AA40: High Pressure Gujarat Gas Grid | AB40: 78 | AC40: 44.8 | AD40: 0 | AE40: =IF(R40="","",IF(R40>=Control!$D$4,"Y","N")) -> N | AF40: =IF(S40="","",IF(M40>=Control!$D$5,"Y","N")) -> Y | AG40: =IF(T40="","",IF(AB40<=Control!$D$10,"Y","N")) -> Y | AI40: =IF(X40="","",IF(X40>=Control!$D$9,"Y","N")) -> N | AK40: =IFERROR(INDEX(Assumptions!$D$92:$D$115,MATCH(C40,Assumptions!$B$92:$B$115,0)),"Low") -> High
B41: 38 | C41: GJ | D41: Banas Kantha | E41: =SUM(G41:I41) -> 5 | F41: =SUMIFS('CBG Plants'!N:N,'CBG Plants'!F:F,D41,'CBG Plants'!L:L,"Completed") +SUMIFS('CBG Plants'!N:N,'CBG Plants'!F:F,D41,'CBG Plants'!L:L,"Functional")+SUMIFS('CBG Plants'!N:N,'CBG Plants'!F:F,D41,'CBG Plants'!L:L,"Under Construction")+SUMIFS('CBG Plants'!N:N,'CBG Plants'!F:F,D41,'CBG Plants'!L:L,"Yet to start construction") -> 11.8 | G41: =COUNTIFS('CBG Plants'!F:F,D41,'CBG Plants'!L:L,"Completed") +COUNTIFS('CBG Plants'!F:F,D41,'CBG Plants'!L:L,"Functional") -> 1 | H41: =COUNTIFS('CBG Plants'!F:F,D41,'CBG Plants'!L:L,"Under Construction") -> 2 | I41: =COUNTIFS('CBG Plants'!F:F,D41,'CBG Plants'!L:L,"Yet to start construction") -> 2 | J41: Milestone CBG Plant | K41: Kahnavi Agro Seeds | L41: BANAS SUZUKI BIOGAS PLANT - 100 MTPD Dung based CBG plant at Agthala Village, Lakhni | M41: =IFERROR(N41-(AD41*365/1000),"") -> 83.8 | N41: =SUM(O41:Q41) -> 98.4 | O41: 80.55 | P41: 0 | Q41: 17.85 | R41: =IFERROR(U41-F41,"") -> -6.044931 | S41: =IFERROR(T41*Assumptions!$C$4,"") -> 170 | T41: 68 | U41: =IFERROR(S41*Assumptions!$C$5,"")+IFERROR(V41*Assumptions!$C$8*Assumptions!$C$5,"") -> 5.755069 | V41: 65181 | W41: =IFERROR(ROUND(T41*(1+Assumptions!$C$7)^5,0),"") -> 208 | X41: =IFERROR(ROUND(W41*Assumptions!$C$4*Assumptions!$C$6,4),"")+IFERROR(ROUND(Y41*Assumptions!$C$8*Assumptions!$C$6,4),"") - F41 -> 17.5319 | Y41: =IFERROR(ROUND(V41*(1+Assumptions!$C$7)^5,0),"") -> 198917 | Z41: Operational Common Carrier | AA41: High Pressure Gujarat Gas Grid | AB41: 85.1 | AC41: 44.8 | AD41: 40 | AE41: =IF(R41="","",IF(R41>=Control!$D$4,"Y","N")) -> N | AF41: =IF(S41="","",IF(M41>=Control!$D$5,"Y","N")) -> Y | AG41: =IF(T41="","",IF(AB41<=Control!$D$10,"Y","N")) -> Y | AI41: =IF(X41="","",IF(X41>=Control!$D$9,"Y","N")) -> Y | AK41: =IFERROR(INDEX(Assumptions!$D$92:$D$115,MATCH(C41,Assumptions!$B$92:$B$115,0)),"Low") -> High
B42: 39 | C42: GJ | D42: Bharuch | E42: =SUM(G42:I42) -> 8 | F42: =SUMIFS('CBG Plants'!N:N,'CBG Plants'!F:F,D42,'CBG Plants'!L:L,"Completed") +SUMIFS('CBG Plants'!N:N,'CBG Plants'!F:F,D42,'CBG Plants'!L:L,"Functional")+SUMIFS('CBG Plants'!N:N,'CBG Plants'!F:F,D42,'CBG Plants'!L:L,"Under Construction")+SUMIFS('CBG Plants'!N:N,'CBG Plants'!F:F,D42,'CBG Plants'!L:L,"Yet to start construction") -> 59.028 | G42: =COUNTIFS('CBG Plants'!F:F,D42,'CBG Plants'!L:L,"Completed") +COUNTIFS('CBG Plants'!F:F,D42,'CBG Plants'!L:L,"Functional") -> 3 | H42: =COUNTIFS('CBG Plants'!F:F,D42,'CBG Plants'!L:L,"Under Construction") -> 2 | I42: =COUNTIFS('CBG Plants'!F:F,D42,'CBG Plants'!L:L,"Yet to start construction") -> 3 | J42: CBG - JAMBUSAR | K42: Laxmi enterprise | L42: Ankleshwar BioCNG | M42: =IFERROR(N42-(AD42*365/1000),"") -> -146.77 | N42: =SUM(O42:Q42) -> 35.73 | O42: 16.2 | P42: 18.48 | Q42: 1.05 | R42: =IFERROR(U42-F42,"") -> -49.829565 | S42: =IFERROR(T42*Assumptions!$C$4,"") -> 150 | T42: 60 | U42: =IFERROR(S42*Assumptions!$C$5,"")+IFERROR(V42*Assumptions!$C$8*Assumptions!$C$5,"") -> 9.1984353 | V42: 467506 | W42: =IFERROR(ROUND(T42*(1+Assumptions!$C$7)^5,0),"") -> 183 | X42: =IFERROR(ROUND(W42*Assumptions!$C$4*Assumptions!$C$6,4),"")+IFERROR(ROUND(Y42*Assumptions!$C$8*Assumptions!$C$6,4),"") - F42 -> -12.2555 | Y42: =IFERROR(ROUND(V42*(1+Assumptions!$C$7)^5,0),"") -> 1426715 | Z42: Operational Common Carrier | AA42: High Pressure Gujarat Gas Grid | AB42: 8.6 | AC42: 44.8 | AD42: 500 | AE42: =IF(R42="","",IF(R42>=Control!$D$4,"Y","N")) -> N | AF42: =IF(S42="","",IF(M42>=Control!$D$5,"Y","N")) -> N | AG42: =IF(T42="","",IF(AB42<=Control!$D$10,"Y","N")) -> Y | AI42: =IF(X42="","",IF(X42>=Control!$D$9,"Y","N")) -> N | AK42: =IFERROR(INDEX(Assumptions!$D$92:$D$115,MATCH(C42,Assumptions!$B$92:$B$115,0)),"Low") -> High
B43: 40 | C43: GJ | D43: Bhavnagar | E43: =SUM(G43:I43) -> 4 | F43: =SUMIFS('CBG Plants'!N:N,'CBG Plants'!F:F,D43,'CBG Plants'!L:L,"Completed") +SUMIFS('CBG Plants'!N:N,'CBG Plants'!F:F,D43,'CBG Plants'!L:L,"Functional")+SUMIFS('CBG Plants'!N:N,'CBG Plants'!F:F,D43,'CBG Plants'!L:L,"Under Construction")+SUMIFS('CBG Plants'!N:N,'CBG Plants'!F:F,D43,'CBG Plants'!L:L,"Yet to start construction") -> 9.8 | G43: =COUNTIFS('CBG Plants'!F:F,D43,'CBG Plants'!L:L,"Completed") +COUNTIFS('CBG Plants'!F:F,D43,'CBG Plants'!L:L,"Functional") -> 2 | H43: =COUNTIFS('CBG Plants'!F:F,D43,'CBG Plants'!L:L,"Under Construction") -> 0 | I43: =COUNTIFS('CBG Plants'!F:F,D43,'CBG Plants'!L:L,"Yet to start construction") -> 2 | J43: TIRUPATI BIOCNG AND FERTILIZER | K43: KAKADIYA GREENENERGY PRIVATE LIMITED | L43: SARVOPATI GREEN TECH PRIVATE LIMITED | M43: =IFERROR(N43-(AD43*365/1000),"") -> 15.95 | N43: =SUM(O43:Q43) -> 50.625 | O43: 49.05 | P43: 0 | Q43: 1.575 | R43: =IFERROR(U43-F43,"") -> -5.9010206 | S43: =IFERROR(T43*Assumptions!$C$4,"") -> 102.5 | T43: 41 | U43: =IFERROR(S43*Assumptions!$C$5,"")+IFERROR(V43*Assumptions!$C$8*Assumptions!$C$5,"") -> 3.8989794 | V43: 81988 | W43: =IFERROR(ROUND(T43*(1+Assumptions!$C$7)^5,0),"") -> 125 | X43: =IFERROR(ROUND(W43*Assumptions!$C$4*Assumptions!$C$6,4),"")+IFERROR(ROUND(Y43*Assumptions!$C$8*Assumptions!$C$6,4),"") - F43 -> 10.016 | Y43: =IFERROR(ROUND(V43*(1+Assumptions!$C$7)^5,0),"") -> 250208 | Z43: Operational Common Carrier | AA43: High Pressure Gujarat Gas Grid | AB43: 69.1 | AC43: 44.8 | AD43: 95 | AE43: =IF(R43="","",IF(R43>=Control!$D$4,"Y","N")) -> N | AF43: =IF(S43="","",IF(M43>=Control!$D$5,"Y","N")) -> N | AG43: =IF(T43="","",IF(AB43<=Control!$D$10,"Y","N")) -> Y | AI43: =IF(X43="","",IF(X43>=Control!$D$9,"Y","N")) -> Y | AK43: =IFERROR(INDEX(Assumptions!$D$92:$D$115,MATCH(C43,Assumptions!$B$92:$B$115,0)),"Low") -> High
B44: 41 | C44: GJ | D44: Botad | E44: =SUM(G44:I44) -> 3 | F44: =SUMIFS('CBG Plants'!N:N,'CBG Plants'!F:F,D44,'CBG Plants'!L:L,"Completed") +SUMIFS('CBG Plants'!N:N,'CBG Plants'!F:F,D44,'CBG Plants'!L:L,"Functional")+SUMIFS('CBG Plants'!N:N,'CBG Plants'!F:F,D44,'CBG Plants'!L:L,"Under Construction")+SUMIFS('CBG Plants'!N:N,'CBG Plants'!F:F,D44,'CBG Plants'!L:L,"Yet to start construction") -> 15 | G44: =COUNTIFS('CBG Plants'!F:F,D44,'CBG Plants'!L:L,"Completed") +COUNTIFS('CBG Plants'!F:F,D44,'CBG Plants'!L:L,"Functional") -> 0 | H44: =COUNTIFS('CBG Plants'!F:F,D44,'CBG Plants'!L:L,"Under Construction") -> 1 | I44: =COUNTIFS('CBG Plants'!F:F,D44,'CBG Plants'!L:L,"Yet to start construction") -> 2 | J44: Govimka Biotech CBG Plant | K44: RENEWSPHERE ENERGY LLP | L44: ZYDUS GREEN ENERGY CBG PLANT | M44: =IFERROR(N44-(AD44*365/1000),"") -> 33.3 | N44: =SUM(O44:Q44) -> 33.3 | O44: 33.3 | P44: 0 | Q44: 0 | R44: =IFERROR(U44-F44,"") -> -15 | S44: =IFERROR(T44*Assumptions!$C$4,"") -> 0 | T44: 0 | U44: =IFERROR(S44*Assumptions!$C$5,"")+IFERROR(V44*Assumptions!$C$8*Assumptions!$C$5,"") -> 0 | V44: 0 | W44: =IFERROR(ROUND(T44*(1+Assumptions!$C$7)^5,0),"") -> 0 | X44: =IFERROR(ROUND(W44*Assumptions!$C$4*Assumptions!$C$6,4),"")+IFERROR(ROUND(Y44*Assumptions!$C$8*Assumptions!$C$6,4),"") - F44 -> -15 | Y44: =IFERROR(ROUND(V44*(1+Assumptions!$C$7)^5,0),"") -> 0 | Z44: Operational Common Carrier | AA44: High Pressure Gujarat Gas Grid | AB44: 101 | AC44: 44.8 | AD44: 0 | AE44: =IF(R44="","",IF(R44>=Control!$D$4,"Y","N")) -> N | AF44: =IF(S44="","",IF(M44>=Control!$D$5,"Y","N")) -> N | AG44: =IF(T44="","",IF(AB44<=Control!$D$10,"Y","N")) -> Y | AI44: =IF(X44="","",IF(X44>=Control!$D$9,"Y","N")) -> N | AK44: =IFERROR(INDEX(Assumptions!$D$92:$D$115,MATCH(C44,Assumptions!$B$92:$B$115,0)),"Low") -> High
B45: 42 | C45: GJ | D45: Chhotaudepur | E45: =SUM(G45:I45) -> 0 | F45: =SUMIFS('CBG Plants'!N:N,'CBG Plants'!F:F,D45,'CBG Plants'!L:L,"Completed") +SUMIFS('CBG Plants'!N:N,'CBG Plants'!F:F,D45,'CBG Plants'!L:L,"Functional")+SUMIFS('CBG Plants'!N:N,'CBG Plants'!F:F,D45,'CBG Plants'!L:L,"Under Construction")+SUMIFS('CBG Plants'!N:N,'CBG Plants'!F:F,D45,'CBG Plants'!L:L,"Yet to start construction") -> 0 | G45: =COUNTIFS('CBG Plants'!F:F,D45,'CBG Plants'!L:L,"Completed") +COUNTIFS('CBG Plants'!F:F,D45,'CBG Plants'!L:L,"Functional") -> 0 | H45: =COUNTIFS('CBG Plants'!F:F,D45,'CBG Plants'!L:L,"Under Construction") -> 0 | I45: =COUNTIFS('CBG Plants'!F:F,D45,'CBG Plants'!L:L,"Yet to start construction") -> 0 | M45: =IFERROR(N45-(AD45*365/1000),"") -> 52.77 | N45: =SUM(O45:Q45) -> 52.77 | O45: 0.9 | P45: 10.92 | Q45: 40.95 | R45: =IFERROR(U45-F45,"") -> 0 | S45: =IFERROR(T45*Assumptions!$C$4,"") -> 0 | T45: 0 | U45: =IFERROR(S45*Assumptions!$C$5,"")+IFERROR(V45*Assumptions!$C$8*Assumptions!$C$5,"") -> 0 | V45: 0 | W45: =IFERROR(ROUND(T45*(1+Assumptions!$C$7)^5,0),"") -> 0 | X45: =IFERROR(ROUND(W45*Assumptions!$C$4*Assumptions!$C$6,4),"")+IFERROR(ROUND(Y45*Assumptions!$C$8*Assumptions!$C$6,4),"") - F45 -> 0 | Y45: =IFERROR(ROUND(V45*(1+Assumptions!$C$7)^5,0),"") -> 0 | Z45: Operational Common Carrier | AA45: High Pressure Gujarat Gas Grid | AB45: 72 | AC45: 44.8 | AD45: 0 | AE45: =IF(R45="","",IF(R45>=Control!$D$4,"Y","N")) -> N | AF45: =IF(S45="","",IF(M45>=Control!$D$5,"Y","N")) -> Y | AG45: =IF(T45="","",IF(AB45<=Control!$D$10,"Y","N")) -> Y | AI45: =IF(X45="","",IF(X45>=Control!$D$9,"Y","N")) -> N | AK45: =IFERROR(INDEX(Assumptions!$D$92:$D$115,MATCH(C45,Assumptions!$B$92:$B$115,0)),"Low") -> High
B46: 43 | C46: GJ | D46: Dahod | E46: =SUM(G46:I46) -> 0 | F46: =SUMIFS('CBG Plants'!N:N,'CBG Plants'!F:F,D46,'CBG Plants'!L:L,"Completed") +SUMIFS('CBG Plants'!N:N,'CBG Plants'!F:F,D46,'CBG Plants'!L:L,"Functional")+SUMIFS('CBG Plants'!N:N,'CBG Plants'!F:F,D46,'CBG Plants'!L:L,"Under Construction")+SUMIFS('CBG Plants'!N:N,'CBG Plants'!F:F,D46,'CBG Plants'!L:L,"Yet to start construction") -> 0 | G46: =COUNTIFS('CBG Plants'!F:F,D46,'CBG Plants'!L:L,"Completed") +COUNTIFS('CBG Plants'!F:F,D46,'CBG Plants'!L:L,"Functional") -> 0 | H46: =COUNTIFS('CBG Plants'!F:F,D46,'CBG Plants'!L:L,"Under Construction") -> 0 | I46: =COUNTIFS('CBG Plants'!F:F,D46,'CBG Plants'!L:L,"Yet to start construction") -> 0 | M46: =IFERROR(N46-(AD46*365/1000),"") -> 204.825 | N46: =SUM(O46:Q46) -> 204.825 | O46: 56.25 | P46: 29.4 | Q46: 119.175 | R46: =IFERROR(U46-F46,"") -> 1.5839207 | S46: =IFERROR(T46*Assumptions!$C$4,"") -> 47.5 | T46: 19 | U46: =IFERROR(S46*Assumptions!$C$5,"")+IFERROR(V46*Assumptions!$C$8*Assumptions!$C$5,"") -> 1.5839207 | V46: 15813 | W46: =IFERROR(ROUND(T46*(1+Assumptions!$C$7)^5,0),"") -> 58 | X46: =IFERROR(ROUND(W46*Assumptions!$C$4*Assumptions!$C$6,4),"")+IFERROR(ROUND(Y46*Assumptions!$C$8*Assumptions!$C$6,4),"") - F46 -> 8.0583 | Y46: =IFERROR(ROUND(V46*(1+Assumptions!$C$7)^5,0),"") -> 48257 | Z46: Operational Common Carrier | AA46: High Pressure Gujarat Gas Grid | AB46: 113.6 | AC46: 44.8 | AD46: 0 | AE46: =IF(R46="","",IF(R46>=Control!$D$4,"Y","N")) -> N | AF46: =IF(S46="","",IF(M46>=Control!$D$5,"Y","N")) -> Y | AG46: =IF(T46="","",IF(AB46<=Control!$D$10,"Y","N")) -> Y | AI46: =IF(X46="","",IF(X46>=Control!$D$9,"Y","N")) -> N | AK46: =IFERROR(INDEX(Assumptions!$D$92:$D$115,MATCH(C46,Assumptions!$B$92:$B$115,0)),"Low") -> High
B47: 44 | C47: GJ | D47: Dangs | E47: =SUM(G47:I47) -> 0 | F47: =SUMIFS('CBG Plants'!N:N,'CBG Plants'!F:F,D47,'CBG Plants'!L:L,"Completed") +SUMIFS('CBG Plants'!N:N,'CBG Plants'!F:F,D47,'CBG Plants'!L:L,"Functional")+SUMIFS('CBG Plants'!N:N,'CBG Plants'!F:F,D47,'CBG Plants'!L:L,"Under Construction")+SUMIFS('CBG Plants'!N:N,'CBG Plants'!F:F,D47,'CBG Plants'!L:L,"Yet to start construction") -> 0 | G47: =COUNTIFS('CBG Plants'!F:F,D47,'CBG Plants'!L:L,"Completed") +COUNTIFS('CBG Plants'!F:F,D47,'CBG Plants'!L:L,"Functional") -> 0 | H47: =COUNTIFS('CBG Plants'!F:F,D47,'CBG Plants'!L:L,"Under Construction") -> 0 | I47: =COUNTIFS('CBG Plants'!F:F,D47,'CBG Plants'!L:L,"Yet to start construction") -> 0 | M47: =IFERROR(N47-(AD47*365/1000),"") -> 19.425 | N47: =SUM(O47:Q47) -> 19.425 | O47: 0 | P47: 18.9 | Q47: 0.525 | R47: =IFERROR(U47-F47,"") -> 0.3200598 | S47: =IFERROR(T47*Assumptions!$C$4,"") -> 10 | T47: 4 | U47: =IFERROR(S47*Assumptions!$C$5,"")+IFERROR(V47*Assumptions!$C$8*Assumptions!$C$5,"") -> 0.3200598 | V47: 1996 | W47: =IFERROR(ROUND(T47*(1+Assumptions!$C$7)^5,0),"") -> 12 | X47: =IFERROR(ROUND(W47*Assumptions!$C$4*Assumptions!$C$6,4),"")+IFERROR(ROUND(Y47*Assumptions!$C$8*Assumptions!$C$6,4),"") - F47 -> 1.602 | Y47: =IFERROR(ROUND(V47*(1+Assumptions!$C$7)^5,0),"") -> 6091 | Z47: Operational Common Carrier | AA47: High Pressure Gujarat Gas Grid | AB47: 115.4 | AC47: 44.8 | AD47: 0 | AE47: =IF(R47="","",IF(R47>=Control!$D$4,"Y","N")) -> N | AF47: =IF(S47="","",IF(M47>=Control!$D$5,"Y","N")) -> N | AG47: =IF(T47="","",IF(AB47<=Control!$D$10,"Y","N")) -> Y | AI47: =IF(X47="","",IF(X47>=Control!$D$9,"Y","N")) -> N | AK47: =IFERROR(INDEX(Assumptions!$D$92:$D$115,MATCH(C47,Assumptions!$B$92:$B$115,0)),"Low") -> High
B48: 45 | C48: GJ | D48: Devbhumi Dwarka | E48: =SUM(G48:I48) -> 0 | F48: =SUMIFS('CBG Plants'!N:N,'CBG Plants'!F:F,D48,'CBG Plants'!L:L,"Completed") +SUMIFS('CBG Plants'!N:N,'CBG Plants'!F:F,D48,'CBG Plants'!L:L,"Functional")+SUMIFS('CBG Plants'!N:N,'CBG Plants'!F:F,D48,'CBG Plants'!L:L,"Under Construction")+SUMIFS('CBG Plants'!N:N,'CBG Plants'!F:F,D48,'CBG Plants'!L:L,"Yet to start construction") -> 0 | G48: =COUNTIFS('CBG Plants'!F:F,D48,'CBG Plants'!L:L,"Completed") +COUNTIFS('CBG Plants'!F:F,D48,'CBG Plants'!L:L,"Functional") -> 0 | H48: =COUNTIFS('CBG Plants'!F:F,D48,'CBG Plants'!L:L,"Under Construction") -> 0 | I48: =COUNTIFS('CBG Plants'!F:F,D48,'CBG Plants'!L:L,"Yet to start construction") -> 0 | M48: =IFERROR(N48-(AD48*365/1000),"") -> 20.7 | N48: =SUM(O48:Q48) -> 20.7 | O48: 20.7 | P48: 0 | Q48: 0 | R48: =IFERROR(U48-F48,"") -> 0 | S48: =IFERROR(T48*Assumptions!$C$4,"") -> 0 | T48: 0 | U48: =IFERROR(S48*Assumptions!$C$5,"")+IFERROR(V48*Assumptions!$C$8*Assumptions!$C$5,"") -> 0 | V48: 0 | W48: =IFERROR(ROUND(T48*(1+Assumptions!$C$7)^5,0),"") -> 0 | X48: =IFERROR(ROUND(W48*Assumptions!$C$4*Assumptions!$C$6,4),"")+IFERROR(ROUND(Y48*Assumptions!$C$8*Assumptions!$C$6,4),"") - F48 -> 0 | Y48: =IFERROR(ROUND(V48*(1+Assumptions!$C$7)^5,0),"") -> 0 | Z48: Operational Common Carrier | AA48: High Pressure Gujarat Gas Grid | AB48: 322.3 | AC48: 44.8 | AD48: 0 | AE48: =IF(R48="","",IF(R48>=Control!$D$4,"Y","N")) -> N | AF48: =IF(S48="","",IF(M48>=Control!$D$5,"Y","N")) -> N | AG48: =IF(T48="","",IF(AB48<=Control!$D$10,"Y","N")) -> Y | AI48: =IF(X48="","",IF(X48>=Control!$D$9,"Y","N")) -> N | AK48: =IFERROR(INDEX(Assumptions!$D$92:$D$115,MATCH(C48,Assumptions!$B$92:$B$115,0)),"Low") -> High
B49: 46 | C49: GJ | D49: Gandhinagar | E49: =SUM(G49:I49) -> 2 | F49: =SUMIFS('CBG Plants'!N:N,'CBG Plants'!F:F,D49,'CBG Plants'!L:L,"Completed") +SUMIFS('CBG Plants'!N:N,'CBG Plants'!F:F,D49,'CBG Plants'!L:L,"Functional")+SUMIFS('CBG Plants'!N:N,'CBG Plants'!F:F,D49,'CBG Plants'!L:L,"Under Construction")+SUMIFS('CBG Plants'!N:N,'CBG Plants'!F:F,D49,'CBG Plants'!L:L,"Yet to start construction") -> 3 | G49: =COUNTIFS('CBG Plants'!F:F,D49,'CBG Plants'!L:L,"Completed") +COUNTIFS('CBG Plants'!F:F,D49,'CBG Plants'!L:L,"Functional") -> 0 | H49: =COUNTIFS('CBG Plants'!F:F,D49,'CBG Plants'!L:L,"Under Construction") -> 0 | I49: =COUNTIFS('CBG Plants'!F:F,D49,'CBG Plants'!L:L,"Yet to start construction") -> 2 | J49: AXAYAH CLEAN-TECH PRIVATE LIMITED | K49: GMC Bio CNG Plant | M49: =IFERROR(N49-(AD49*365/1000),"") -> 51.81 | N49: =SUM(O49:Q49) -> 51.81 | O49: 40.05 | P49: 11.76 | Q49: 0 | R49: =IFERROR(U49-F49,"") -> 3.8257156 | S49: =IFERROR(T49*Assumptions!$C$4,"") -> 170 | T49: 68 | U49: =IFERROR(S49*Assumptions!$C$5,"")+IFERROR(V49*Assumptions!$C$8*Assumptions!$C$5,"") -> 6.8257156 | V49: 171713 | W49: =IFERROR(ROUND(T49*(1+Assumptions!$C$7)^5,0),"") -> 208 | X49: =IFERROR(ROUND(W49*Assumptions!$C$4*Assumptions!$C$6,4),"")+IFERROR(ROUND(Y49*Assumptions!$C$8*Assumptions!$C$6,4),"") - F49 -> 31.7774 | Y49: =IFERROR(ROUND(V49*(1+Assumptions!$C$7)^5,0),"") -> 524026 | Z49: Operational Common Carrier | AA49: High Pressure Gujarat Gas Grid | AB49: 9.8 | AC49: 44.8 | AD49: 0 | AE49: =IF(R49="","",IF(R49>=Control!$D$4,"Y","N")) -> Y | AF49: =IF(S49="","",IF(M49>=Control!$D$5,"Y","N")) -> Y | AG49: =IF(T49="","",IF(AB49<=Control!$D$10,"Y","N")) -> Y | AI49: =IF(X49="","",IF(X49>=Control!$D$9,"Y","N")) -> Y | AK49: =IFERROR(INDEX(Assumptions!$D$92:$D$115,MATCH(C49,Assumptions!$B$92:$B$115,0)),"Low") -> High
B50: 47 | C50: GJ | D50: Gir Somnath | E50: =SUM(G50:I50) -> 1 | F50: =SUMIFS('CBG Plants'!N:N,'CBG Plants'!F:F,D50,'CBG Plants'!L:L,"Completed") +SUMIFS('CBG Plants'!N:N,'CBG Plants'!F:F,D50,'CBG Plants'!L:L,"Functional")+SUMIFS('CBG Plants'!N:N,'CBG Plants'!F:F,D50,'CBG Plants'!L:L,"Under Construction")+SUMIFS('CBG Plants'!N:N,'CBG Plants'!F:F,D50,'CBG Plants'!L:L,"Yet to start construction") -> 3 | G50: =COUNTIFS('CBG Plants'!F:F,D50,'CBG Plants'!L:L,"Completed") +COUNTIFS('CBG Plants'!F:F,D50,'CBG Plants'!L:L,"Functional") -> 0 | H50: =COUNTIFS('CBG Plants'!F:F,D50,'CBG Plants'!L:L,"Under Construction") -> 0 | I50: =COUNTIFS('CBG Plants'!F:F,D50,'CBG Plants'!L:L,"Yet to start construction") -> 1 | J50: YAGNIK | M50: =IFERROR(N50-(AD50*365/1000),"") -> 78.3 | N50: =SUM(O50:Q50) -> 78.3 | O50: 78.3 | P50: 0 | Q50: 0 | R50: =IFERROR(U50-F50,"") -> -1.3021991 | S50: =IFERROR(T50*Assumptions!$C$4,"") -> 52.5 | T50: 21 | U50: =IFERROR(S50*Assumptions!$C$5,"")+IFERROR(V50*Assumptions!$C$8*Assumptions!$C$5,"") -> 1.6978009 | V50: 12219 | W50: =IFERROR(ROUND(T50*(1+Assumptions!$C$7)^5,0),"") -> 64 | X50: =IFERROR(ROUND(W50*Assumptions!$C$4*Assumptions!$C$6,4),"")+IFERROR(ROUND(Y50*Assumptions!$C$8*Assumptions!$C$6,4),"") - F50 -> 5.6246 | Y50: =IFERROR(ROUND(V50*(1+Assumptions!$C$7)^5,0),"") -> 37289 | Z50: Operational Common Carrier | AA50: High Pressure Gujarat Gas Grid | AB50: 205.6 | AC50: 44.8 | AD50: 0 | AE50: =IF(R50="","",IF(R50>=Control!$D$4,"Y","N")) -> N | AF50: =IF(S50="","",IF(M50>=Control!$D$5,"Y","N")) -> Y | AG50: =IF(T50="","",IF(AB50<=Control!$D$10,"Y","N")) -> Y | AI50: =IF(X50="","",IF(X50>=Control!$D$9,"Y","N")) -> N | AK50: =IFERROR(INDEX(Assumptions!$D$92:$D$115,MATCH(C50,Assumptions!$B$92:$B$115,0)),"Low") -> High
B51: 48 | C51: GJ | D51: Jamnagar | E51: =SUM(G51:I51) -> 9 | F51: =SUMIFS('CBG Plants'!N:N,'CBG Plants'!F:F,D51,'CBG Plants'!L:L,"Completed") +SUMIFS('CBG Plants'!N:N,'CBG Plants'!F:F,D51,'CBG Plants'!L:L,"Functional")+SUMIFS('CBG Plants'!N:N,'CBG Plants'!F:F,D51,'CBG Plants'!L:L,"Under Construction")+SUMIFS('CBG Plants'!N:N,'CBG Plants'!F:F,D51,'CBG Plants'!L:L,"Yet to start construction") -> 34.4 | G51: =COUNTIFS('CBG Plants'!F:F,D51,'CBG Plants'!L:L,"Completed") +COUNTIFS('CBG Plants'!F:F,D51,'CBG Plants'!L:L,"Functional") -> 1 | H51: =COUNTIFS('CBG Plants'!F:F,D51,'CBG Plants'!L:L,"Under Construction") -> 4 | I51: =COUNTIFS('CBG Plants'!F:F,D51,'CBG Plants'!L:L,"Yet to start construction") -> 4 | J51: PROTICKS GREENTECH JAMNAGAR | K51: NEXGEN CBG PLANT | L51: Greenonbio Balance Pvt Ltd | M51: =IFERROR(N51-(AD51*365/1000),"") -> 21.915 | N51: =SUM(O51:Q51) -> 58.05 | O51: 58.05 | P51: 0 | Q51: 0 | R51: =IFERROR(U51-F51,"") -> -31.423227 | S51: =IFERROR(T51*Assumptions!$C$4,"") -> 77.5 | T51: 31 | U51: =IFERROR(S51*Assumptions!$C$5,"")+IFERROR(V51*Assumptions!$C$8*Assumptions!$C$5,"") -> 2.9767726 | V51: 64853 | W51: =IFERROR(ROUND(T51*(1+Assumptions!$C$7)^5,0),"") -> 95 | X51: =IFERROR(ROUND(W51*Assumptions!$C$4*Assumptions!$C$6,4),"")+IFERROR(ROUND(Y51*Assumptions!$C$8*Assumptions!$C$6,4),"") - F51 -> -19.2099 | Y51: =IFERROR(ROUND(V51*(1+Assumptions!$C$7)^5,0),"") -> 197916 | Z51: Operational Common Carrier | AA51: High Pressure Gujarat Gas Grid | AB51: 251.2 | AC51: 44.8 | AD51: 99 | AE51: =IF(R51="","",IF(R51>=Control!$D$4,"Y","N")) -> N | AF51: =IF(S51="","",IF(M51>=Control!$D$5,"Y","N")) -> N | AG51: =IF(T51="","",IF(AB51<=Control!$D$10,"Y","N")) -> Y | AI51: =IF(X51="","",IF(X51>=Control!$D$9,"Y","N")) -> N | AK51: =IFERROR(INDEX(Assumptions!$D$92:$D$115,MATCH(C51,Assumptions!$B$92:$B$115,0)),"Low") -> High
B52: 49 | C52: GJ | D52: Junagadh | E52: =SUM(G52:I52) -> 5 | F52: =SUMIFS('CBG Plants'!N:N,'CBG Plants'!F:F,D52,'CBG Plants'!L:L,"Completed") +SUMIFS('CBG Plants'!N:N,'CBG Plants'!F:F,D52,'CBG Plants'!L:L,"Functional")+SUMIFS('CBG Plants'!N:N,'CBG Plants'!F:F,D52,'CBG Plants'!L:L,"Under Construction")+SUMIFS('CBG Plants'!N:N,'CBG Plants'!F:F,D52,'CBG Plants'!L:L,"Yet to start construction") -> 59.6 | G52: =COUNTIFS('CBG Plants'!F:F,D52,'CBG Plants'!L:L,"Completed") +COUNTIFS('CBG Plants'!F:F,D52,'CBG Plants'!L:L,"Functional") -> 1 | H52: =COUNTIFS('CBG Plants'!F:F,D52,'CBG Plants'!L:L,"Under Construction") -> 0 | I52: =COUNTIFS('CBG Plants'!F:F,D52,'CBG Plants'!L:L,"Yet to start construction") -> 4 | J52: Amrutam edutech pvt.ltd | K52: al qaswa gas | L52: ZVS INTERNATIONAL PRIVATE LIMITED | M52: =IFERROR(N52-(AD52*365/1000),"") -> 35.075 | N52: =SUM(O52:Q52) -> 168.3 | O52: 168.3 | P52: 0 | Q52: 0 | R52: =IFERROR(U52-F52,"") -> -57.989949 | S52: =IFERROR(T52*Assumptions!$C$4,"") -> 47.5 | T52: 19 | U52: =IFERROR(S52*Assumptions!$C$5,"")+IFERROR(V52*Assumptions!$C$8*Assumptions!$C$5,"") -> 1.6100507 | V52: 18413 | W52: =IFERROR(ROUND(T52*(1+Assumptions!$C$7)^5,0),"") -> 58 | X52: =IFERROR(ROUND(W52*Assumptions!$C$4*Assumptions!$C$6,4),"")+IFERROR(ROUND(Y52*Assumptions!$C$8*Assumptions!$C$6,4),"") - F52 -> -51.4088 | Y52: =IFERROR(ROUND(V52*(1+Assumptions!$C$7)^5,0),"") -> 56192 | Z52: Operational Common Carrier | AA52: High Pressure Gujarat Gas Grid | AB52: 217.5 | AC52: 44.8 | AD52: 365 | AE52: =IF(R52="","",IF(R52>=Control!$D$4,"Y","N")) -> N | AF52: =IF(S52="","",IF(M52>=Control!$D$5,"Y","N")) -> N | AG52: =IF(T52="","",IF(AB52<=Control!$D$10,"Y","N")) -> Y | AI52: =IF(X52="","",IF(X52>=Control!$D$9,"Y","N")) -> N | AK52: =IFERROR(INDEX(Assumptions!$D$92:$D$115,MATCH(C52,Assumptions!$B$92:$B$115,0)),"Low") -> High
B53: 50 | C53: GJ | D53: Kachchh | E53: =SUM(G53:I53) -> 4 | F53: =SUMIFS('CBG Plants'!N:N,'CBG Plants'!F:F,D53,'CBG Plants'!L:L,"Completed") +SUMIFS('CBG Plants'!N:N,'CBG Plants'!F:F,D53,'CBG Plants'!L:L,"Functional")+SUMIFS('CBG Plants'!N:N,'CBG Plants'!F:F,D53,'CBG Plants'!L:L,"Under Construction")+SUMIFS('CBG Plants'!N:N,'CBG Plants'!F:F,D53,'CBG Plants'!L:L,"Yet to start construction") -> 31 | G53: =COUNTIFS('CBG Plants'!F:F,D53,'CBG Plants'!L:L,"Completed") +COUNTIFS('CBG Plants'!F:F,D53,'CBG Plants'!L:L,"Functional") -> 0 | H53: =COUNTIFS('CBG Plants'!F:F,D53,'CBG Plants'!L:L,"Under Construction") -> 1 | I53: =COUNTIFS('CBG Plants'!F:F,D53,'CBG Plants'!L:L,"Yet to start construction") -> 3 | J53: Botanic Harvest Global LLP | K53: M D ENTERPRISES | L53: Bakutra Brother's 06 TPD CBG Plant | M53: =IFERROR(N53-(AD53*365/1000),"") -> 45.525 | N53: =SUM(O53:Q53) -> 45.525 | O53: 45 | P53: 0 | Q53: 0.525 | R53: =IFERROR(U53-F53,"") -> -31 | S53: =IFERROR(T53*Assumptions!$C$4,"") -> 0 | T53: 0 | U53: =IFERROR(S53*Assumptions!$C$5,"")+IFERROR(V53*Assumptions!$C$8*Assumptions!$C$5,"") -> 0 | V53: 0 | W53: =IFERROR(ROUND(T53*(1+Assumptions!$C$7)^5,0),"") -> 0 | X53: =IFERROR(ROUND(W53*Assumptions!$C$4*Assumptions!$C$6,4),"")+IFERROR(ROUND(Y53*Assumptions!$C$8*Assumptions!$C$6,4),"") - F53 -> -31 | Y53: =IFERROR(ROUND(V53*(1+Assumptions!$C$7)^5,0),"") -> 0 | Z53: Operational Common Carrier | AA53: High Pressure Gujarat Gas Grid | AB53: 247.9 | AC53: 44.8 | AD53: 0 | AE53: =IF(R53="","",IF(R53>=Control!$D$4,"Y","N")) -> N | AF53: =IF(S53="","",IF(M53>=Control!$D$5,"Y","N")) -> N | AG53: =IF(T53="","",IF(AB53<=Control!$D$10,"Y","N")) -> Y | AI53: =IF(X53="","",IF(X53>=Control!$D$9,"Y","N")) -> N | AK53: =IFERROR(INDEX(Assumptions!$D$92:$D$115,MATCH(C53,Assumptions!$B$92:$B$115,0)),"Low") -> High
B54: 51 | C54: GJ | D54: Kheda | E54: =SUM(G54:I54) -> 1 | F54: =SUMIFS('CBG Plants'!N:N,'CBG Plants'!F:F,D54,'CBG Plants'!L:L,"Completed") +SUMIFS('CBG Plants'!N:N,'CBG Plants'!F:F,D54,'CBG Plants'!L:L,"Functional")+SUMIFS('CBG Plants'!N:N,'CBG Plants'!F:F,D54,'CBG Plants'!L:L,"Under Construction")+SUMIFS('CBG Plants'!N:N,'CBG Plants'!F:F,D54,'CBG Plants'!L:L,"Yet to start construction") -> 7.5 | G54: =COUNTIFS('CBG Plants'!F:F,D54,'CBG Plants'!L:L,"Completed") +COUNTIFS('CBG Plants'!F:F,D54,'CBG Plants'!L:L,"Functional") -> 1 | H54: =COUNTIFS('CBG Plants'!F:F,D54,'CBG Plants'!L:L,"Under Construction") -> 0 | I54: =COUNTIFS('CBG Plants'!F:F,D54,'CBG Plants'!L:L,"Yet to start construction") -> 0 | J54: Govardhannathji Energies LLP | M54: =IFERROR(N54-(AD54*365/1000),"") -> 136.025 | N54: =SUM(O54:Q54) -> 209.025 | O54: 65.7 | P54: 142.8 | Q54: 0.525 | R54: =IFERROR(U54-F54,"") -> -5.5313849 | S54: =IFERROR(T54*Assumptions!$C$4,"") -> 55 | T54: 22 | U54: =IFERROR(S54*Assumptions!$C$5,"")+IFERROR(V54*Assumptions!$C$8*Assumptions!$C$5,"") -> 1.9686151 | V54: 31703 | W54: =IFERROR(ROUND(T54*(1+Assumptions!$C$7)^5,0),"") -> 67 | X54: =IFERROR(ROUND(W54*Assumptions!$C$4*Assumptions!$C$6,4),"")+IFERROR(ROUND(Y54*Assumptions!$C$8*Assumptions!$C$6,4),"") - F54 -> 2.4956 | Y54: =IFERROR(ROUND(V54*(1+Assumptions!$C$7)^5,0),"") -> 96750 | Z54: Operational Common Carrier | AA54: High Pressure Gujarat Gas Grid | AB54: 9.3 | AC54: 44.8 | AD54: 200 | AE54: =IF(R54="","",IF(R54>=Control!$D$4,"Y","N")) -> N | AF54: =IF(S54="","",IF(M54>=Control!$D$5,"Y","N")) -> Y | AG54: =IF(T54="","",IF(AB54<=Control!$D$10,"Y","N")) -> Y | AI54: =IF(X54="","",IF(X54>=Control!$D$9,"Y","N")) -> N | AK54: =IFERROR(INDEX(Assumptions!$D$92:$D$115,MATCH(C54,Assumptions!$B$92:$B$115,0)),"Low") -> High
B55: 52 | C55: GJ | D55: Mahesana | E55: =SUM(G55:I55) -> 0 | F55: =SUMIFS('CBG Plants'!N:N,'CBG Plants'!F:F,D55,'CBG Plants'!L:L,"Completed") +SUMIFS('CBG Plants'!N:N,'CBG Plants'!F:F,D55,'CBG Plants'!L:L,"Functional")+SUMIFS('CBG Plants'!N:N,'CBG Plants'!F:F,D55,'CBG Plants'!L:L,"Under Construction")+SUMIFS('CBG Plants'!N:N,'CBG Plants'!F:F,D55,'CBG Plants'!L:L,"Yet to start construction") -> 0 | G55: =COUNTIFS('CBG Plants'!F:F,D55,'CBG Plants'!L:L,"Completed") +COUNTIFS('CBG Plants'!F:F,D55,'CBG Plants'!L:L,"Functional") -> 0 | H55: =COUNTIFS('CBG Plants'!F:F,D55,'CBG Plants'!L:L,"Under Construction") -> 0 | I55: =COUNTIFS('CBG Plants'!F:F,D55,'CBG Plants'!L:L,"Yet to start construction") -> 0 | J55: CBG Plant 20 TPD | M55: =IFERROR(N55-(AD55*365/1000),"") -> 96.255 | N55: =SUM(O55:Q55) -> 96.255 | O55: 87.75 | P55: 7.98 | Q55: 0.525 | R55: =IFERROR(U55-F55,"") -> 6.8257156 | S55: =IFERROR(T55*Assumptions!$C$4,"") -> 170 | T55: 68 | U55: =IFERROR(S55*Assumptions!$C$5,"")+IFERROR(V55*Assumptions!$C$8*Assumptions!$C$5,"") -> 6.8257156 | V55: 171713 | W55: =IFERROR(ROUND(T55*(1+Assumptions!$C$7)^5,0),"") -> 208 | X55: =IFERROR(ROUND(W55*Assumptions!$C$4*Assumptions!$C$6,4),"")+IFERROR(ROUND(Y55*Assumptions!$C$8*Assumptions!$C$6,4),"") - F55 -> 34.7774 | Y55: =IFERROR(ROUND(V55*(1+Assumptions!$C$7)^5,0),"") -> 524026 | Z55: Operational Common Carrier | AA55: High Pressure Gujarat Gas Grid | AB55: 9.8 | AC55: 44.8 | AD55: 0 | AE55: =IF(R55="","",IF(R55>=Control!$D$4,"Y","N")) -> Y | AF55: =IF(S55="","",IF(M55>=Control!$D$5,"Y","N")) -> Y | AG55: =IF(T55="","",IF(AB55<=Control!$D$10,"Y","N")) -> Y | AI55: =IF(X55="","",IF(X55>=Control!$D$9,"Y","N")) -> Y | AK55: =IFERROR(INDEX(Assumptions!$D$92:$D$115,MATCH(C55,Assumptions!$B$92:$B$115,0)),"Low") -> High
B56: 53 | C56: GJ | D56: Mahisagar | E56: =SUM(G56:I56) -> 1 | F56: =SUMIFS('CBG Plants'!N:N,'CBG Plants'!F:F,D56,'CBG Plants'!L:L,"Completed") +SUMIFS('CBG Plants'!N:N,'CBG Plants'!F:F,D56,'CBG Plants'!L:L,"Functional")+SUMIFS('CBG Plants'!N:N,'CBG Plants'!F:F,D56,'CBG Plants'!L:L,"Under Construction")+SUMIFS('CBG Plants'!N:N,'CBG Plants'!F:F,D56,'CBG Plants'!L:L,"Yet to start construction") -> 6 | G56: =COUNTIFS('CBG Plants'!F:F,D56,'CBG Plants'!L:L,"Completed") +COUNTIFS('CBG Plants'!F:F,D56,'CBG Plants'!L:L,"Functional") -> 0 | H56: =COUNTIFS('CBG Plants'!F:F,D56,'CBG Plants'!L:L,"Under Construction") -> 0 | I56: =COUNTIFS('CBG Plants'!F:F,D56,'CBG Plants'!L:L,"Yet to start construction") -> 1 | J56: MAHIJA BIOFUEL INDUSTRIES PVT LTD | M56: =IFERROR(N56-(AD56*365/1000),"") -> 117.63 | N56: =SUM(O56:Q56) -> 117.63 | O56: 28.8 | P56: 43.68 | Q56: 45.15 | R56: =IFERROR(U56-F56,"") -> -4.8373829 | S56: =IFERROR(T56*Assumptions!$C$4,"") -> 37.5 | T56: 15 | U56: =IFERROR(S56*Assumptions!$C$5,"")+IFERROR(V56*Assumptions!$C$8*Assumptions!$C$5,"") -> 1.1626171 | V56: 3743 | W56: =IFERROR(ROUND(T56*(1+Assumptions!$C$7)^5,0),"") -> 46 | X56: =IFERROR(ROUND(W56*Assumptions!$C$4*Assumptions!$C$6,4),"")+IFERROR(ROUND(Y56*Assumptions!$C$8*Assumptions!$C$6,4),"") - F56 -> -0.0587 | Y56: =IFERROR(ROUND(V56*(1+Assumptions!$C$7)^5,0),"") -> 11423 | Z56: Operational Common Carrier | AA56: High Pressure Gujarat Gas Grid | AB56: 90.5 | AC56: 44.8 | AD56: 0 | AE56: =IF(R56="","",IF(R56>=Control!$D$4,"Y","N")) -> N | AF56: =IF(S56="","",IF(M56>=Control!$D$5,"Y","N")) -> Y | AG56: =IF(T56="","",IF(AB56<=Control!$D$10,"Y","N")) -> Y | AI56: =IF(X56="","",IF(X56>=Control!$D$9,"Y","N")) -> N | AK56: =IFERROR(INDEX(Assumptions!$D$92:$D$115,MATCH(C56,Assumptions!$B$92:$B$115,0)),"Low") -> High
B57: 54 | C57: GJ | D57: Morbi | E57: =SUM(G57:I57) -> 8 | F57: =SUMIFS('CBG Plants'!N:N,'CBG Plants'!F:F,D57,'CBG Plants'!L:L,"Completed") +SUMIFS('CBG Plants'!N:N,'CBG Plants'!F:F,D57,'CBG Plants'!L:L,"Functional")+SUMIFS('CBG Plants'!N:N,'CBG Plants'!F:F,D57,'CBG Plants'!L:L,"Under Construction")+SUMIFS('CBG Plants'!N:N,'CBG Plants'!F:F,D57,'CBG Plants'!L:L,"Yet to start construction") -> 47.4 | G57: =COUNTIFS('CBG Plants'!F:F,D57,'CBG Plants'!L:L,"Completed") +COUNTIFS('CBG Plants'!F:F,D57,'CBG Plants'!L:L,"Functional") -> 0 | H57: =COUNTIFS('CBG Plants'!F:F,D57,'CBG Plants'!L:L,"Under Construction") -> 5 | I57: =COUNTIFS('CBG Plants'!F:F,D57,'CBG Plants'!L:L,"Yet to start construction") -> 3 | J57: SENTO VITRIFIED LLP | K57: SIMCO BIOFUELS LLP CBG PLANT | L57: GEOTECH ENERGY LLP | M57: =IFERROR(N57-(AD57*365/1000),"") -> 93.15 | N57: =SUM(O57:Q57) -> 93.15 | O57: 93.15 | P57: 0 | Q57: 0 | R57: =IFERROR(U57-F57,"") -> -47.4 | S57: =IFERROR(T57*Assumptions!$C$4,"") -> 0 | T57: 0 | U57: =IFERROR(S57*Assumptions!$C$5,"")+IFERROR(V57*Assumptions!$C$8*Assumptions!$C$5,"") -> 0 | V57: 0 | W57: =IFERROR(ROUND(T57*(1+Assumptions!$C$7)^5,0),"") -> 0 | X57: =IFERROR(ROUND(W57*Assumptions!$C$4*Assumptions!$C$6,4),"")+IFERROR(ROUND(Y57*Assumptions!$C$8*Assumptions!$C$6,4),"") - F57 -> -47.4 | Y57: =IFERROR(ROUND(V57*(1+Assumptions!$C$7)^5,0),"") -> 0 | Z57: Operational Common Carrier | AA57: High Pressure Gujarat Gas Grid | AB57: 168.8 | AC57: 44.8 | AD57: 0 | AE57: =IF(R57="","",IF(R57>=Control!$D$4,"Y","N")) -> N | AF57: =IF(S57="","",IF(M57>=Control!$D$5,"Y","N")) -> Y | AG57: =IF(T57="","",IF(AB57<=Control!$D$10,"Y","N")) -> Y | AI57: =IF(X57="","",IF(X57>=Control!$D$9,"Y","N")) -> N | AK57: =IFERROR(INDEX(Assumptions!$D$92:$D$115,MATCH(C57,Assumptions!$B$92:$B$115,0)),"Low") -> High
B58: 55 | C58: GJ | D58: Narmada | E58: =SUM(G58:I58) -> 0 | F58: =SUMIFS('CBG Plants'!N:N,'CBG Plants'!F:F,D58,'CBG Plants'!L:L,"Completed") +SUMIFS('CBG Plants'!N:N,'CBG Plants'!F:F,D58,'CBG Plants'!L:L,"Functional")+SUMIFS('CBG Plants'!N:N,'CBG Plants'!F:F,D58,'CBG Plants'!L:L,"Under Construction")+SUMIFS('CBG Plants'!N:N,'CBG Plants'!F:F,D58,'CBG Plants'!L:L,"Yet to start construction") -> 0 | G58: =COUNTIFS('CBG Plants'!F:F,D58,'CBG Plants'!L:L,"Completed") +COUNTIFS('CBG Plants'!F:F,D58,'CBG Plants'!L:L,"Functional") -> 0 | H58: =COUNTIFS('CBG Plants'!F:F,D58,'CBG Plants'!L:L,"Under Construction") -> 0 | I58: =COUNTIFS('CBG Plants'!F:F,D58,'CBG Plants'!L:L,"Yet to start construction") -> 0 | M58: =IFERROR(N58-(AD58*365/1000),"") -> 24.57 | N58: =SUM(O58:Q58) -> 24.57 | O58: 3.15 | P58: 4.62 | Q58: 16.8 | R58: =IFERROR(U58-F58,"") -> 0.8020791 | S58: =IFERROR(T58*Assumptions!$C$4,"") -> 25 | T58: 10 | U58: =IFERROR(S58*Assumptions!$C$5,"")+IFERROR(V58*Assumptions!$C$8*Assumptions!$C$5,"") -> 0.8020791 | V58: 5182 | W58: =IFERROR(ROUND(T58*(1+Assumptions!$C$7)^5,0),"") -> 31 | X58: =IFERROR(ROUND(W58*Assumptions!$C$4*Assumptions!$C$6,4),"")+IFERROR(ROUND(Y58*Assumptions!$C$8*Assumptions!$C$6,4),"") - F58 -> 4.1399 | Y58: =IFERROR(ROUND(V58*(1+Assumptions!$C$7)^5,0),"") -> 15814 | Z58: Operational Common Carrier | AA58: High Pressure Gujarat Gas Grid | AB58: 60.7 | AC58: 44.8 | AD58: 0 | AE58: =IF(R58="","",IF(R58>=Control!$D$4,"Y","N")) -> N | AF58: =IF(S58="","",IF(M58>=Control!$D$5,"Y","N")) -> N | AG58: =IF(T58="","",IF(AB58<=Control!$D$10,"Y","N")) -> Y | AI58: =IF(X58="","",IF(X58>=Control!$D$9,"Y","N")) -> N | AK58: =IFERROR(INDEX(Assumptions!$D$92:$D$115,MATCH(C58,Assumptions!$B$92:$B$115,0)),"Low") -> High
B59: 56 | C59: GJ | D59: Navsari | E59: =SUM(G59:I59) -> 2 | F59: =SUMIFS('CBG Plants'!N:N,'CBG Plants'!F:F,D59,'CBG Plants'!L:L,"Completed") +SUMIFS('CBG Plants'!N:N,'CBG Plants'!F:F,D59,'CBG Plants'!L:L,"Functional")+SUMIFS('CBG Plants'!N:N,'CBG Plants'!F:F,D59,'CBG Plants'!L:L,"Under Construction")+SUMIFS('CBG Plants'!N:N,'CBG Plants'!F:F,D59,'CBG Plants'!L:L,"Yet to start construction") -> 44 | G59: =COUNTIFS('CBG Plants'!F:F,D59,'CBG Plants'!L:L,"Completed") +COUNTIFS('CBG Plants'!F:F,D59,'CBG Plants'!L:L,"Functional") -> 0 | H59: =COUNTIFS('CBG Plants'!F:F,D59,'CBG Plants'!L:L,"Under Construction") -> 2 | I59: =COUNTIFS('CBG Plants'!F:F,D59,'CBG Plants'!L:L,"Yet to start construction") -> 0 | J59: Surat (Navsari) CBG Plant | K59: Surat (Navsari-2) CBG Plant | M59: =IFERROR(N59-(AD59*365/1000),"") -> 62.16 | N59: =SUM(O59:Q59) -> 62.16 | O59: 0 | P59: 62.16 | Q59: 0 | R59: =IFERROR(U59-F59,"") -> -40.327586 | S59: =IFERROR(T59*Assumptions!$C$4,"") -> 77.5 | T59: 31 | U59: =IFERROR(S59*Assumptions!$C$5,"")+IFERROR(V59*Assumptions!$C$8*Assumptions!$C$5,"") -> 3.6724135 | V59: 134071 | W59: =IFERROR(ROUND(T59*(1+Assumptions!$C$7)^5,0),"") -> 95 | X59: =IFERROR(ROUND(W59*Assumptions!$C$4*Assumptions!$C$6,4),"")+IFERROR(ROUND(Y59*Assumptions!$C$8*Assumptions!$C$6,4),"") - F59 -> -25.2717 | Y59: =IFERROR(ROUND(V59*(1+Assumptions!$C$7)^5,0),"") -> 409152 | Z59: Operational Common Carrier | AA59: High Pressure Gujarat Gas Grid | AB59: 90.2 | AC59: 44.8 | AD59: 0 | AE59: =IF(R59="","",IF(R59>=Control!$D$4,"Y","N")) -> N | AF59: =IF(S59="","",IF(M59>=Control!$D$5,"Y","N")) -> Y | AG59: =IF(T59="","",IF(AB59<=Control!$D$10,"Y","N")) -> Y | AI59: =IF(X59="","",IF(X59>=Control!$D$9,"Y","N")) -> N | AK59: =IFERROR(INDEX(Assumptions!$D$92:$D$115,MATCH(C59,Assumptions!$B$92:$B$115,0)),"Low") -> High
B60: 57 | C60: GJ | D60: Panch Mahals | E60: =SUM(G60:I60) -> 2 | F60: =SUMIFS('CBG Plants'!N:N,'CBG Plants'!F:F,D60,'CBG Plants'!L:L,"Completed") +SUMIFS('CBG Plants'!N:N,'CBG Plants'!F:F,D60,'CBG Plants'!L:L,"Functional")+SUMIFS('CBG Plants'!N:N,'CBG Plants'!F:F,D60,'CBG Plants'!L:L,"Under Construction")+SUMIFS('CBG Plants'!N:N,'CBG Plants'!F:F,D60,'CBG Plants'!L:L,"Yet to start construction") -> 24 | G60: =COUNTIFS('CBG Plants'!F:F,D60,'CBG Plants'!L:L,"Completed") +COUNTIFS('CBG Plants'!F:F,D60,'CBG Plants'!L:L,"Functional") -> 0 | H60: =COUNTIFS('CBG Plants'!F:F,D60,'CBG Plants'!L:L,"Under Construction") -> 0 | I60: =COUNTIFS('CBG Plants'!F:F,D60,'CBG Plants'!L:L,"Yet to start construction") -> 2 | J60: AXAR BIO ENERGY LLP | K60: AKSHAR BIO ENERGIES | M60: =IFERROR(N60-(AD60*365/1000),"") -> 134.685 | N60: =SUM(O60:Q60) -> 134.685 | O60: 15.3 | P60: 41.16 | Q60: 78.225 | R60: =IFERROR(U60-F60,"") -> -21.353973 | S60: =IFERROR(T60*Assumptions!$C$4,"") -> 77.5 | T60: 31 | U60: =IFERROR(S60*Assumptions!$C$5,"")+IFERROR(V60*Assumptions!$C$8*Assumptions!$C$5,"") -> 2.6460271 | V60: 31943 | W60: =IFERROR(ROUND(T60*(1+Assumptions!$C$7)^5,0),"") -> 95 | X60: =IFERROR(ROUND(W60*Assumptions!$C$4*Assumptions!$C$6,4),"")+IFERROR(ROUND(Y60*Assumptions!$C$8*Assumptions!$C$6,4),"") - F60 -> -10.4922 | Y60: =IFERROR(ROUND(V60*(1+Assumptions!$C$7)^5,0),"") -> 97482 | Z60: Operational Common Carrier | AA60: High Pressure Gujarat Gas Grid | AB60: 62.6 | AC60: 44.8 | AD60: 0 | AE60: =IF(R60="","",IF(R60>=Control!$D$4,"Y","N")) -> N | AF60: =IF(S60="","",IF(M60>=Control!$D$5,"Y","N")) -> Y | AG60: =IF(T60="","",IF(AB60<=Control!$D$10,"Y","N")) -> Y | AI60: =IF(X60="","",IF(X60>=Control!$D$9,"Y","N")) -> N | AK60: =IFERROR(INDEX(Assumptions!$D$92:$D$115,MATCH(C60,Assumptions!$B$92:$B$115,0)),"Low") -> High
B61: 58 | C61: GJ | D61: Patan | E61: =SUM(G61:I61) -> 3 | F61: =SUMIFS('CBG Plants'!N:N,'CBG Plants'!F:F,D61,'CBG Plants'!L:L,"Completed") +SUMIFS('CBG Plants'!N:N,'CBG Plants'!F:F,D61,'CBG Plants'!L:L,"Functional")+SUMIFS('CBG Plants'!N:N,'CBG Plants'!F:F,D61,'CBG Plants'!L:L,"Under Construction")+SUMIFS('CBG Plants'!N:N,'CBG Plants'!F:F,D61,'CBG Plants'!L:L,"Yet to start construction") -> 23 | G61: =COUNTIFS('CBG Plants'!F:F,D61,'CBG Plants'!L:L,"Completed") +COUNTIFS('CBG Plants'!F:F,D61,'CBG Plants'!L:L,"Functional") -> 0 | H61: =COUNTIFS('CBG Plants'!F:F,D61,'CBG Plants'!L:L,"Under Construction") -> 0 | I61: =COUNTIFS('CBG Plants'!F:F,D61,'CBG Plants'!L:L,"Yet to start construction") -> 3 | J61: Milestone CBG Plant-2 | K61: MAHADEV GREEN BIO ENERGY LLP | L61: mahadev green bio energy lap | M61: =IFERROR(N61-(AD61*365/1000),"") -> 43.65 | N61: =SUM(O61:Q61) -> 43.65 | O61: 43.65 | P61: 0 | Q61: 0 | R61: =IFERROR(U61-F61,"") -> -20.848545 | S61: =IFERROR(T61*Assumptions!$C$4,"") -> 62.5 | T61: 25 | U61: =IFERROR(S61*Assumptions!$C$5,"")+IFERROR(V61*Assumptions!$C$8*Assumptions!$C$5,"") -> 2.1514554 | V61: 27508 | W61: =IFERROR(ROUND(T61*(1+Assumptions!$C$7)^5,0),"") -> 76 | X61: =IFERROR(ROUND(W61*Assumptions!$C$4*Assumptions!$C$6,4),"")+IFERROR(ROUND(Y61*Assumptions!$C$8*Assumptions!$C$6,4),"") - F61 -> -12.0939 | Y61: =IFERROR(ROUND(V61*(1+Assumptions!$C$7)^5,0),"") -> 83948 | Z61: Operational Common Carrier | AA61: High Pressure Gujarat Gas Grid | AB61: 65.5 | AC61: 44.8 | AD61: 0 | AE61: =IF(R61="","",IF(R61>=Control!$D$4,"Y","N")) -> N | AF61: =IF(S61="","",IF(M61>=Control!$D$5,"Y","N")) -> N | AG61: =IF(T61="","",IF(AB61<=Control!$D$10,"Y","N")) -> Y | AI61: =IF(X61="","",IF(X61>=Control!$D$9,"Y","N")) -> N | AK61: =IFERROR(INDEX(Assumptions!$D$92:$D$115,MATCH(C61,Assumptions!$B$92:$B$115,0)),"Low") -> High
B62: 59 | C62: GJ | D62: Porbandar | E62: =SUM(G62:I62) -> 0 | F62: =SUMIFS('CBG Plants'!N:N,'CBG Plants'!F:F,D62,'CBG Plants'!L:L,"Completed") +SUMIFS('CBG Plants'!N:N,'CBG Plants'!F:F,D62,'CBG Plants'!L:L,"Functional")+SUMIFS('CBG Plants'!N:N,'CBG Plants'!F:F,D62,'CBG Plants'!L:L,"Under Construction")+SUMIFS('CBG Plants'!N:N,'CBG Plants'!F:F,D62,'CBG Plants'!L:L,"Yet to start construction") -> 0 | G62: =COUNTIFS('CBG Plants'!F:F,D62,'CBG Plants'!L:L,"Completed") +COUNTIFS('CBG Plants'!F:F,D62,'CBG Plants'!L:L,"Functional") -> 0 | H62: =COUNTIFS('CBG Plants'!F:F,D62,'CBG Plants'!L:L,"Under Construction") -> 0 | I62: =COUNTIFS('CBG Plants'!F:F,D62,'CBG Plants'!L:L,"Yet to start construction") -> 0 | M62: =IFERROR(N62-(AD62*365/1000),"") -> 40.05 | N62: =SUM(O62:Q62) -> 40.05 | O62: 40.05 | P62: 0 | Q62: 0 | R62: =IFERROR(U62-F62,"") -> 0.78480315 | S62: =IFERROR(T62*Assumptions!$C$4,"") -> 25 | T62: 10 | U62: =IFERROR(S62*Assumptions!$C$5,"")+IFERROR(V62*Assumptions!$C$8*Assumptions!$C$5,"") -> 0.78480315 | V62: 3463 | W62: =IFERROR(ROUND(T62*(1+Assumptions!$C$7)^5,0),"") -> 31 | X62: =IFERROR(ROUND(W62*Assumptions!$C$4*Assumptions!$C$6,4),"")+IFERROR(ROUND(Y62*Assumptions!$C$8*Assumptions!$C$6,4),"") - F62 -> 4.052 | Y62: =IFERROR(ROUND(V62*(1+Assumptions!$C$7)^5,0),"") -> 10568 | Z62: Operational Common Carrier | AA62: High Pressure Gujarat Gas Grid | AB62: 286.6 | AC62: 44.8 | AD62: 0 | AE62: =IF(R62="","",IF(R62>=Control!$D$4,"Y","N")) -> N | AF62: =IF(S62="","",IF(M62>=Control!$D$5,"Y","N")) -> N | AG62: =IF(T62="","",IF(AB62<=Control!$D$10,"Y","N")) -> Y | AI62: =IF(X62="","",IF(X62>=Control!$D$9,"Y","N")) -> N | AK62: =IFERROR(INDEX(Assumptions!$D$92:$D$115,MATCH(C62,Assumptions!$B$92:$B$115,0)),"Low") -> High
B63: 60 | C63: GJ | D63: Rajkot | E63: =SUM(G63:I63) -> 2 | F63: =SUMIFS('CBG Plants'!N:N,'CBG Plants'!F:F,D63,'CBG Plants'!L:L,"Completed") +SUMIFS('CBG Plants'!N:N,'CBG Plants'!F:F,D63,'CBG Plants'!L:L,"Functional")+SUMIFS('CBG Plants'!N:N,'CBG Plants'!F:F,D63,'CBG Plants'!L:L,"Under Construction")+SUMIFS('CBG Plants'!N:N,'CBG Plants'!F:F,D63,'CBG Plants'!L:L,"Yet to start construction") -> 7.1 | G63: =COUNTIFS('CBG Plants'!F:F,D63,'CBG Plants'!L:L,"Completed") +COUNTIFS('CBG Plants'!F:F,D63,'CBG Plants'!L:L,"Functional") -> 0 | H63: =COUNTIFS('CBG Plants'!F:F,D63,'CBG Plants'!L:L,"Under Construction") -> 0 | I63: =COUNTIFS('CBG Plants'!F:F,D63,'CBG Plants'!L:L,"Yet to start construction") -> 2 | J63: Earth-1 | K63: KAIZEN BIO ENERGY LLP | M63: =IFERROR(N63-(AD63*365/1000),"") -> 177.75 | N63: =SUM(O63:Q63) -> 177.75 | O63: 177.75 | P63: 0 | Q63: 0 | R63: =IFERROR(U63-F63,"") -> 4.4283409 | S63: =IFERROR(T63*Assumptions!$C$4,"") -> 242.5 | T63: 97 | U63: =IFERROR(S63*Assumptions!$C$5,"")+IFERROR(V63*Assumptions!$C$8*Assumptions!$C$5,"") -> 11.528341 | V63: 423218 | W63: =IFERROR(ROUND(T63*(1+Assumptions!$C$7)^5,0),"") -> 296 | X63: =IFERROR(ROUND(W63*Assumptions!$C$4*Assumptions!$C$6,4),"")+IFERROR(ROUND(Y63*Assumptions!$C$8*Assumptions!$C$6,4),"") - F63 -> 51.5336 | Y63: =IFERROR(ROUND(V63*(1+Assumptions!$C$7)^5,0),"") -> 1291559 | Z63: Operational Common Carrier | AA63: High Pressure Gujarat Gas Grid | AB63: 189.3 | AC63: 44.8 | AD63: 0 | AE63: =IF(R63="","",IF(R63>=Control!$D$4,"Y","N")) -> Y | AF63: =IF(S63="","",IF(M63>=Control!$D$5,"Y","N")) -> Y | AG63: =IF(T63="","",IF(AB63<=Control!$D$10,"Y","N")) -> Y | AI63: =IF(X63="","",IF(X63>=Control!$D$9,"Y","N")) -> Y | AK63: =IFERROR(INDEX(Assumptions!$D$92:$D$115,MATCH(C63,Assumptions!$B$92:$B$115,0)),"Low") -> High
B64: 61 | C64: GJ | D64: Sabar Kantha | E64: =SUM(G64:I64) -> 5 | F64: =SUMIFS('CBG Plants'!N:N,'CBG Plants'!F:F,D64,'CBG Plants'!L:L,"Completed") +SUMIFS('CBG Plants'!N:N,'CBG Plants'!F:F,D64,'CBG Plants'!L:L,"Functional")+SUMIFS('CBG Plants'!N:N,'CBG Plants'!F:F,D64,'CBG Plants'!L:L,"Under Construction")+SUMIFS('CBG Plants'!N:N,'CBG Plants'!F:F,D64,'CBG Plants'!L:L,"Yet to start construction") -> 18 | G64: =COUNTIFS('CBG Plants'!F:F,D64,'CBG Plants'!L:L,"Completed") +COUNTIFS('CBG Plants'!F:F,D64,'CBG Plants'!L:L,"Functional") -> 0 | H64: =COUNTIFS('CBG Plants'!F:F,D64,'CBG Plants'!L:L,"Under Construction") -> 1 | I64: =COUNTIFS('CBG Plants'!F:F,D64,'CBG Plants'!L:L,"Yet to start construction") -> 4 | J64: NAR NARAYAN GREEN ENERGY LLP | K64: Agronx Bio CBG Industries | L64: GUJARAT ORGANIC FERTILIZER | M64: =IFERROR(N64-(AD64*365/1000),"") -> 127.815 | N64: =SUM(O64:Q64) -> 127.815 | O64: 104.4 | P64: 9.24 | Q64: 14.175 | R64: =IFERROR(U64-F64,"") -> -18 | S64: =IFERROR(T64*Assumptions!$C$4,"") -> 0 | T64: 0 | U64: =IFERROR(S64*Assumptions!$C$5,"")+IFERROR(V64*Assumptions!$C$8*Assumptions!$C$5,"") -> 0 | V64: 0 | W64: =IFERROR(ROUND(T64*(1+Assumptions!$C$7)^5,0),"") -> 0 | X64: =IFERROR(ROUND(W64*Assumptions!$C$4*Assumptions!$C$6,4),"")+IFERROR(ROUND(Y64*Assumptions!$C$8*Assumptions!$C$6,4),"") - F64 -> -18 | Y64: =IFERROR(ROUND(V64*(1+Assumptions!$C$7)^5,0),"") -> 0 | Z64: Operational Common Carrier | AA64: High Pressure Gujarat Gas Grid | AB64: 70.8 | AC64: 44.8 | AD64: 0 | AE64: =IF(R64="","",IF(R64>=Control!$D$4,"Y","N")) -> N | AF64: =IF(S64="","",IF(M64>=Control!$D$5,"Y","N")) -> Y | AG64: =IF(T64="","",IF(AB64<=Control!$D$10,"Y","N")) -> Y | AI64: =IF(X64="","",IF(X64>=Control!$D$9,"Y","N")) -> N | AK64: =IFERROR(INDEX(Assumptions!$D$92:$D$115,MATCH(C64,Assumptions!$B$92:$B$115,0)),"Low") -> High
B65: 62 | C65: GJ | D65: Surat | E65: =SUM(G65:I65) -> 9 | F65: =SUMIFS('CBG Plants'!N:N,'CBG Plants'!F:F,D65,'CBG Plants'!L:L,"Completed") +SUMIFS('CBG Plants'!N:N,'CBG Plants'!F:F,D65,'CBG Plants'!L:L,"Functional")+SUMIFS('CBG Plants'!N:N,'CBG Plants'!F:F,D65,'CBG Plants'!L:L,"Under Construction")+SUMIFS('CBG Plants'!N:N,'CBG Plants'!F:F,D65,'CBG Plants'!L:L,"Yet to start construction") -> 42.6 | G65: =COUNTIFS('CBG Plants'!F:F,D65,'CBG Plants'!L:L,"Completed") +COUNTIFS('CBG Plants'!F:F,D65,'CBG Plants'!L:L,"Functional") -> 4 | H65: =COUNTIFS('CBG Plants'!F:F,D65,'CBG Plants'!L:L,"Under Construction") -> 3 | I65: =COUNTIFS('CBG Plants'!F:F,D65,'CBG Plants'!L:L,"Yet to start construction") -> 2 | J65: Biofics Advance Multifeed BioCNG & Premium Biofertilizer Plant | K65: SHREE GANESH BIO ENERGY | L65: Anand Bio Renewable Pvt. Ltd | M65: =IFERROR(N65-(AD65*365/1000),"") -> -25.57 | N65: =SUM(O65:Q65) -> 69.33 | O65: 3.6 | P65: 58.38 | Q65: 7.35 | R65: =IFERROR(U65-F65,"") -> -33.081515 | S65: =IFERROR(T65*Assumptions!$C$4,"") -> 160 | T65: 64 | U65: =IFERROR(S65*Assumptions!$C$5,"")+IFERROR(V65*Assumptions!$C$8*Assumptions!$C$5,"") -> 9.518485 | V65: 469501 | W65: =IFERROR(ROUND(T65*(1+Assumptions!$C$7)^5,0),"") -> 195 | X65: =IFERROR(ROUND(W65*Assumptions!$C$4*Assumptions!$C$6,4),"")+IFERROR(ROUND(Y65*Assumptions!$C$8*Assumptions!$C$6,4),"") - F65 -> 5.7745 | Y65: =IFERROR(ROUND(V65*(1+Assumptions!$C$7)^5,0),"") -> 1432803 | Z65: Operational Common Carrier | AA65: High Pressure Gujarat Gas Grid | AB65: 40 | AC65: 44.8 | AD65: 260 | AE65: =IF(R65="","",IF(R65>=Control!$D$4,"Y","N")) -> N | AF65: =IF(S65="","",IF(M65>=Control!$D$5,"Y","N")) -> N | AG65: =IF(T65="","",IF(AB65<=Control!$D$10,"Y","N")) -> Y | AI65: =IF(X65="","",IF(X65>=Control!$D$9,"Y","N")) -> N | AK65: =IFERROR(INDEX(Assumptions!$D$92:$D$115,MATCH(C65,Assumptions!$B$92:$B$115,0)),"Low") -> High
B66: 63 | C66: GJ | D66: Surendranagar | E66: =SUM(G66:I66) -> 6 | F66: =SUMIFS('CBG Plants'!N:N,'CBG Plants'!F:F,D66,'CBG Plants'!L:L,"Completed") +SUMIFS('CBG Plants'!N:N,'CBG Plants'!F:F,D66,'CBG Plants'!L:L,"Functional")+SUMIFS('CBG Plants'!N:N,'CBG Plants'!F:F,D66,'CBG Plants'!L:L,"Under Construction")+SUMIFS('CBG Plants'!N:N,'CBG Plants'!F:F,D66,'CBG Plants'!L:L,"Yet to start construction") -> 44.822 | G66: =COUNTIFS('CBG Plants'!F:F,D66,'CBG Plants'!L:L,"Completed") +COUNTIFS('CBG Plants'!F:F,D66,'CBG Plants'!L:L,"Functional") -> 2 | H66: =COUNTIFS('CBG Plants'!F:F,D66,'CBG Plants'!L:L,"Under Construction") -> 1 | I66: =COUNTIFS('CBG Plants'!F:F,D66,'CBG Plants'!L:L,"Yet to start construction") -> 3 | J66: ENRGREEN GEDI ONE | K66: Chem Process Systems Integrated Bio-fraction & CBG Plant | L66: 7.5TPD CBG Plant - Tolani Energies | M66: =IFERROR(N66-(AD66*365/1000),"") -> -25.21 | N66: =SUM(O66:Q66) -> 58.74 | O66: 55.8 | P66: 2.94 | Q66: 0 | R66: =IFERROR(U66-F66,"") -> -41.042508 | S66: =IFERROR(T66*Assumptions!$C$4,"") -> 112.5 | T66: 45 | U66: =IFERROR(S66*Assumptions!$C$5,"")+IFERROR(V66*Assumptions!$C$8*Assumptions!$C$5,"") -> 3.7794924 | V66: 40248 | W66: =IFERROR(ROUND(T66*(1+Assumptions!$C$7)^5,0),"") -> 137 | X66: =IFERROR(ROUND(W66*Assumptions!$C$4*Assumptions!$C$6,4),"")+IFERROR(ROUND(Y66*Assumptions!$C$8*Assumptions!$C$6,4),"") - F66 -> -25.6396 | Y66: =IFERROR(ROUND(V66*(1+Assumptions!$C$7)^5,0),"") -> 122827 | Z66: Operational Common Carrier | AA66: High Pressure Gujarat Gas Grid | AB66: 104.1 | AC66: 44.8 | AD66: 230 | AE66: =IF(R66="","",IF(R66>=Control!$D$4,"Y","N")) -> N | AF66: =IF(S66="","",IF(M66>=Control!$D$5,"Y","N")) -> N | AG66: =IF(T66="","",IF(AB66<=Control!$D$10,"Y","N")) -> Y | AI66: =IF(X66="","",IF(X66>=Control!$D$9,"Y","N")) -> N | AK66: =IFERROR(INDEX(Assumptions!$D$92:$D$115,MATCH(C66,Assumptions!$B$92:$B$115,0)),"Low") -> High
B67: 64 | C67: GJ | D67: Tapi | E67: =SUM(G67:I67) -> 6 | F67: =SUMIFS('CBG Plants'!N:N,'CBG Plants'!F:F,D67,'CBG Plants'!L:L,"Completed") +SUMIFS('CBG Plants'!N:N,'CBG Plants'!F:F,D67,'CBG Plants'!L:L,"Functional")+SUMIFS('CBG Plants'!N:N,'CBG Plants'!F:F,D67,'CBG Plants'!L:L,"Under Construction")+SUMIFS('CBG Plants'!N:N,'CBG Plants'!F:F,D67,'CBG Plants'!L:L,"Yet to start construction") -> 30 | G67: =COUNTIFS('CBG Plants'!F:F,D67,'CBG Plants'!L:L,"Completed") +COUNTIFS('CBG Plants'!F:F,D67,'CBG Plants'!L:L,"Functional") -> 1 | H67: =COUNTIFS('CBG Plants'!F:F,D67,'CBG Plants'!L:L,"Under Construction") -> 2 | I67: =COUNTIFS('CBG Plants'!F:F,D67,'CBG Plants'!L:L,"Yet to start construction") -> 3 | J67: 1.25 MWeq. Biogas Generation (15,000 m3/day) plant and Generation of 6000 kg Bio-CNG from press mud, | K67: 6 TPD CBG Plant at Vyara | L67: GANGAA OORJA LLP | M67: =IFERROR(N67-(AD67*365/1000),"") -> 43.095 | N67: =SUM(O67:Q67) -> 97.845 | O67: 4.5 | P67: 88.62 | Q67: 4.725 | R67: =IFERROR(U67-F67,"") -> -29.67994 | S67: =IFERROR(T67*Assumptions!$C$4,"") -> 10 | T67: 4 | U67: =IFERROR(S67*Assumptions!$C$5,"")+IFERROR(V67*Assumptions!$C$8*Assumptions!$C$5,"") -> 0.3200598 | V67: 1996 | W67: =IFERROR(ROUND(T67*(1+Assumptions!$C$7)^5,0),"") -> 12 | X67: =IFERROR(ROUND(W67*Assumptions!$C$4*Assumptions!$C$6,4),"")+IFERROR(ROUND(Y67*Assumptions!$C$8*Assumptions!$C$6,4),"") - F67 -> -28.398 | Y67: =IFERROR(ROUND(V67*(1+Assumptions!$C$7)^5,0),"") -> 6091 | Z67: Operational Common Carrier | AA67: High Pressure Gujarat Gas Grid | AB67: 79.5 | AC67: 44.8 | AD67: 150 | AE67: =IF(R67="","",IF(R67>=Control!$D$4,"Y","N")) -> N | AF67: =IF(S67="","",IF(M67>=Control!$D$5,"Y","N")) -> N | AG67: =IF(T67="","",IF(AB67<=Control!$D$10,"Y","N")) -> Y | AI67: =IF(X67="","",IF(X67>=Control!$D$9,"Y","N")) -> N | AK67: =IFERROR(INDEX(Assumptions!$D$92:$D$115,MATCH(C67,Assumptions!$B$92:$B$115,0)),"Low") -> High
B68: 65 | C68: GJ | D68: Vadodara | E68: =SUM(G68:I68) -> 8 | F68: =SUMIFS('CBG Plants'!N:N,'CBG Plants'!F:F,D68,'CBG Plants'!L:L,"Completed") +SUMIFS('CBG Plants'!N:N,'CBG Plants'!F:F,D68,'CBG Plants'!L:L,"Functional")+SUMIFS('CBG Plants'!N:N,'CBG Plants'!F:F,D68,'CBG Plants'!L:L,"Under Construction")+SUMIFS('CBG Plants'!N:N,'CBG Plants'!F:F,D68,'CBG Plants'!L:L,"Yet to start construction") -> 60.84 | G68: =COUNTIFS('CBG Plants'!F:F,D68,'CBG Plants'!L:L,"Completed") +COUNTIFS('CBG Plants'!F:F,D68,'CBG Plants'!L:L,"Functional") -> 4 | H68: =COUNTIFS('CBG Plants'!F:F,D68,'CBG Plants'!L:L,"Under Construction") -> 1 | I68: =COUNTIFS('CBG Plants'!F:F,D68,'CBG Plants'!L:L,"Yet to start construction") -> 3 | J68: GREENSPHERE BIO ENERGY PRIVATE LIMITED | K68: Organic Municipal Solid Waste (MSW) from Vadodara Municipal corporation (VMC) for Compressed Bio-gas | L68: Vadodara CBG Plant | M68: =IFERROR(N68-(AD68*365/1000),"") -> -156.055 | N68: =SUM(O68:Q68) -> 64.77 | O68: 23.4 | P68: 31.92 | Q68: 9.45 | R68: =IFERROR(U68-F68,"") -> -53.5445 | S68: =IFERROR(T68*Assumptions!$C$4,"") -> 140 | T68: 56 | U68: =IFERROR(S68*Assumptions!$C$5,"")+IFERROR(V68*Assumptions!$C$8*Assumptions!$C$5,"") -> 7.2955005 | V68: 308010 | W68: =IFERROR(ROUND(T68*(1+Assumptions!$C$7)^5,0),"") -> 171 | X68: =IFERROR(ROUND(W68*Assumptions!$C$4*Assumptions!$C$6,4),"")+IFERROR(ROUND(Y68*Assumptions!$C$8*Assumptions!$C$6,4),"") - F68 -> -23.7205 | Y68: =IFERROR(ROUND(V68*(1+Assumptions!$C$7)^5,0),"") -> 939972 | Z68: Operational Common Carrier | AA68: High Pressure Gujarat Gas Grid | AB68: 7.3 | AC68: 44.8 | AD68: 605 | AE68: =IF(R68="","",IF(R68>=Control!$D$4,"Y","N")) -> N | AF68: =IF(S68="","",IF(M68>=Control!$D$5,"Y","N")) -> N | AG68: =IF(T68="","",IF(AB68<=Control!$D$10,"Y","N")) -> Y | AI68: =IF(X68="","",IF(X68>=Control!$D$9,"Y","N")) -> N | AK68: =IFERROR(INDEX(Assumptions!$D$92:$D$115,MATCH(C68,Assumptions!$B$92:$B$115,0)),"Low") -> High
B69: 66 | C69: GJ | D69: Valsad | E69: =SUM(G69:I69) -> 0 | F69: =SUMIFS('CBG Plants'!N:N,'CBG Plants'!F:F,D69,'CBG Plants'!L:L,"Completed") +SUMIFS('CBG Plants'!N:N,'CBG Plants'!F:F,D69,'CBG Plants'!L:L,"Functional")+SUMIFS('CBG Plants'!N:N,'CBG Plants'!F:F,D69,'CBG Plants'!L:L,"Under Construction")+SUMIFS('CBG Plants'!N:N,'CBG Plants'!F:F,D69,'CBG Plants'!L:L,"Yet to start construction") -> 0 | G69: =COUNTIFS('CBG Plants'!F:F,D69,'CBG Plants'!L:L,"Completed") +COUNTIFS('CBG Plants'!F:F,D69,'CBG Plants'!L:L,"Functional") -> 0 | H69: =COUNTIFS('CBG Plants'!F:F,D69,'CBG Plants'!L:L,"Under Construction") -> 0 | I69: =COUNTIFS('CBG Plants'!F:F,D69,'CBG Plants'!L:L,"Yet to start construction") -> 0 | M69: =IFERROR(N69-(AD69*365/1000),"") -> 79.38 | N69: =SUM(O69:Q69) -> 79.38 | O69: 0 | P69: 79.38 | Q69: 0 | R69: =IFERROR(U69-F69,"") -> 14.549574 | S69: =IFERROR(T69*Assumptions!$C$4,"") -> 352.5 | T69: 141 | U69: =IFERROR(S69*Assumptions!$C$5,"")+IFERROR(V69*Assumptions!$C$8*Assumptions!$C$5,"") -> 14.549574 | V69: 395480 | W69: =IFERROR(ROUND(T69*(1+Assumptions!$C$7)^5,0),"") -> 430 | X69: =IFERROR(ROUND(W69*Assumptions!$C$4*Assumptions!$C$6,4),"")+IFERROR(ROUND(Y69*Assumptions!$C$8*Assumptions!$C$6,4),"") - F69 -> 73.9657 | Y69: =IFERROR(ROUND(V69*(1+Assumptions!$C$7)^5,0),"") -> 1206909 | Z69: Operational Common Carrier | AA69: High Pressure Gujarat Gas Grid | AB69: 134.2 | AC69: 44.8 | AD69: 0 | AE69: =IF(R69="","",IF(R69>=Control!$D$4,"Y","N")) -> Y | AF69: =IF(S69="","",IF(M69>=Control!$D$5,"Y","N")) -> Y | AG69: =IF(T69="","",IF(AB69<=Control!$D$10,"Y","N")) -> Y | AI69: =IF(X69="","",IF(X69>=Control!$D$9,"Y","N")) -> Y | AK69: =IFERROR(INDEX(Assumptions!$D$92:$D$115,MATCH(C69,Assumptions!$B$92:$B$115,0)),"Low") -> High
B70: 67 | C70: AP | D70: Alluri Sitharama Raju | E70: =SUM(G70:I70) -> 0 | F70: =SUMIFS('CBG Plants'!N:N,'CBG Plants'!F:F,D70,'CBG Plants'!L:L,"Completed") +SUMIFS('CBG Plants'!N:N,'CBG Plants'!F:F,D70,'CBG Plants'!L:L,"Functional")+SUMIFS('CBG Plants'!N:N,'CBG Plants'!F:F,D70,'CBG Plants'!L:L,"Under Construction")+SUMIFS('CBG Plants'!N:N,'CBG Plants'!F:F,D70,'CBG Plants'!L:L,"Yet to start construction") -> 0 | G70: =COUNTIFS('CBG Plants'!F:F,D70,'CBG Plants'!L:L,"Completed") +COUNTIFS('CBG Plants'!F:F,D70,'CBG Plants'!L:L,"Functional") -> 0 | H70: =COUNTIFS('CBG Plants'!F:F,D70,'CBG Plants'!L:L,"Under Construction") -> 0 | I70: =COUNTIFS('CBG Plants'!F:F,D70,'CBG Plants'!L:L,"Yet to start construction") -> 0 | M70: =IFERROR(N70-(AD70*365/1000),"") -> 79.38 | N70: =SUM(O70:Q70) -> 79.38 | O70: 0 | P70: 75.18 | Q70: 4.2 | R70: =IFERROR(U70-F70,"") -> 0 | S70: =IFERROR(T70*Assumptions!$C$4,"") -> 0 | T70: 0 | U70: =IFERROR(S70*Assumptions!$C$5,"")+IFERROR(V70*Assumptions!$C$8*Assumptions!$C$5,"") -> 0 | V70: 0 | W70: =IFERROR(ROUND(T70*(1+Assumptions!$C$7)^5,0),"") -> 0 | X70: =IFERROR(ROUND(W70*Assumptions!$C$4*Assumptions!$C$6,4),"")+IFERROR(ROUND(Y70*Assumptions!$C$8*Assumptions!$C$6,4),"") - F70 -> 0 | Y70: =IFERROR(ROUND(V70*(1+Assumptions!$C$7)^5,0),"") -> 0 | Z70: Operational Common Carrier | AA70: KG Basin Network | AB70: 94.5 | AC70: 16 | AD70: 0 | AE70: =IF(R70="","",IF(R70>=Control!$D$4,"Y","N")) -> N | AF70: =IF(S70="","",IF(M70>=Control!$D$5,"Y","N")) -> Y | AG70: =IF(T70="","",IF(AB70<=Control!$D$10,"Y","N")) -> Y | AI70: =IF(X70="","",IF(X70>=Control!$D$9,"Y","N")) -> N | AK70: =IFERROR(INDEX(Assumptions!$D$92:$D$115,MATCH(C70,Assumptions!$B$92:$B$115,0)),"Low") -> Low
B71: 68 | C71: AP | D71: Anakapalli | E71: =SUM(G71:I71) -> 4 | F71: =SUMIFS('CBG Plants'!N:N,'CBG Plants'!F:F,D71,'CBG Plants'!L:L,"Completed") +SUMIFS('CBG Plants'!N:N,'CBG Plants'!F:F,D71,'CBG Plants'!L:L,"Functional")+SUMIFS('CBG Plants'!N:N,'CBG Plants'!F:F,D71,'CBG Plants'!L:L,"Under Construction")+SUMIFS('CBG Plants'!N:N,'CBG Plants'!F:F,D71,'CBG Plants'!L:L,"Yet to start construction") -> 56 | G71: =COUNTIFS('CBG Plants'!F:F,D71,'CBG Plants'!L:L,"Completed") +COUNTIFS('CBG Plants'!F:F,D71,'CBG Plants'!L:L,"Functional") -> 0 | H71: =COUNTIFS('CBG Plants'!F:F,D71,'CBG Plants'!L:L,"Under Construction") -> 1 | I71: =COUNTIFS('CBG Plants'!F:F,D71,'CBG Plants'!L:L,"Yet to start construction") -> 3 | J71: AASMAK INDUSTRIES LIMITED | K71: ANDHRA BIO ENERGY PRIVATE LIMITED | L71: VARADOCHY BIO CNG PRIVATE LIMITED | M71: =IFERROR(N71-(AD71*365/1000),"") -> 76.965 | N71: =SUM(O71:Q71) -> 76.965 | O71: 0 | P71: 76.44 | Q71: 0.525 | R71: =IFERROR(U71-F71,"") -> -56 | S71: =IFERROR(T71*Assumptions!$C$4,"") -> 0 | T71: 0 | U71: =IFERROR(S71*Assumptions!$C$5,"")+IFERROR(V71*Assumptions!$C$8*Assumptions!$C$5,"") -> 0 | V71: 0 | W71: =IFERROR(ROUND(T71*(1+Assumptions!$C$7)^5,0),"") -> 0 | X71: =IFERROR(ROUND(W71*Assumptions!$C$4*Assumptions!$C$6,4),"")+IFERROR(ROUND(Y71*Assumptions!$C$8*Assumptions!$C$6,4),"") - F71 -> -56 | Y71: =IFERROR(ROUND(V71*(1+Assumptions!$C$7)^5,0),"") -> 0 | Z71: Operational Common Carrier | AA71: KG Basin Network | AB71: 94.7 | AC71: 16 | AD71: 0 | AE71: =IF(R71="","",IF(R71>=Control!$D$4,"Y","N")) -> N | AF71: =IF(S71="","",IF(M71>=Control!$D$5,"Y","N")) -> Y | AG71: =IF(T71="","",IF(AB71<=Control!$D$10,"Y","N")) -> Y | AI71: =IF(X71="","",IF(X71>=Control!$D$9,"Y","N")) -> N | AK71: =IFERROR(INDEX(Assumptions!$D$92:$D$115,MATCH(C71,Assumptions!$B$92:$B$115,0)),"Low") -> Low
B72: 69 | C72: AP | D72: Ananthapuramu | E72: =SUM(G72:I72) -> 1 | F72: =SUMIFS('CBG Plants'!N:N,'CBG Plants'!F:F,D72,'CBG Plants'!L:L,"Completed") +SUMIFS('CBG Plants'!N:N,'CBG Plants'!F:F,D72,'CBG Plants'!L:L,"Functional")+SUMIFS('CBG Plants'!N:N,'CBG Plants'!F:F,D72,'CBG Plants'!L:L,"Under Construction")+SUMIFS('CBG Plants'!N:N,'CBG Plants'!F:F,D72,'CBG Plants'!L:L,"Yet to start construction") -> 5 | G72: =COUNTIFS('CBG Plants'!F:F,D72,'CBG Plants'!L:L,"Completed") +COUNTIFS('CBG Plants'!F:F,D72,'CBG Plants'!L:L,"Functional") -> 0 | H72: =COUNTIFS('CBG Plants'!F:F,D72,'CBG Plants'!L:L,"Under Construction") -> 1 | I72: =COUNTIFS('CBG Plants'!F:F,D72,'CBG Plants'!L:L,"Yet to start construction") -> 0 | J72: NGREEN TECH LLP | M72: =IFERROR(N72-(AD72*365/1000),"") -> 108.99 | N72: =SUM(O72:Q72) -> 108.99 | O72: 0 | P72: 36.54 | Q72: 72.45 | R72: =IFERROR(U72-F72,"") -> -2.7878018 | S72: =IFERROR(T72*Assumptions!$C$4,"") -> 70 | T72: 28 | U72: =IFERROR(S72*Assumptions!$C$5,"")+IFERROR(V72*Assumptions!$C$8*Assumptions!$C$5,"") -> 2.2121982 | V72: 11164 | W72: =IFERROR(ROUND(T72*(1+Assumptions!$C$7)^5,0),"") -> 85 | X72: =IFERROR(ROUND(W72*Assumptions!$C$4*Assumptions!$C$6,4),"")+IFERROR(ROUND(Y72*Assumptions!$C$8*Assumptions!$C$6,4),"") - F72 -> 6.1957 | Y72: =IFERROR(ROUND(V72*(1+Assumptions!$C$7)^5,0),"") -> 34070 | Z72: Operational Common Carrier | AA72: KG Basin Network | AB72: 548.3 | AC72: 16 | AD72: 0 | AE72: =IF(R72="","",IF(R72>=Control!$D$4,"Y","N")) -> N | AF72: =IF(S72="","",IF(M72>=Control!$D$5,"Y","N")) -> Y | AG72: =IF(T72="","",IF(AB72<=Control!$D$10,"Y","N")) -> Y | AI72: =IF(X72="","",IF(X72>=Control!$D$9,"Y","N")) -> N | AK72: =IFERROR(INDEX(Assumptions!$D$92:$D$115,MATCH(C72,Assumptions!$B$92:$B$115,0)),"Low") -> Low
B73: 70 | C73: AP | D73: Annamayya | E73: =SUM(G73:I73) -> 1 | F73: =SUMIFS('CBG Plants'!N:N,'CBG Plants'!F:F,D73,'CBG Plants'!L:L,"Completed") +SUMIFS('CBG Plants'!N:N,'CBG Plants'!F:F,D73,'CBG Plants'!L:L,"Functional")+SUMIFS('CBG Plants'!N:N,'CBG Plants'!F:F,D73,'CBG Plants'!L:L,"Under Construction")+SUMIFS('CBG Plants'!N:N,'CBG Plants'!F:F,D73,'CBG Plants'!L:L,"Yet to start construction") -> 5 | G73: =COUNTIFS('CBG Plants'!F:F,D73,'CBG Plants'!L:L,"Completed") +COUNTIFS('CBG Plants'!F:F,D73,'CBG Plants'!L:L,"Functional") -> 0 | H73: =COUNTIFS('CBG Plants'!F:F,D73,'CBG Plants'!L:L,"Under Construction") -> 0 | I73: =COUNTIFS('CBG Plants'!F:F,D73,'CBG Plants'!L:L,"Yet to start construction") -> 1 | J73: SVS TRADERS | M73: =IFERROR(N73-(AD73*365/1000),"") -> 27.93 | N73: =SUM(O73:Q73) -> 27.93 | O73: 0 | P73: 18.48 | Q73: 9.45 | R73: =IFERROR(U73-F73,"") -> -5 | S73: =IFERROR(T73*Assumptions!$C$4,"") -> 0 | T73: 0 | U73: =IFERROR(S73*Assumptions!$C$5,"")+IFERROR(V73*Assumptions!$C$8*Assumptions!$C$5,"") -> 0 | V73: 0 | W73: =IFERROR(ROUND(T73*(1+Assumptions!$C$7)^5,0),"") -> 0 | X73: =IFERROR(ROUND(W73*Assumptions!$C$4*Assumptions!$C$6,4),"")+IFERROR(ROUND(Y73*Assumptions!$C$8*Assumptions!$C$6,4),"") - F73 -> -5 | Y73: =IFERROR(ROUND(V73*(1+Assumptions!$C$7)^5,0),"") -> 0 | Z73: Operational Common Carrier | AA73: KG Basin Network | AB73: 459.7 | AC73: 16 | AD73: 0 | AE73: =IF(R73="","",IF(R73>=Control!$D$4,"Y","N")) -> N | AF73: =IF(S73="","",IF(M73>=Control!$D$5,"Y","N")) -> N | AG73: =IF(T73="","",IF(AB73<=Control!$D$10,"Y","N")) -> Y | AI73: =IF(X73="","",IF(X73>=Control!$D$9,"Y","N")) -> N | AK73: =IFERROR(INDEX(Assumptions!$D$92:$D$115,MATCH(C73,Assumptions!$B$92:$B$115,0)),"Low") -> Low
B74: 71 | C74: AP | D74: Bapatla | E74: =SUM(G74:I74) -> 0 | F74: =SUMIFS('CBG Plants'!N:N,'CBG Plants'!F:F,D74,'CBG Plants'!L:L,"Completed") +SUMIFS('CBG Plants'!N:N,'CBG Plants'!F:F,D74,'CBG Plants'!L:L,"Functional")+SUMIFS('CBG Plants'!N:N,'CBG Plants'!F:F,D74,'CBG Plants'!L:L,"Under Construction")+SUMIFS('CBG Plants'!N:N,'CBG Plants'!F:F,D74,'CBG Plants'!L:L,"Yet to start construction") -> 0 | G74: =COUNTIFS('CBG Plants'!F:F,D74,'CBG Plants'!L:L,"Completed") +COUNTIFS('CBG Plants'!F:F,D74,'CBG Plants'!L:L,"Functional") -> 0 | H74: =COUNTIFS('CBG Plants'!F:F,D74,'CBG Plants'!L:L,"Under Construction") -> 0 | I74: =COUNTIFS('CBG Plants'!F:F,D74,'CBG Plants'!L:L,"Yet to start construction") -> 0 | M74: =IFERROR(N74-(AD74*365/1000),"") -> 273.525 | N74: =SUM(O74:Q74) -> 273.525 | O74: 0 | P74: 157.5 | Q74: 116.025 | R74: =IFERROR(U74-F74,"") -> 0 | S74: =IFERROR(T74*Assumptions!$C$4,"") -> 0 | T74: 0 | U74: =IFERROR(S74*Assumptions!$C$5,"")+IFERROR(V74*Assumptions!$C$8*Assumptions!$C$5,"") -> 0 | V74: 0 | W74: =IFERROR(ROUND(T74*(1+Assumptions!$C$7)^5,0),"") -> 0 | X74: =IFERROR(ROUND(W74*Assumptions!$C$4*Assumptions!$C$6,4),"")+IFERROR(ROUND(Y74*Assumptions!$C$8*Assumptions!$C$6,4),"") - F74 -> 0 | Y74: =IFERROR(ROUND(V74*(1+Assumptions!$C$7)^5,0),"") -> 0 | Z74: Operational Common Carrier | AA74: KG Basin Network | AB74: 205.7 | AC74: 16 | AD74: 0 | AE74: =IF(R74="","",IF(R74>=Control!$D$4,"Y","N")) -> N | AF74: =IF(S74="","",IF(M74>=Control!$D$5,"Y","N")) -> Y | AG74: =IF(T74="","",IF(AB74<=Control!$D$10,"Y","N")) -> Y | AI74: =IF(X74="","",IF(X74>=Control!$D$9,"Y","N")) -> N | AK74: =IFERROR(INDEX(Assumptions!$D$92:$D$115,MATCH(C74,Assumptions!$B$92:$B$115,0)),"Low") -> Low
B75: 72 | C75: AP | D75: Chittoor | E75: =SUM(G75:I75) -> 2 | F75: =SUMIFS('CBG Plants'!N:N,'CBG Plants'!F:F,D75,'CBG Plants'!L:L,"Completed") +SUMIFS('CBG Plants'!N:N,'CBG Plants'!F:F,D75,'CBG Plants'!L:L,"Functional")+SUMIFS('CBG Plants'!N:N,'CBG Plants'!F:F,D75,'CBG Plants'!L:L,"Under Construction")+SUMIFS('CBG Plants'!N:N,'CBG Plants'!F:F,D75,'CBG Plants'!L:L,"Yet to start construction") -> 16.2 | G75: =COUNTIFS('CBG Plants'!F:F,D75,'CBG Plants'!L:L,"Completed") +COUNTIFS('CBG Plants'!F:F,D75,'CBG Plants'!L:L,"Functional") -> 0 | H75: =COUNTIFS('CBG Plants'!F:F,D75,'CBG Plants'!L:L,"Under Construction") -> 0 | I75: =COUNTIFS('CBG Plants'!F:F,D75,'CBG Plants'!L:L,"Yet to start construction") -> 2 | J75: AIRA BIOENERGY PRIVATE LIMITED - PANNUR | K75: NANDARAPU BIOENERGY PRIVATE LIMITED - Vinjam, GD Nellore, Chittoor | M75: =IFERROR(N75-(AD75*365/1000),"") -> 28.56 | N75: =SUM(O75:Q75) -> 28.56 | O75: 0 | P75: 26.46 | Q75: 2.1 | R75: =IFERROR(U75-F75,"") -> -12.185115 | S75: =IFERROR(T75*Assumptions!$C$4,"") -> 127.5 | T75: 51 | U75: =IFERROR(S75*Assumptions!$C$5,"")+IFERROR(V75*Assumptions!$C$8*Assumptions!$C$5,"") -> 4.0148847 | V75: 18894 | W75: =IFERROR(ROUND(T75*(1+Assumptions!$C$7)^5,0),"") -> 156 | X75: =IFERROR(ROUND(W75*Assumptions!$C$4*Assumptions!$C$6,4),"")+IFERROR(ROUND(Y75*Assumptions!$C$8*Assumptions!$C$6,4),"") - F75 -> 4.2658 | Y75: =IFERROR(ROUND(V75*(1+Assumptions!$C$7)^5,0),"") -> 57660 | Z75: Operational Common Carrier | AA75: KG Basin Network | AB75: 506.1 | AC75: 16 | AD75: 0 | AE75: =IF(R75="","",IF(R75>=Control!$D$4,"Y","N")) -> N | AF75: =IF(S75="","",IF(M75>=Control!$D$5,"Y","N")) -> N | AG75: =IF(T75="","",IF(AB75<=Control!$D$10,"Y","N")) -> Y | AI75: =IF(X75="","",IF(X75>=Control!$D$9,"Y","N")) -> N | AK75: =IFERROR(INDEX(Assumptions!$D$92:$D$115,MATCH(C75,Assumptions!$B$92:$B$115,0)),"Low") -> Low
B76: 73 | C76: AP | D76: Dr. B.R. Ambedkar Konaseema | E76: =SUM(G76:I76) -> 0 | F76: =SUMIFS('CBG Plants'!N:N,'CBG Plants'!F:F,D76,'CBG Plants'!L:L,"Completed") +SUMIFS('CBG Plants'!N:N,'CBG Plants'!F:F,D76,'CBG Plants'!L:L,"Functional")+SUMIFS('CBG Plants'!N:N,'CBG Plants'!F:F,D76,'CBG Plants'!L:L,"Under Construction")+SUMIFS('CBG Plants'!N:N,'CBG Plants'!F:F,D76,'CBG Plants'!L:L,"Yet to start construction") -> 0 | G76: =COUNTIFS('CBG Plants'!F:F,D76,'CBG Plants'!L:L,"Completed") +COUNTIFS('CBG Plants'!F:F,D76,'CBG Plants'!L:L,"Functional") -> 0 | H76: =COUNTIFS('CBG Plants'!F:F,D76,'CBG Plants'!L:L,"Under Construction") -> 0 | I76: =COUNTIFS('CBG Plants'!F:F,D76,'CBG Plants'!L:L,"Yet to start construction") -> 0 | M76: =IFERROR(N76-(AD76*365/1000),"") -> 241.08 | N76: =SUM(O76:Q76) -> 241.08 | O76: 0 | P76: 236.88 | Q76: 4.2 | R76: =IFERROR(U76-F76,"") -> 0 | S76: =IFERROR(T76*Assumptions!$C$4,"") -> 0 | T76: 0 | U76: =IFERROR(S76*Assumptions!$C$5,"")+IFERROR(V76*Assumptions!$C$8*Assumptions!$C$5,"") -> 0 | V76: 0 | W76: =IFERROR(ROUND(T76*(1+Assumptions!$C$7)^5,0),"") -> 0 | X76: =IFERROR(ROUND(W76*Assumptions!$C$4*Assumptions!$C$6,4),"")+IFERROR(ROUND(Y76*Assumptions!$C$8*Assumptions!$C$6,4),"") - F76 -> 0 | Y76: =IFERROR(ROUND(V76*(1+Assumptions!$C$7)^5,0),"") -> 0 | Z76: Operational Common Carrier | AA76: KG Basin Network | AB76: 26.1 | AC76: 16 | AD76: 0 | AE76: =IF(R76="","",IF(R76>=Control!$D$4,"Y","N")) -> N | AF76: =IF(S76="","",IF(M76>=Control!$D$5,"Y","N")) -> Y | AG76: =IF(T76="","",IF(AB76<=Control!$D$10,"Y","N")) -> Y | AI76: =IF(X76="","",IF(X76>=Control!$D$9,"Y","N")) -> N | AK76: =IFERROR(INDEX(Assumptions!$D$92:$D$115,MATCH(C76,Assumptions!$B$92:$B$115,0)),"Low") -> Low
B77: 74 | C77: AP | D77: East Godavari | E77: =SUM(G77:I77) -> 9 | F77: =SUMIFS('CBG Plants'!N:N,'CBG Plants'!F:F,D77,'CBG Plants'!L:L,"Completed") +SUMIFS('CBG Plants'!N:N,'CBG Plants'!F:F,D77,'CBG Plants'!L:L,"Functional")+SUMIFS('CBG Plants'!N:N,'CBG Plants'!F:F,D77,'CBG Plants'!L:L,"Under Construction")+SUMIFS('CBG Plants'!N:N,'CBG Plants'!F:F,D77,'CBG Plants'!L:L,"Yet to start construction") -> 116 | G77: =COUNTIFS('CBG Plants'!F:F,D77,'CBG Plants'!L:L,"Completed") +COUNTIFS('CBG Plants'!F:F,D77,'CBG Plants'!L:L,"Functional") -> 1 | H77: =COUNTIFS('CBG Plants'!F:F,D77,'CBG Plants'!L:L,"Under Construction") -> 2 | I77: =COUNTIFS('CBG Plants'!F:F,D77,'CBG Plants'!L:L,"Yet to start construction") -> 6 | J77: AASMUK ENTERPRISES PRIVATE LIMITED | K77: Rajahmundry 2 CBG Plant | L77: Rajahmundry-1 CBG Plant | M77: =IFERROR(N77-(AD77*365/1000),"") -> 266.64 | N77: =SUM(O77:Q77) -> 288.54 | O77: 0 | P77: 248.64 | Q77: 39.9 | R77: =IFERROR(U77-F77,"") -> -114.29891 | S77: =IFERROR(T77*Assumptions!$C$4,"") -> 40 | T77: 16 | U77: =IFERROR(S77*Assumptions!$C$5,"")+IFERROR(V77*Assumptions!$C$8*Assumptions!$C$5,"") -> 1.701093 | V77: 49860 | W77: =IFERROR(ROUND(T77*(1+Assumptions!$C$7)^5,0),"") -> 49 | X77: =IFERROR(ROUND(W77*Assumptions!$C$4*Assumptions!$C$6,4),"")+IFERROR(ROUND(Y77*Assumptions!$C$8*Assumptions!$C$6,4),"") - F77 -> -107.3263 | Y77: =IFERROR(ROUND(V77*(1+Assumptions!$C$7)^5,0),"") -> 152161 | Z77: Operational Common Carrier | AA77: KG Basin Network | AB77: 55.9 | AC77: 16 | AD77: 60 | AE77: =IF(R77="","",IF(R77>=Control!$D$4,"Y","N")) -> N | AF77: =IF(S77="","",IF(M77>=Control!$D$5,"Y","N")) -> Y | AG77: =IF(T77="","",IF(AB77<=Control!$D$10,"Y","N")) -> Y | AI77: =IF(X77="","",IF(X77>=Control!$D$9,"Y","N")) -> N | AK77: =IFERROR(INDEX(Assumptions!$D$92:$D$115,MATCH(C77,Assumptions!$B$92:$B$115,0)),"Low") -> Low
B78: 75 | C78: AP | D78: Eluru | E78: =SUM(G78:I78) -> 2 | F78: =SUMIFS('CBG Plants'!N:N,'CBG Plants'!F:F,D78,'CBG Plants'!L:L,"Completed") +SUMIFS('CBG Plants'!N:N,'CBG Plants'!F:F,D78,'CBG Plants'!L:L,"Functional")+SUMIFS('CBG Plants'!N:N,'CBG Plants'!F:F,D78,'CBG Plants'!L:L,"Under Construction")+SUMIFS('CBG Plants'!N:N,'CBG Plants'!F:F,D78,'CBG Plants'!L:L,"Yet to start construction") -> 23 | G78: =COUNTIFS('CBG Plants'!F:F,D78,'CBG Plants'!L:L,"Completed") +COUNTIFS('CBG Plants'!F:F,D78,'CBG Plants'!L:L,"Functional") -> 0 | H78: =COUNTIFS('CBG Plants'!F:F,D78,'CBG Plants'!L:L,"Under Construction") -> 0 | I78: =COUNTIFS('CBG Plants'!F:F,D78,'CBG Plants'!L:L,"Yet to start construction") -> 2 | J78: Nitinsai | K78: ARJUN BIO PRODUCTS | M78: =IFERROR(N78-(AD78*365/1000),"") -> 313.32 | N78: =SUM(O78:Q78) -> 313.32 | O78: 0 | P78: 204.12 | Q78: 109.2 | R78: =IFERROR(U78-F78,"") -> -23 | S78: =IFERROR(T78*Assumptions!$C$4,"") -> 0 | T78: 0 | U78: =IFERROR(S78*Assumptions!$C$5,"")+IFERROR(V78*Assumptions!$C$8*Assumptions!$C$5,"") -> 0 | V78: 0 | W78: =IFERROR(ROUND(T78*(1+Assumptions!$C$7)^5,0),"") -> 0 | X78: =IFERROR(ROUND(W78*Assumptions!$C$4*Assumptions!$C$6,4),"")+IFERROR(ROUND(Y78*Assumptions!$C$8*Assumptions!$C$6,4),"") - F78 -> -23 | Y78: =IFERROR(ROUND(V78*(1+Assumptions!$C$7)^5,0),"") -> 0 | Z78: Operational Common Carrier | AA78: KG Basin Network | AB78: 113 | AC78: 16 | AD78: 0 | AE78: =IF(R78="","",IF(R78>=Control!$D$4,"Y","N")) -> N | AF78: =IF(S78="","",IF(M78>=Control!$D$5,"Y","N")) -> Y | AG78: =IF(T78="","",IF(AB78<=Control!$D$10,"Y","N")) -> Y | AI78: =IF(X78="","",IF(X78>=Control!$D$9,"Y","N")) -> N | AK78: =IFERROR(INDEX(Assumptions!$D$92:$D$115,MATCH(C78,Assumptions!$B$92:$B$115,0)),"Low") -> Low
B79: 76 | C79: AP | D79: Guntur | E79: =SUM(G79:I79) -> 2 | F79: =SUMIFS('CBG Plants'!N:N,'CBG Plants'!F:F,D79,'CBG Plants'!L:L,"Completed") +SUMIFS('CBG Plants'!N:N,'CBG Plants'!F:F,D79,'CBG Plants'!L:L,"Functional")+SUMIFS('CBG Plants'!N:N,'CBG Plants'!F:F,D79,'CBG Plants'!L:L,"Under Construction")+SUMIFS('CBG Plants'!N:N,'CBG Plants'!F:F,D79,'CBG Plants'!L:L,"Yet to start construction") -> 14 | G79: =COUNTIFS('CBG Plants'!F:F,D79,'CBG Plants'!L:L,"Completed") +COUNTIFS('CBG Plants'!F:F,D79,'CBG Plants'!L:L,"Functional") -> 0 | H79: =COUNTIFS('CBG Plants'!F:F,D79,'CBG Plants'!L:L,"Under Construction") -> 0 | I79: =COUNTIFS('CBG Plants'!F:F,D79,'CBG Plants'!L:L,"Yet to start construction") -> 2 | J79: Bhairava BioAbilites | K79: Guntur Municipal Corporation Compressed CNG unit | M79: =IFERROR(N79-(AD79*365/1000),"") -> 199.185 | N79: =SUM(O79:Q79) -> 199.185 | O79: 0 | P79: 89.46 | Q79: 109.725 | R79: =IFERROR(U79-F79,"") -> -13.022186 | S79: =IFERROR(T79*Assumptions!$C$4,"") -> 32.5 | T79: 13 | U79: =IFERROR(S79*Assumptions!$C$5,"")+IFERROR(V79*Assumptions!$C$8*Assumptions!$C$5,"") -> 0.977814 | V79: 280 | W79: =IFERROR(ROUND(T79*(1+Assumptions!$C$7)^5,0),"") -> 40 | X79: =IFERROR(ROUND(W79*Assumptions!$C$4*Assumptions!$C$6,4),"")+IFERROR(ROUND(Y79*Assumptions!$C$8*Assumptions!$C$6,4),"") - F79 -> -8.9857 | Y79: =IFERROR(ROUND(V79*(1+Assumptions!$C$7)^5,0),"") -> 854 | Z79: Operational Common Carrier | AA79: KG Basin Network | AB79: 187.9 | AC79: 16 | AD79: 0 | AE79: =IF(R79="","",IF(R79>=Control!$D$4,"Y","N")) -> N | AF79: =IF(S79="","",IF(M79>=Control!$D$5,"Y","N")) -> Y | AG79: =IF(T79="","",IF(AB79<=Control!$D$10,"Y","N")) -> Y | AI79: =IF(X79="","",IF(X79>=Control!$D$9,"Y","N")) -> N | AK79: =IFERROR(INDEX(Assumptions!$D$92:$D$115,MATCH(C79,Assumptions!$B$92:$B$115,0)),"Low") -> Low
B80: 77 | C80: AP | D80: Kakinada | E80: =SUM(G80:I80) -> 6 | F80: =SUMIFS('CBG Plants'!N:N,'CBG Plants'!F:F,D80,'CBG Plants'!L:L,"Completed") +SUMIFS('CBG Plants'!N:N,'CBG Plants'!F:F,D80,'CBG Plants'!L:L,"Functional")+SUMIFS('CBG Plants'!N:N,'CBG Plants'!F:F,D80,'CBG Plants'!L:L,"Under Construction")+SUMIFS('CBG Plants'!N:N,'CBG Plants'!F:F,D80,'CBG Plants'!L:L,"Yet to start construction") -> 133.5 | G80: =COUNTIFS('CBG Plants'!F:F,D80,'CBG Plants'!L:L,"Completed") +COUNTIFS('CBG Plants'!F:F,D80,'CBG Plants'!L:L,"Functional") -> 1 | H80: =COUNTIFS('CBG Plants'!F:F,D80,'CBG Plants'!L:L,"Under Construction") -> 4 | I80: =COUNTIFS('CBG Plants'!F:F,D80,'CBG Plants'!L:L,"Yet to start construction") -> 1 | J80: Synergy Biorefineries Private Limited | K80: ARUNODAYA GREEN FUELS LIMITED | L80: Kakinada 1 CBG Plant | M80: =IFERROR(N80-(AD80*365/1000),"") -> 198.575 | N80: =SUM(O80:Q80) -> 293.475 | O80: 0 | P80: 287.7 | Q80: 5.775 | R80: =IFERROR(U80-F80,"") -> -131.82974 | S80: =IFERROR(T80*Assumptions!$C$4,"") -> 32.5 | T80: 13 | U80: =IFERROR(S80*Assumptions!$C$5,"")+IFERROR(V80*Assumptions!$C$8*Assumptions!$C$5,"") -> 1.670259 | V80: 69180 | W80: =IFERROR(ROUND(T80*(1+Assumptions!$C$7)^5,0),"") -> 40 | X80: =IFERROR(ROUND(W80*Assumptions!$C$4*Assumptions!$C$6,4),"")+IFERROR(ROUND(Y80*Assumptions!$C$8*Assumptions!$C$6,4),"") - F80 -> -124.9637 | Y80: =IFERROR(ROUND(V80*(1+Assumptions!$C$7)^5,0),"") -> 211121 | Z80: Operational Common Carrier | AA80: KG Basin Network | AB80: 19.2 | AC80: 16 | AD80: 260 | AE80: =IF(R80="","",IF(R80>=Control!$D$4,"Y","N")) -> N | AF80: =IF(S80="","",IF(M80>=Control!$D$5,"Y","N")) -> Y | AG80: =IF(T80="","",IF(AB80<=Control!$D$10,"Y","N")) -> Y | AI80: =IF(X80="","",IF(X80>=Control!$D$9,"Y","N")) -> N | AK80: =IFERROR(INDEX(Assumptions!$D$92:$D$115,MATCH(C80,Assumptions!$B$92:$B$115,0)),"Low") -> Low
B81: 78 | C81: AP | D81: Krishna | E81: =SUM(G81:I81) -> 1 | F81: =SUMIFS('CBG Plants'!N:N,'CBG Plants'!F:F,D81,'CBG Plants'!L:L,"Completed") +SUMIFS('CBG Plants'!N:N,'CBG Plants'!F:F,D81,'CBG Plants'!L:L,"Functional")+SUMIFS('CBG Plants'!N:N,'CBG Plants'!F:F,D81,'CBG Plants'!L:L,"Under Construction")+SUMIFS('CBG Plants'!N:N,'CBG Plants'!F:F,D81,'CBG Plants'!L:L,"Yet to start construction") -> 12 | G81: =COUNTIFS('CBG Plants'!F:F,D81,'CBG Plants'!L:L,"Completed") +COUNTIFS('CBG Plants'!F:F,D81,'CBG Plants'!L:L,"Functional") -> 0 | H81: =COUNTIFS('CBG Plants'!F:F,D81,'CBG Plants'!L:L,"Under Construction") -> 0 | I81: =COUNTIFS('CBG Plants'!F:F,D81,'CBG Plants'!L:L,"Yet to start construction") -> 1 | J81: AARADHYA BIO FUEL PRIVATE LIMITED | M81: =IFERROR(N81-(AD81*365/1000),"") -> 278.67 | N81: =SUM(O81:Q81) -> 278.67 | O81: 0 | P81: 254.52 | Q81: 24.15 | R81: =IFERROR(U81-F81,"") -> -9.2922087 | S81: =IFERROR(T81*Assumptions!$C$4,"") -> 80 | T81: 32 | U81: =IFERROR(S81*Assumptions!$C$5,"")+IFERROR(V81*Assumptions!$C$8*Assumptions!$C$5,"") -> 2.7077913 | V81: 30626 | W81: =IFERROR(ROUND(T81*(1+Assumptions!$C$7)^5,0),"") -> 98 | X81: =IFERROR(ROUND(W81*Assumptions!$C$4*Assumptions!$C$6,4),"")+IFERROR(ROUND(Y81*Assumptions!$C$8*Assumptions!$C$6,4),"") - F81 -> 1.8155 | Y81: =IFERROR(ROUND(V81*(1+Assumptions!$C$7)^5,0),"") -> 93463 | Z81: Operational Common Carrier | AA81: KG Basin Network | AB81: 132.5 | AC81: 16 | AD81: 0 | AE81: =IF(R81="","",IF(R81>=Control!$D$4,"Y","N")) -> N | AF81: =IF(S81="","",IF(M81>=Control!$D$5,"Y","N")) -> Y | AG81: =IF(T81="","",IF(AB81<=Control!$D$10,"Y","N")) -> Y | AI81: =IF(X81="","",IF(X81>=Control!$D$9,"Y","N")) -> N | AK81: =IFERROR(INDEX(Assumptions!$D$92:$D$115,MATCH(C81,Assumptions!$B$92:$B$115,0)),"Low") -> Low
B82: 79 | C82: AP | D82: Kurnool | E82: =SUM(G82:I82) -> 3 | F82: =SUMIFS('CBG Plants'!N:N,'CBG Plants'!F:F,D82,'CBG Plants'!L:L,"Completed") +SUMIFS('CBG Plants'!N:N,'CBG Plants'!F:F,D82,'CBG Plants'!L:L,"Functional")+SUMIFS('CBG Plants'!N:N,'CBG Plants'!F:F,D82,'CBG Plants'!L:L,"Under Construction")+SUMIFS('CBG Plants'!N:N,'CBG Plants'!F:F,D82,'CBG Plants'!L:L,"Yet to start construction") -> 41.85 | G82: =COUNTIFS('CBG Plants'!F:F,D82,'CBG Plants'!L:L,"Completed") +COUNTIFS('CBG Plants'!F:F,D82,'CBG Plants'!L:L,"Functional") -> 1 | H82: =COUNTIFS('CBG Plants'!F:F,D82,'CBG Plants'!L:L,"Under Construction") -> 1 | I82: =COUNTIFS('CBG Plants'!F:F,D82,'CBG Plants'!L:L,"Yet to start construction") -> 1 | J82: Kurnool CBG Plant | K82: AARADHYA BIO GAS PRIVATE LIMITED | L82: ADONI PROJECT- 20 TPD | M82: =IFERROR(N82-(AD82*365/1000),"") -> 52.13 | N82: =SUM(O82:Q82) -> 59.43 | O82: 0 | P82: 24.78 | Q82: 34.65 | R82: =IFERROR(U82-F82,"") -> -40.872186 | S82: =IFERROR(T82*Assumptions!$C$4,"") -> 32.5 | T82: 13 | U82: =IFERROR(S82*Assumptions!$C$5,"")+IFERROR(V82*Assumptions!$C$8*Assumptions!$C$5,"") -> 0.977814 | V82: 280 | W82: =IFERROR(ROUND(T82*(1+Assumptions!$C$7)^5,0),"") -> 40 | X82: =IFERROR(ROUND(W82*Assumptions!$C$4*Assumptions!$C$6,4),"")+IFERROR(ROUND(Y82*Assumptions!$C$8*Assumptions!$C$6,4),"") - F82 -> -36.8357 | Y82: =IFERROR(ROUND(V82*(1+Assumptions!$C$7)^5,0),"") -> 854 | Z82: Operational Common Carrier | AA82: KG Basin Network | AB82: 509.7 | AC82: 16 | AD82: 20 | AE82: =IF(R82="","",IF(R82>=Control!$D$4,"Y","N")) -> N | AF82: =IF(S82="","",IF(M82>=Control!$D$5,"Y","N")) -> Y | AG82: =IF(T82="","",IF(AB82<=Control!$D$10,"Y","N")) -> Y | AI82: =IF(X82="","",IF(X82>=Control!$D$9,"Y","N")) -> N | AK82: =IFERROR(INDEX(Assumptions!$D$92:$D$115,MATCH(C82,Assumptions!$B$92:$B$115,0)),"Low") -> Low
B83: 80 | C83: AP | D83: Nandyal | E83: =SUM(G83:I83) -> 2 | F83: =SUMIFS('CBG Plants'!N:N,'CBG Plants'!F:F,D83,'CBG Plants'!L:L,"Completed") +SUMIFS('CBG Plants'!N:N,'CBG Plants'!F:F,D83,'CBG Plants'!L:L,"Functional")+SUMIFS('CBG Plants'!N:N,'CBG Plants'!F:F,D83,'CBG Plants'!L:L,"Under Construction")+SUMIFS('CBG Plants'!N:N,'CBG Plants'!F:F,D83,'CBG Plants'!L:L,"Yet to start construction") -> 22 | G83: =COUNTIFS('CBG Plants'!F:F,D83,'CBG Plants'!L:L,"Completed") +COUNTIFS('CBG Plants'!F:F,D83,'CBG Plants'!L:L,"Functional") -> 0 | H83: =COUNTIFS('CBG Plants'!F:F,D83,'CBG Plants'!L:L,"Under Construction") -> 0 | I83: =COUNTIFS('CBG Plants'!F:F,D83,'CBG Plants'!L:L,"Yet to start construction") -> 2 | J83: EcoMax Nandi plant | K83: dakshayani CBG | M83: =IFERROR(N83-(AD83*365/1000),"") -> 360.255 | N83: =SUM(O83:Q83) -> 360.255 | O83: 0 | P83: 184.38 | Q83: 175.875 | R83: =IFERROR(U83-F83,"") -> -22 | S83: =IFERROR(T83*Assumptions!$C$4,"") -> 0 | T83: 0 | U83: =IFERROR(S83*Assumptions!$C$5,"")+IFERROR(V83*Assumptions!$C$8*Assumptions!$C$5,"") -> 0 | V83: 0 | W83: =IFERROR(ROUND(T83*(1+Assumptions!$C$7)^5,0),"") -> 0 | X83: =IFERROR(ROUND(W83*Assumptions!$C$4*Assumptions!$C$6,4),"")+IFERROR(ROUND(Y83*Assumptions!$C$8*Assumptions!$C$6,4),"") - F83 -> -22 | Y83: =IFERROR(ROUND(V83*(1+Assumptions!$C$7)^5,0),"") -> 0 | Z83: Operational Common Carrier | AA83: KG Basin Network | AB83: 425.6 | AC83: 16 | AD83: 0 | AE83: =IF(R83="","",IF(R83>=Control!$D$4,"Y","N")) -> N | AF83: =IF(S83="","",IF(M83>=Control!$D$5,"Y","N")) -> Y | AG83: =IF(T83="","",IF(AB83<=Control!$D$10,"Y","N")) -> Y | AI83: =IF(X83="","",IF(X83>=Control!$D$9,"Y","N")) -> N | AK83: =IFERROR(INDEX(Assumptions!$D$92:$D$115,MATCH(C83,Assumptions!$B$92:$B$115,0)),"Low") -> Low
B84: 81 | C84: AP | D84: Ntr | E84: =SUM(G84:I84) -> 6 | F84: =SUMIFS('CBG Plants'!N:N,'CBG Plants'!F:F,D84,'CBG Plants'!L:L,"Completed") +SUMIFS('CBG Plants'!N:N,'CBG Plants'!F:F,D84,'CBG Plants'!L:L,"Functional")+SUMIFS('CBG Plants'!N:N,'CBG Plants'!F:F,D84,'CBG Plants'!L:L,"Under Construction")+SUMIFS('CBG Plants'!N:N,'CBG Plants'!F:F,D84,'CBG Plants'!L:L,"Yet to start construction") -> 57 | G84: =COUNTIFS('CBG Plants'!F:F,D84,'CBG Plants'!L:L,"Completed") +COUNTIFS('CBG Plants'!F:F,D84,'CBG Plants'!L:L,"Functional") -> 0 | H84: =COUNTIFS('CBG Plants'!F:F,D84,'CBG Plants'!L:L,"Under Construction") -> 2 | I84: =COUNTIFS('CBG Plants'!F:F,D84,'CBG Plants'!L:L,"Yet to start construction") -> 4 | J84: Vijayawada CBG Plant | K84: 15 TPD CBG Project at NTR, Andhra Pradesh | L84: BUNSU BIO CNG | M84: =IFERROR(N84-(AD84*365/1000),"") -> 141.12 | N84: =SUM(O84:Q84) -> 141.12 | O84: 0 | P84: 101.22 | Q84: 39.9 | R84: =IFERROR(U84-F84,"") -> -57 | S84: =IFERROR(T84*Assumptions!$C$4,"") -> 0 | T84: 0 | U84: =IFERROR(S84*Assumptions!$C$5,"")+IFERROR(V84*Assumptions!$C$8*Assumptions!$C$5,"") -> 0 | V84: 0 | W84: =IFERROR(ROUND(T84*(1+Assumptions!$C$7)^5,0),"") -> 0 | X84: =IFERROR(ROUND(W84*Assumptions!$C$4*Assumptions!$C$6,4),"")+IFERROR(ROUND(Y84*Assumptions!$C$8*Assumptions!$C$6,4),"") - F84 -> -57 | Y84: =IFERROR(ROUND(V84*(1+Assumptions!$C$7)^5,0),"") -> 0 | Z84: Operational Common Carrier | AA84: KG Basin Network | AB84: 188.9 | AC84: 16 | AD84: 0 | AE84: =IF(R84="","",IF(R84>=Control!$D$4,"Y","N")) -> N | AF84: =IF(S84="","",IF(M84>=Control!$D$5,"Y","N")) -> Y | AG84: =IF(T84="","",IF(AB84<=Control!$D$10,"Y","N")) -> Y | AI84: =IF(X84="","",IF(X84>=Control!$D$9,"Y","N")) -> N | AK84: =IFERROR(INDEX(Assumptions!$D$92:$D$115,MATCH(C84,Assumptions!$B$92:$B$115,0)),"Low") -> Low
B85: 82 | C85: AP | D85: Palnadu | E85: =SUM(G85:I85) -> 3 | F85: =SUMIFS('CBG Plants'!N:N,'CBG Plants'!F:F,D85,'CBG Plants'!L:L,"Completed") +SUMIFS('CBG Plants'!N:N,'CBG Plants'!F:F,D85,'CBG Plants'!L:L,"Functional")+SUMIFS('CBG Plants'!N:N,'CBG Plants'!F:F,D85,'CBG Plants'!L:L,"Under Construction")+SUMIFS('CBG Plants'!N:N,'CBG Plants'!F:F,D85,'CBG Plants'!L:L,"Yet to start construction") -> 15.85 | G85: =COUNTIFS('CBG Plants'!F:F,D85,'CBG Plants'!L:L,"Completed") +COUNTIFS('CBG Plants'!F:F,D85,'CBG Plants'!L:L,"Functional") -> 1 | H85: =COUNTIFS('CBG Plants'!F:F,D85,'CBG Plants'!L:L,"Under Construction") -> 0 | I85: =COUNTIFS('CBG Plants'!F:F,D85,'CBG Plants'!L:L,"Yet to start construction") -> 2 | J85: DELTA BIO GAS PRIVATE LIMITED | K85: BIOGAS /CBG/BIO CNG | L85: PIDUGURALLA PROJECT -20 TPD | M85: =IFERROR(N85-(AD85*365/1000),"") -> 144.635 | N85: =SUM(O85:Q85) -> 151.935 | O85: 0 | P85: 91.56 | Q85: 60.375 | R85: =IFERROR(U85-F85,"") -> -15.85 | S85: =IFERROR(T85*Assumptions!$C$4,"") -> 0 | T85: 0 | U85: =IFERROR(S85*Assumptions!$C$5,"")+IFERROR(V85*Assumptions!$C$8*Assumptions!$C$5,"") -> 0 | V85: 0 | W85: =IFERROR(ROUND(T85*(1+Assumptions!$C$7)^5,0),"") -> 0 | X85: =IFERROR(ROUND(W85*Assumptions!$C$4*Assumptions!$C$6,4),"")+IFERROR(ROUND(Y85*Assumptions!$C$8*Assumptions!$C$6,4),"") - F85 -> -15.85 | Y85: =IFERROR(ROUND(V85*(1+Assumptions!$C$7)^5,0),"") -> 0 | Z85: Operational Common Carrier | AA85: KG Basin Network | AB85: 257.2 | AC85: 16 | AD85: 20 | AE85: =IF(R85="","",IF(R85>=Control!$D$4,"Y","N")) -> N | AF85: =IF(S85="","",IF(M85>=Control!$D$5,"Y","N")) -> Y | AG85: =IF(T85="","",IF(AB85<=Control!$D$10,"Y","N")) -> Y | AI85: =IF(X85="","",IF(X85>=Control!$D$9,"Y","N")) -> N | AK85: =IFERROR(INDEX(Assumptions!$D$92:$D$115,MATCH(C85,Assumptions!$B$92:$B$115,0)),"Low") -> Low
B86: 83 | C86: AP | D86: Parvathipuram Manyam | E86: =SUM(G86:I86) -> 0 | F86: =SUMIFS('CBG Plants'!N:N,'CBG Plants'!F:F,D86,'CBG Plants'!L:L,"Completed") +SUMIFS('CBG Plants'!N:N,'CBG Plants'!F:F,D86,'CBG Plants'!L:L,"Functional")+SUMIFS('CBG Plants'!N:N,'CBG Plants'!F:F,D86,'CBG Plants'!L:L,"Under Construction")+SUMIFS('CBG Plants'!N:N,'CBG Plants'!F:F,D86,'CBG Plants'!L:L,"Yet to start construction") -> 0 | G86: =COUNTIFS('CBG Plants'!F:F,D86,'CBG Plants'!L:L,"Completed") +COUNTIFS('CBG Plants'!F:F,D86,'CBG Plants'!L:L,"Functional") -> 0 | H86: =COUNTIFS('CBG Plants'!F:F,D86,'CBG Plants'!L:L,"Under Construction") -> 0 | I86: =COUNTIFS('CBG Plants'!F:F,D86,'CBG Plants'!L:L,"Yet to start construction") -> 0 | M86: =IFERROR(N86-(AD86*365/1000),"") -> 134.82 | N86: =SUM(O86:Q86) -> 134.82 | O86: 0 | P86: 105.42 | Q86: 29.4 | R86: =IFERROR(U86-F86,"") -> 0 | S86: =IFERROR(T86*Assumptions!$C$4,"") -> 0 | T86: 0 | U86: =IFERROR(S86*Assumptions!$C$5,"")+IFERROR(V86*Assumptions!$C$8*Assumptions!$C$5,"") -> 0 | V86: 0 | W86: =IFERROR(ROUND(T86*(1+Assumptions!$C$7)^5,0),"") -> 0 | X86: =IFERROR(ROUND(W86*Assumptions!$C$4*Assumptions!$C$6,4),"")+IFERROR(ROUND(Y86*Assumptions!$C$8*Assumptions!$C$6,4),"") - F86 -> 0 | Y86: =IFERROR(ROUND(V86*(1+Assumptions!$C$7)^5,0),"") -> 0 | Z86: Operational Common Carrier | AA86: KG Basin Network | AB86: 234.8 | AC86: 16 | AD86: 0 | AE86: =IF(R86="","",IF(R86>=Control!$D$4,"Y","N")) -> N | AF86: =IF(S86="","",IF(M86>=Control!$D$5,"Y","N")) -> Y | AG86: =IF(T86="","",IF(AB86<=Control!$D$10,"Y","N")) -> Y | AI86: =IF(X86="","",IF(X86>=Control!$D$9,"Y","N")) -> N | AK86: =IFERROR(INDEX(Assumptions!$D$92:$D$115,MATCH(C86,Assumptions!$B$92:$B$115,0)),"Low") -> Low
B87: 84 | C87: AP | D87: Prakasam | E87: =SUM(G87:I87) -> 7 | F87: =SUMIFS('CBG Plants'!N:N,'CBG Plants'!F:F,D87,'CBG Plants'!L:L,"Completed") +SUMIFS('CBG Plants'!N:N,'CBG Plants'!F:F,D87,'CBG Plants'!L:L,"Functional")+SUMIFS('CBG Plants'!N:N,'CBG Plants'!F:F,D87,'CBG Plants'!L:L,"Under Construction")+SUMIFS('CBG Plants'!N:N,'CBG Plants'!F:F,D87,'CBG Plants'!L:L,"Yet to start construction") -> 79 | G87: =COUNTIFS('CBG Plants'!F:F,D87,'CBG Plants'!L:L,"Completed") +COUNTIFS('CBG Plants'!F:F,D87,'CBG Plants'!L:L,"Functional") -> 0 | H87: =COUNTIFS('CBG Plants'!F:F,D87,'CBG Plants'!L:L,"Under Construction") -> 0 | I87: =COUNTIFS('CBG Plants'!F:F,D87,'CBG Plants'!L:L,"Yet to start construction") -> 7 | J87: Prakasam | K87: BRAMARAMBHA MALLIKARJUNA BIO ENERGY PRIVATE LIMITED | L87: DHARANI RENEW PROJECTS PRIVATE LIMITED | M87: =IFERROR(N87-(AD87*365/1000),"") -> 54.915 | N87: =SUM(O87:Q87) -> 54.915 | O87: 0 | P87: 32.34 | Q87: 22.575 | R87: =IFERROR(U87-F87,"") -> -78.022186 | S87: =IFERROR(T87*Assumptions!$C$4,"") -> 32.5 | T87: 13 | U87: =IFERROR(S87*Assumptions!$C$5,"")+IFERROR(V87*Assumptions!$C$8*Assumptions!$C$5,"") -> 0.977814 | V87: 280 | W87: =IFERROR(ROUND(T87*(1+Assumptions!$C$7)^5,0),"") -> 40 | X87: =IFERROR(ROUND(W87*Assumptions!$C$4*Assumptions!$C$6,4),"")+IFERROR(ROUND(Y87*Assumptions!$C$8*Assumptions!$C$6,4),"") - F87 -> -73.9857 | Y87: =IFERROR(ROUND(V87*(1+Assumptions!$C$7)^5,0),"") -> 854 | Z87: Operational Common Carrier | AA87: KG Basin Network | AB87: 316.6 | AC87: 16 | AD87: 0 | AE87: =IF(R87="","",IF(R87>=Control!$D$4,"Y","N")) -> N | AF87: =IF(S87="","",IF(M87>=Control!$D$5,"Y","N")) -> Y | AG87: =IF(T87="","",IF(AB87<=Control!$D$10,"Y","N")) -> Y | AI87: =IF(X87="","",IF(X87>=Control!$D$9,"Y","N")) -> N | AK87: =IFERROR(INDEX(Assumptions!$D$92:$D$115,MATCH(C87,Assumptions!$B$92:$B$115,0)),"Low") -> Low
B88: 85 | C88: AP | D88: Sri Potti Sriramulu Nellore | E88: =SUM(G88:I88) -> 0 | F88: =SUMIFS('CBG Plants'!N:N,'CBG Plants'!F:F,D88,'CBG Plants'!L:L,"Completed") +SUMIFS('CBG Plants'!N:N,'CBG Plants'!F:F,D88,'CBG Plants'!L:L,"Functional")+SUMIFS('CBG Plants'!N:N,'CBG Plants'!F:F,D88,'CBG Plants'!L:L,"Under Construction")+SUMIFS('CBG Plants'!N:N,'CBG Plants'!F:F,D88,'CBG Plants'!L:L,"Yet to start construction") -> 0 | G88: =COUNTIFS('CBG Plants'!F:F,D88,'CBG Plants'!L:L,"Completed") +COUNTIFS('CBG Plants'!F:F,D88,'CBG Plants'!L:L,"Functional") -> 0 | H88: =COUNTIFS('CBG Plants'!F:F,D88,'CBG Plants'!L:L,"Under Construction") -> 0 | I88: =COUNTIFS('CBG Plants'!F:F,D88,'CBG Plants'!L:L,"Yet to start construction") -> 0 | J88: Nellore CBG Plant | K88: USHODAYA BIO GAS PRIVATE LIMITED | L88: Energia Biofuels LLP | M88: =IFERROR(N88-(AD88*365/1000),"") -> 249.165 | N88: =SUM(O88:Q88) -> 249.165 | O88: 0 | P88: 246.54 | Q88: 2.625 | R88: =IFERROR(U88-F88,"") -> 1.5656265 | S88: =IFERROR(T88*Assumptions!$C$4,"") -> 50 | T88: 20 | U88: =IFERROR(S88*Assumptions!$C$5,"")+IFERROR(V88*Assumptions!$C$8*Assumptions!$C$5,"") -> 1.5656265 | V88: 6530 | W88: =IFERROR(ROUND(T88*(1+Assumptions!$C$7)^5,0),"") -> 61 | X88: =IFERROR(ROUND(W88*Assumptions!$C$4*Assumptions!$C$6,4),"")+IFERROR(ROUND(Y88*Assumptions!$C$8*Assumptions!$C$6,4),"") - F88 -> 7.9588 | Y88: =IFERROR(ROUND(V88*(1+Assumptions!$C$7)^5,0),"") -> 19928 | Z88: Operational Common Carrier | AA88: KG Basin Network | AB88: 335.2 | AC88: 16 | AD88: 0 | AE88: =IF(R88="","",IF(R88>=Control!$D$4,"Y","N")) -> N | AF88: =IF(S88="","",IF(M88>=Control!$D$5,"Y","N")) -> Y | AG88: =IF(T88="","",IF(AB88<=Control!$D$10,"Y","N")) -> Y | AI88: =IF(X88="","",IF(X88>=Control!$D$9,"Y","N")) -> N | AK88: =IFERROR(INDEX(Assumptions!$D$92:$D$115,MATCH(C88,Assumptions!$B$92:$B$115,0)),"Low") -> Low
B89: 86 | C89: AP | D89: Sri Sathya Sai | E89: =SUM(G89:I89) -> 0 | F89: =SUMIFS('CBG Plants'!N:N,'CBG Plants'!F:F,D89,'CBG Plants'!L:L,"Completed") +SUMIFS('CBG Plants'!N:N,'CBG Plants'!F:F,D89,'CBG Plants'!L:L,"Functional")+SUMIFS('CBG Plants'!N:N,'CBG Plants'!F:F,D89,'CBG Plants'!L:L,"Under Construction")+SUMIFS('CBG Plants'!N:N,'CBG Plants'!F:F,D89,'CBG Plants'!L:L,"Yet to start construction") -> 0 | G89: =COUNTIFS('CBG Plants'!F:F,D89,'CBG Plants'!L:L,"Completed") +COUNTIFS('CBG Plants'!F:F,D89,'CBG Plants'!L:L,"Functional") -> 0 | H89: =COUNTIFS('CBG Plants'!F:F,D89,'CBG Plants'!L:L,"Under Construction") -> 0 | I89: =COUNTIFS('CBG Plants'!F:F,D89,'CBG Plants'!L:L,"Yet to start construction") -> 0 | M89: =IFERROR(N89-(AD89*365/1000),"") -> 74.34 | N89: =SUM(O89:Q89) -> 74.34 | O89: 0 | P89: 17.64 | Q89: 56.7 | R89: =IFERROR(U89-F89,"") -> 0 | S89: =IFERROR(T89*Assumptions!$C$4,"") -> 0 | T89: 0 | U89: =IFERROR(S89*Assumptions!$C$5,"")+IFERROR(V89*Assumptions!$C$8*Assumptions!$C$5,"") -> 0 | V89: 0 | W89: =IFERROR(ROUND(T89*(1+Assumptions!$C$7)^5,0),"") -> 0 | X89: =IFERROR(ROUND(W89*Assumptions!$C$4*Assumptions!$C$6,4),"")+IFERROR(ROUND(Y89*Assumptions!$C$8*Assumptions!$C$6,4),"") - F89 -> 0 | Y89: =IFERROR(ROUND(V89*(1+Assumptions!$C$7)^5,0),"") -> 0 | Z89: Operational Common Carrier | AA89: KG Basin Network | AB89: 543.4 | AC89: 16 | AD89: 0 | AE89: =IF(R89="","",IF(R89>=Control!$D$4,"Y","N")) -> N | AF89: =IF(S89="","",IF(M89>=Control!$D$5,"Y","N")) -> Y | AG89: =IF(T89="","",IF(AB89<=Control!$D$10,"Y","N")) -> Y | AI89: =IF(X89="","",IF(X89>=Control!$D$9,"Y","N")) -> N | AK89: =IFERROR(INDEX(Assumptions!$D$92:$D$115,MATCH(C89,Assumptions!$B$92:$B$115,0)),"Low") -> Low
B90: 87 | C90: AP | D90: Srikakulam | E90: =SUM(G90:I90) -> 6 | F90: =SUMIFS('CBG Plants'!N:N,'CBG Plants'!F:F,D90,'CBG Plants'!L:L,"Completed") +SUMIFS('CBG Plants'!N:N,'CBG Plants'!F:F,D90,'CBG Plants'!L:L,"Functional")+SUMIFS('CBG Plants'!N:N,'CBG Plants'!F:F,D90,'CBG Plants'!L:L,"Under Construction")+SUMIFS('CBG Plants'!N:N,'CBG Plants'!F:F,D90,'CBG Plants'!L:L,"Yet to start construction") -> 69 | G90: =COUNTIFS('CBG Plants'!F:F,D90,'CBG Plants'!L:L,"Completed") +COUNTIFS('CBG Plants'!F:F,D90,'CBG Plants'!L:L,"Functional") -> 0 | H90: =COUNTIFS('CBG Plants'!F:F,D90,'CBG Plants'!L:L,"Under Construction") -> 0 | I90: =COUNTIFS('CBG Plants'!F:F,D90,'CBG Plants'!L:L,"Yet to start construction") -> 6 | J90: SAM HOUSING AND INFRA PRIVATE LIMITED | K90: PVS RAMMOHAN INDUSTRIES PRIVATE LIMITED - UNIT 01 | L90: PVS RAMMOHAN INDUSTRIES PRIVATE LIMITED - UNIT 02 | M90: =IFERROR(N90-(AD90*365/1000),"") -> 294.63 | N90: =SUM(O90:Q90) -> 294.63 | O90: 0 | P90: 207.48 | Q90: 87.15 | R90: =IFERROR(U90-F90,"") -> -68.302377 | S90: =IFERROR(T90*Assumptions!$C$4,"") -> 22.5 | T90: 9 | U90: =IFERROR(S90*Assumptions!$C$5,"")+IFERROR(V90*Assumptions!$C$8*Assumptions!$C$5,"") -> 0.69762255 | V90: 2251 | W90: =IFERROR(ROUND(T90*(1+Assumptions!$C$7)^5,0),"") -> 27 | X90: =IFERROR(ROUND(W90*Assumptions!$C$4*Assumptions!$C$6,4),"")+IFERROR(ROUND(Y90*Assumptions!$C$8*Assumptions!$C$6,4),"") - F90 -> -65.5099 | Y90: =IFERROR(ROUND(V90*(1+Assumptions!$C$7)^5,0),"") -> 6870 | Z90: Operational Common Carrier | AA90: KG Basin Network | AB90: 265.4 | AC90: 16 | AD90: 0 | AE90: =IF(R90="","",IF(R90>=Control!$D$4,"Y","N")) -> N | AF90: =IF(S90="","",IF(M90>=Control!$D$5,"Y","N")) -> Y | AG90: =IF(T90="","",IF(AB90<=Control!$D$10,"Y","N")) -> Y | AI90: =IF(X90="","",IF(X90>=Control!$D$9,"Y","N")) -> N | AK90: =IFERROR(INDEX(Assumptions!$D$92:$D$115,MATCH(C90,Assumptions!$B$92:$B$115,0)),"Low") -> Low
B91: 88 | C91: AP | D91: Tirupati | E91: =SUM(G91:I91) -> 1 | F91: =SUMIFS('CBG Plants'!N:N,'CBG Plants'!F:F,D91,'CBG Plants'!L:L,"Completed") +SUMIFS('CBG Plants'!N:N,'CBG Plants'!F:F,D91,'CBG Plants'!L:L,"Functional")+SUMIFS('CBG Plants'!N:N,'CBG Plants'!F:F,D91,'CBG Plants'!L:L,"Under Construction")+SUMIFS('CBG Plants'!N:N,'CBG Plants'!F:F,D91,'CBG Plants'!L:L,"Yet to start construction") -> 2 | G91: =COUNTIFS('CBG Plants'!F:F,D91,'CBG Plants'!L:L,"Completed") +COUNTIFS('CBG Plants'!F:F,D91,'CBG Plants'!L:L,"Functional") -> 1 | H91: =COUNTIFS('CBG Plants'!F:F,D91,'CBG Plants'!L:L,"Under Construction") -> 0 | I91: =COUNTIFS('CBG Plants'!F:F,D91,'CBG Plants'!L:L,"Yet to start construction") -> 0 | J91: TIRUPATI PROJECT -50 TPD | M91: =IFERROR(N91-(AD91*365/1000),"") -> 136.31 | N91: =SUM(O91:Q91) -> 154.56 | O91: 0 | P91: 154.56 | Q91: 0 | R91: =IFERROR(U91-F91,"") -> -2 | S91: =IFERROR(T91*Assumptions!$C$4,"") -> 0 | T91: 0 | U91: =IFERROR(S91*Assumptions!$C$5,"")+IFERROR(V91*Assumptions!$C$8*Assumptions!$C$5,"") -> 0 | V91: 0 | W91: =IFERROR(ROUND(T91*(1+Assumptions!$C$7)^5,0),"") -> 0 | X91: =IFERROR(ROUND(W91*Assumptions!$C$4*Assumptions!$C$6,4),"")+IFERROR(ROUND(Y91*Assumptions!$C$8*Assumptions!$C$6,4),"") - F91 -> -2 | Y91: =IFERROR(ROUND(V91*(1+Assumptions!$C$7)^5,0),"") -> 0 | Z91: Operational Common Carrier | AA91: KG Basin Network | AB91: 403.1 | AC91: 16 | AD91: 50 | AE91: =IF(R91="","",IF(R91>=Control!$D$4,"Y","N")) -> N | AF91: =IF(S91="","",IF(M91>=Control!$D$5,"Y","N")) -> Y | AG91: =IF(T91="","",IF(AB91<=Control!$D$10,"Y","N")) -> Y | AI91: =IF(X91="","",IF(X91>=Control!$D$9,"Y","N")) -> N | AK91: =IFERROR(INDEX(Assumptions!$D$92:$D$115,MATCH(C91,Assumptions!$B$92:$B$115,0)),"Low") -> Low
B92: 89 | C92: AP | D92: Visakhapatnam | E92: =SUM(G92:I92) -> 2 | F92: =SUMIFS('CBG Plants'!N:N,'CBG Plants'!F:F,D92,'CBG Plants'!L:L,"Completed") +SUMIFS('CBG Plants'!N:N,'CBG Plants'!F:F,D92,'CBG Plants'!L:L,"Functional")+SUMIFS('CBG Plants'!N:N,'CBG Plants'!F:F,D92,'CBG Plants'!L:L,"Under Construction")+SUMIFS('CBG Plants'!N:N,'CBG Plants'!F:F,D92,'CBG Plants'!L:L,"Yet to start construction") -> 10.85 | G92: =COUNTIFS('CBG Plants'!F:F,D92,'CBG Plants'!L:L,"Completed") +COUNTIFS('CBG Plants'!F:F,D92,'CBG Plants'!L:L,"Functional") -> 1 | H92: =COUNTIFS('CBG Plants'!F:F,D92,'CBG Plants'!L:L,"Under Construction") -> 0 | I92: =COUNTIFS('CBG Plants'!F:F,D92,'CBG Plants'!L:L,"Yet to start construction") -> 1 | J92: Puresustain Energies Biocng plant | K92: Vyzag Bio Energy Fuel Pvt Ltd | M92: =IFERROR(N92-(AD92*365/1000),"") -> -1.815 | N92: =SUM(O92:Q92) -> 9.135 | O92: 0 | P92: 7.56 | Q92: 1.575 | R92: =IFERROR(U92-F92,"") -> -10.152377 | S92: =IFERROR(T92*Assumptions!$C$4,"") -> 22.5 | T92: 9 | U92: =IFERROR(S92*Assumptions!$C$5,"")+IFERROR(V92*Assumptions!$C$8*Assumptions!$C$5,"") -> 0.69762255 | V92: 2251 | W92: =IFERROR(ROUND(T92*(1+Assumptions!$C$7)^5,0),"") -> 27 | X92: =IFERROR(ROUND(W92*Assumptions!$C$4*Assumptions!$C$6,4),"")+IFERROR(ROUND(Y92*Assumptions!$C$8*Assumptions!$C$6,4),"") - F92 -> -7.3599 | Y92: =IFERROR(ROUND(V92*(1+Assumptions!$C$7)^5,0),"") -> 6870 | Z92: Operational Common Carrier | AA92: KG Basin Network | AB92: 143.9 | AC92: 16 | AD92: 30 | AE92: =IF(R92="","",IF(R92>=Control!$D$4,"Y","N")) -> N | AF92: =IF(S92="","",IF(M92>=Control!$D$5,"Y","N")) -> N | AG92: =IF(T92="","",IF(AB92<=Control!$D$10,"Y","N")) -> Y | AI92: =IF(X92="","",IF(X92>=Control!$D$9,"Y","N")) -> N | AK92: =IFERROR(INDEX(Assumptions!$D$92:$D$115,MATCH(C92,Assumptions!$B$92:$B$115,0)),"Low") -> Low
B93: 90 | C93: AP | D93: Vizianagaram | E93: =SUM(G93:I93) -> 3 | F93: =SUMIFS('CBG Plants'!N:N,'CBG Plants'!F:F,D93,'CBG Plants'!L:L,"Completed") +SUMIFS('CBG Plants'!N:N,'CBG Plants'!F:F,D93,'CBG Plants'!L:L,"Functional")+SUMIFS('CBG Plants'!N:N,'CBG Plants'!F:F,D93,'CBG Plants'!L:L,"Under Construction")+SUMIFS('CBG Plants'!N:N,'CBG Plants'!F:F,D93,'CBG Plants'!L:L,"Yet to start construction") -> 26 | G93: =COUNTIFS('CBG Plants'!F:F,D93,'CBG Plants'!L:L,"Completed") +COUNTIFS('CBG Plants'!F:F,D93,'CBG Plants'!L:L,"Functional") -> 0 | H93: =COUNTIFS('CBG Plants'!F:F,D93,'CBG Plants'!L:L,"Under Construction") -> 0 | I93: =COUNTIFS('CBG Plants'!F:F,D93,'CBG Plants'!L:L,"Yet to start construction") -> 3 | J93: AMRUTHA SHREE BIO-CNG PRIVATE LIMITED | K93: SRIKAR ENTERPRISES PRIVATE LIMITED | L93: Sree Veeranjaneya Green Energy (OPC) Private Limited | M93: =IFERROR(N93-(AD93*365/1000),"") -> 261.45 | N93: =SUM(O93:Q93) -> 261.45 | O93: 0 | P93: 151.2 | Q93: 110.25 | R93: =IFERROR(U93-F93,"") -> -25.302377 | S93: =IFERROR(T93*Assumptions!$C$4,"") -> 22.5 | T93: 9 | U93: =IFERROR(S93*Assumptions!$C$5,"")+IFERROR(V93*Assumptions!$C$8*Assumptions!$C$5,"") -> 0.69762255 | V93: 2251 | W93: =IFERROR(ROUND(T93*(1+Assumptions!$C$7)^5,0),"") -> 27 | X93: =IFERROR(ROUND(W93*Assumptions!$C$4*Assumptions!$C$6,4),"")+IFERROR(ROUND(Y93*Assumptions!$C$8*Assumptions!$C$6,4),"") - F93 -> -22.5099 | Y93: =IFERROR(ROUND(V93*(1+Assumptions!$C$7)^5,0),"") -> 6870 | Z93: Operational Common Carrier | AA93: KG Basin Network | AB93: 189 | AC93: 16 | AD93: 0 | AE93: =IF(R93="","",IF(R93>=Control!$D$4,"Y","N")) -> N | AF93: =IF(S93="","",IF(M93>=Control!$D$5,"Y","N")) -> Y | AG93: =IF(T93="","",IF(AB93<=Control!$D$10,"Y","N")) -> Y | AI93: =IF(X93="","",IF(X93>=Control!$D$9,"Y","N")) -> N | AK93: =IFERROR(INDEX(Assumptions!$D$92:$D$115,MATCH(C93,Assumptions!$B$92:$B$115,0)),"Low") -> Low
B94: 91 | C94: AP | D94: West Godavari | E94: =SUM(G94:I94) -> 0 | F94: =SUMIFS('CBG Plants'!N:N,'CBG Plants'!F:F,D94,'CBG Plants'!L:L,"Completed") +SUMIFS('CBG Plants'!N:N,'CBG Plants'!F:F,D94,'CBG Plants'!L:L,"Functional")+SUMIFS('CBG Plants'!N:N,'CBG Plants'!F:F,D94,'CBG Plants'!L:L,"Under Construction")+SUMIFS('CBG Plants'!N:N,'CBG Plants'!F:F,D94,'CBG Plants'!L:L,"Yet to start construction") -> 0 | G94: =COUNTIFS('CBG Plants'!F:F,D94,'CBG Plants'!L:L,"Completed") +COUNTIFS('CBG Plants'!F:F,D94,'CBG Plants'!L:L,"Functional") -> 0 | H94: =COUNTIFS('CBG Plants'!F:F,D94,'CBG Plants'!L:L,"Under Construction") -> 0 | I94: =COUNTIFS('CBG Plants'!F:F,D94,'CBG Plants'!L:L,"Yet to start construction") -> 0 | J94: AASMUK ENTERPRISES PRIVATE LIMITED | K94: Rajahmundry 2 CBG Plant | L94: Rajahmundry-1 CBG Plant | M94: =IFERROR(N94-(AD94*365/1000),"") -> 320.505 | N94: =SUM(O94:Q94) -> 342.405 | O94: 0 | P94: 341.88 | Q94: 0.525 | R94: =IFERROR(U94-F94,"") -> 1.7136655 | S94: =IFERROR(T94*Assumptions!$C$4,"") -> 40 | T94: 16 | U94: =IFERROR(S94*Assumptions!$C$5,"")+IFERROR(V94*Assumptions!$C$8*Assumptions!$C$5,"") -> 1.7136655 | V94: 51111 | W94: =IFERROR(ROUND(T94*(1+Assumptions!$C$7)^5,0),"") -> 49 | X94: =IFERROR(ROUND(W94*Assumptions!$C$4*Assumptions!$C$6,4),"")+IFERROR(ROUND(Y94*Assumptions!$C$8*Assumptions!$C$6,4),"") - F94 -> 8.7376 | Y94: =IFERROR(ROUND(V94*(1+Assumptions!$C$7)^5,0),"") -> 155978 | Z94: Operational Common Carrier | AA94: KG Basin Network | AB94: 67.7 | AC94: 16 | AD94: 60 | AE94: =IF(R94="","",IF(R94>=Control!$D$4,"Y","N")) -> N | AF94: =IF(S94="","",IF(M94>=Control!$D$5,"Y","N")) -> Y | AG94: =IF(T94="","",IF(AB94<=Control!$D$10,"Y","N")) -> Y | AI94: =IF(X94="","",IF(X94>=Control!$D$9,"Y","N")) -> N | AK94: =IFERROR(INDEX(Assumptions!$D$92:$D$115,MATCH(C94,Assumptions!$B$92:$B$115,0)),"Low") -> Low
B95: 92 | C95: AP | D95: Y.S.R. Kadapa | E95: =SUM(G95:I95) -> 0 | F95: =SUMIFS('CBG Plants'!N:N,'CBG Plants'!F:F,D95,'CBG Plants'!L:L,"Completed") +SUMIFS('CBG Plants'!N:N,'CBG Plants'!F:F,D95,'CBG Plants'!L:L,"Functional")+SUMIFS('CBG Plants'!N:N,'CBG Plants'!F:F,D95,'CBG Plants'!L:L,"Under Construction")+SUMIFS('CBG Plants'!N:N,'CBG Plants'!F:F,D95,'CBG Plants'!L:L,"Yet to start construction") -> 0 | G95: =COUNTIFS('CBG Plants'!F:F,D95,'CBG Plants'!L:L,"Completed") +COUNTIFS('CBG Plants'!F:F,D95,'CBG Plants'!L:L,"Functional") -> 0 | H95: =COUNTIFS('CBG Plants'!F:F,D95,'CBG Plants'!L:L,"Under Construction") -> 0 | I95: =COUNTIFS('CBG Plants'!F:F,D95,'CBG Plants'!L:L,"Yet to start construction") -> 0 | J95: BJ Gas pvt ltd | M95: =IFERROR(N95-(AD95*365/1000),"") -> 56.7 | N95: =SUM(O95:Q95) -> 56.7 | O95: 0 | P95: 48.3 | Q95: 8.4 | R95: =IFERROR(U95-F95,"") -> 0 | S95: =IFERROR(T95*Assumptions!$C$4,"") -> 0 | T95: 0 | U95: =IFERROR(S95*Assumptions!$C$5,"")+IFERROR(V95*Assumptions!$C$8*Assumptions!$C$5,"") -> 0 | V95: 0 | W95: =IFERROR(ROUND(T95*(1+Assumptions!$C$7)^5,0),"") -> 0 | X95: =IFERROR(ROUND(W95*Assumptions!$C$4*Assumptions!$C$6,4),"")+IFERROR(ROUND(Y95*Assumptions!$C$8*Assumptions!$C$6,4),"") - F95 -> 0 | Y95: =IFERROR(ROUND(V95*(1+Assumptions!$C$7)^5,0),"") -> 0 | Z95: Operational Common Carrier | AA95: KG Basin Network | AB95: 431.4 | AC95: 16 | AD95: 0 | AE95: =IF(R95="","",IF(R95>=Control!$D$4,"Y","N")) -> N | AF95: =IF(S95="","",IF(M95>=Control!$D$5,"Y","N")) -> Y | AG95: =IF(T95="","",IF(AB95<=Control!$D$10,"Y","N")) -> Y | AI95: =IF(X95="","",IF(X95>=Control!$D$9,"Y","N")) -> N | AK95: =IFERROR(INDEX(Assumptions!$D$92:$D$115,MATCH(C95,Assumptions!$B$92:$B$115,0)),"Low") -> Low
B96: 93 | C96: UP | D96: Agra | E96: =SUM(G96:I96) -> 2 | F96: =SUMIFS('CBG Plants'!N:N,'CBG Plants'!F:F,D96,'CBG Plants'!L:L,"Completed") +SUMIFS('CBG Plants'!N:N,'CBG Plants'!F:F,D96,'CBG Plants'!L:L,"Functional")+SUMIFS('CBG Plants'!N:N,'CBG Plants'!F:F,D96,'CBG Plants'!L:L,"Under Construction")+SUMIFS('CBG Plants'!N:N,'CBG Plants'!F:F,D96,'CBG Plants'!L:L,"Yet to start construction") -> 5 | G96: =COUNTIFS('CBG Plants'!F:F,D96,'CBG Plants'!L:L,"Completed") +COUNTIFS('CBG Plants'!F:F,D96,'CBG Plants'!L:L,"Functional") -> 0 | H96: =COUNTIFS('CBG Plants'!F:F,D96,'CBG Plants'!L:L,"Under Construction") -> 1 | I96: =COUNTIFS('CBG Plants'!F:F,D96,'CBG Plants'!L:L,"Yet to start construction") -> 1 | J96: CBG Plant Agra | K96: GARG GREEN GASES | M96: =IFERROR(N96-(AD96*365/1000),"") -> 257.265 | N96: =SUM(O96:Q96) -> 257.265 | O96: 234.9 | P96: 19.74 | Q96: 2.625 | R96: =IFERROR(U96-F96,"") -> -1.3449792 | S96: =IFERROR(T96*Assumptions!$C$4,"") -> 82.5 | T96: 33 | U96: =IFERROR(S96*Assumptions!$C$5,"")+IFERROR(V96*Assumptions!$C$8*Assumptions!$C$5,"") -> 3.6550208 | V96: 117415 | W96: =IFERROR(ROUND(T96*(1+Assumptions!$C$7)^5,0),"") -> 101 | X96: =IFERROR(ROUND(W96*Assumptions!$C$4*Assumptions!$C$6,4),"")+IFERROR(ROUND(Y96*Assumptions!$C$8*Assumptions!$C$6,4),"") - F96 -> 13.6269 | Y96: =IFERROR(ROUND(V96*(1+Assumptions!$C$7)^5,0),"") -> 358322 | Z96: Operational Common Carrier | AA96: Hazira-Vijaipur-Jagdishpur / HVJ | AB96: 98.9 | AC96: 111.3 | AD96: 0 | AE96: =IF(R96="","",IF(R96>=Control!$D$4,"Y","N")) -> N | AF96: =IF(S96="","",IF(M96>=Control!$D$5,"Y","N")) -> Y | AG96: =IF(T96="","",IF(AB96<=Control!$D$10,"Y","N")) -> Y | AI96: =IF(X96="","",IF(X96>=Control!$D$9,"Y","N")) -> Y | AK96: =IFERROR(INDEX(Assumptions!$D$92:$D$115,MATCH(C96,Assumptions!$B$92:$B$115,0)),"Low") -> High
